Workbook
Name inp_scenario: Inputs_Drivers!$C$4
Name inp_scen_idx: Inputs_Drivers!$C$5
Name inp_logos_ent: Inputs_Drivers!$C$9
Name inp_logos_mid: Inputs_Drivers!$C$10
Name inp_logo_growth: Inputs_Drivers!$C$11
Name inp_acv_ent: Inputs_Drivers!$C$13
Name inp_acv_mid: Inputs_Drivers!$C$14
Name inp_price_uplift: Inputs_Drivers!$C$15
Name inp_exp_ent: Inputs_Drivers!$C$17
Name inp_exp_mid: Inputs_Drivers!$C$18
Name inp_churn_ent: Inputs_Drivers!$C$19
Name inp_churn_mid: Inputs_Drivers!$C$20
Name inp_hires_rd: Inputs_Drivers!$C$22
Name inp_hires_sm: Inputs_Drivers!$C$23
Name inp_hires_ga: Inputs_Drivers!$C$24
Name inp_hires_cs: Inputs_Drivers!$C$25
Name inp_dso: Inputs_Drivers!$C$27
Name inp_model_start: Inputs_Drivers!$C$29
Name inp_arr_open_ent: Inputs_Drivers!$C$30
Name inp_arr_open_mid: Inputs_Drivers!$C$31
Name inp_cust_open_ent: Inputs_Drivers!$C$32
Name inp_cust_open_mid: Inputs_Drivers!$C$33
Name inp_open_cash: Inputs_Drivers!$C$34
Name inp_open_ar: Inputs_Drivers!$C$35
Name inp_open_ppe: Inputs_Drivers!$C$36
Name inp_open_ap: Inputs_Drivers!$C$37
Name inp_open_defrev_impl: Inputs_Drivers!$C$38
Name inp_heads_open_rd: Inputs_Drivers!$C$40
Name inp_heads_open_sm: Inputs_Drivers!$C$41
Name inp_heads_open_ga: Inputs_Drivers!$C$42
Name inp_heads_open_cs: Inputs_Drivers!$C$43
Name inp_sal_rd: Inputs_Drivers!$C$44
Name inp_sal_sm: Inputs_Drivers!$C$45
Name inp_sal_ga: Inputs_Drivers!$C$46
Name inp_sal_cs: Inputs_Drivers!$C$47
Name inp_merit: Inputs_Drivers!$C$48
Name inp_marketing_m: Inputs_Drivers!$C$50
Name inp_rd_other_m: Inputs_Drivers!$C$51
Name inp_ga_other_m: Inputs_Drivers!$C$52
Name inp_commission_pct: Inputs_Drivers!$C$53
Name inp_capitalise_commission: Inputs_Drivers!$C$54
Name inp_cc_life: Inputs_Drivers!$C$55
Name inp_open_cca: Inputs_Drivers!$C$56
Name inp_host_ent: Inputs_Drivers!$C$57
Name inp_host_mid: Inputs_Drivers!$C$58
Name inp_licence_pct: Inputs_Drivers!$C$59
Name inp_impl_fee_pct: Inputs_Drivers!$C$60
Name inp_services_cost_pct: Inputs_Drivers!$C$61
Name inp_v_logos: Inputs_Drivers!$C$63
Name inp_v_exp: Inputs_Drivers!$C$64
Name inp_v_churn: Inputs_Drivers!$C$65
Name inp_ma_syn_achieved: Inputs_Drivers!$C$66
Name inp_ma_include: Inputs_Drivers!$C$68
Name inp_ma_offer_mult: Inputs_Drivers!$C$69
Name inp_ma_debt: Inputs_Drivers!$C$70
Name inp_ma_loan_rate: Inputs_Drivers!$C$71
Name inp_ma_deal_cost_pct: Inputs_Drivers!$C$72
Name inp_ma_integration_total: Inputs_Drivers!$C$73
Name inp_ma_integration_months: Inputs_Drivers!$C$74
Name inp_ma_xsell_logos_m: Inputs_Drivers!$C$75

Sheet Cover
A1: Keel - SaaS operating model for Northgate Controls Ltd
A2: Synthetic data. A formula-driven FP&A model: ARR build, revenue recognition, three statements, SaaS unit economics.
A4: Master check | B4: =Checks!E46
A5: Live scenario | B5: =inp_scenario
A6: Units | B6: GBP thousands unless stated. 24 monthly periods from the model start date, FY1 and FY2 annual columns.
A7: Outlier warnings | B7: =chk_warnings&" series flagged for review (see Checks)"
A8: Colour convention | B8: Blue = typed input
B9: Black = formula
B10: Green = link to another tab
A12: Model map
A13: Inputs_Drivers | B13: Named inputs (inp_*). Scenario selector. Live scenario values | C13: Phase 1
A14: Inputs_Scenarios | B14: Base / Upside / Downside / Custom values | C14: Phase 1
A15: Rev_Build | B15: ARR waterfall and customers by segment | C15: Phase 1
A16: Rev_Rec | B16: Billings, ratable revenue, deferred revenue, receivables | C16: Phase 1
A17: Headcount_Opex | B17: Headcount, payroll, opex by function | C17: Phase 1
A18: COGS | B18: Hosting, licences, support; gross margin by stream | C18: Phase 1
A19: IS / BS / CF | B19: Integrated three statements (balance check on BS) | C19: Phase 1
A20: SaaS_Metrics | B20: ARR bridge, NRR, GRR, CAC, payback, LTV/CAC, burn multiple, runway, Rule of 40 | C20: Phase 1
A21: Checks | B21: Integrity tests and master flag | C21: Phase 1
A22: Contract_Costs | B22: Capitalised sales commission (IFRS 15), amortisation, S&M charge | C22: Phase 2
A23: Inputs_Budget, Budget_vs_Forecast | B23: Board budget as received; mapped variances and three bridges (ARR, revenue, EBITDA) | C23: Phase 2
A24: LT_Model | B24: Five-year view: years 1-2 linked, years 3-5 driver-based | C24: Phase 2
... A30: MA_Target, MA_Valuation, MA_PPA, MA_ProForma, MA_Returns | B30: Vaultline acquisition module | C30: Phase 3 (not built)
A32: Version log
A33: v0.1 | B33: Phase 1 MVP: ARR build, rev rec, opex, COGS, three statements, SaaS metrics, scenarios (Base/Upside/Downside/Custom), checks.
A34: v0.2 | B34: Phase 2: Contract_Costs, budget and variance bridges, LT_Model, Lever_Analysis, Sensitivity, Business_Review. Fixed FY opening-balance columns.
A35: v0.3 | B35: Phase 3: Vaultline acquisition module (MA_* tabs, Inputs_Comps), acquisition scenario drivers, deal outcome in the scenario snapshots.
A36: v0.4 | B36: Phase 4: global tolerance, sign / annual-column / range checks, outlier warnings (validation lives in validation/).
A37: v0.5 | B37: Phase 5: Outputs_Web contract (named out_* ranges, input registry), array formulas replaced by helper rows, named_ranges.json export.

Sheet Inputs_Drivers
A1: Inputs_Drivers - every named input the model (and later the website) reads
A2: Blue = typed input. Green = live value pulled from Inputs_Scenarios for the selected scenario.
A4: Scenario selector | C4: Base | F4: Pick Base, Upside, Downside or Custom.
A5: Scenario index | C5: =MATCH(inp_scenario,Inputs_Scenarios!$C$4:$F$4,0) | F5: Position of the selected scenario in Inputs_Scenarios (1-4).
A7: Driver | B7: Unit | C7: Value | D7: Min | E7: Max | F7: What it drives | G7: Out of range
A8: Growth
A9: New Enterprise logos per month | B9: #/mo | C9: =INDEX(Inputs_Scenarios!$C6:$F6,1,inp_scen_idx) | D9: 0 | E9: 15 | F9: New-logo ARR = logos x ACV. Biggest driver of ARR growth. | G9: =IF(OR(C9<D9,C9>E9),1,0)
A10: New Mid-market logos per month | B10: #/mo | C10: =INDEX(Inputs_Scenarios!$C7:$F7,1,inp_scen_idx) | D10: 0 | E10: 60 | F10: Volume engine for the Mid-market segment. | G10: =IF(OR(C10<D10,C10>E10),1,0)
A11: Annual growth in new-logo volume | B11: % p.a. | C11: =INDEX(Inputs_Scenarios!$C8:$F8,1,inp_scen_idx) | D11: -0.2 | E11: 0.5 | F11: Compounds monthly. Sales capacity proxy in the MVP. | G11: =IF(OR(C11<D11,C11>E11),1,0)
A12: Pricing
A13: Enterprise ACV (new logos) | B13: GBP k | C13: =INDEX(Inputs_Scenarios!$C10:$F10,1,inp_scen_idx) | D13: 50 | E13: 1000 | F13: Average annual contract value of a new Enterprise logo. | G13: =IF(OR(C13<D13,C13>E13),1,0)
A14: Mid-market ACV (new logos) | B14: GBP k | C14: =INDEX(Inputs_Scenarios!$C11:$F11,1,inp_scen_idx) | D14: 5 | E14: 100 | F14: Average annual contract value of a new Mid-market logo. | G14: =IF(OR(C14<D14,C14>E14),1,0)
A15: Annual price uplift on new-logo ACV | B15: % p.a. | C15: =INDEX(Inputs_Scenarios!$C12:$F12,1,inp_scen_idx) | D15: 0 | E15: 0.15 | F15: Applied from month 13, 25, ... to new-logo ACV. | G15: =IF(OR(C15<D15,C15>E15),1,0)
A16: Retention
A17: Enterprise annual expansion | B17: % of ARR | C17: =INDEX(Inputs_Scenarios!$C14:$F14,1,inp_scen_idx) | D17: 0 | E17: 0.5 | F17: Upsell / cross-sell on the existing Enterprise base. | G17: =IF(OR(C17<D17,C17>E17),1,0)
A18: Mid-market annual expansion | B18: % of ARR | C18: =INDEX(Inputs_Scenarios!$C15:$F15,1,inp_scen_idx) | D18: 0 | E18: 0.5 | F18: Upsell on the existing Mid-market base. | G18: =IF(OR(C18<D18,C18>E18),1,0)
A19: Enterprise annual gross churn | B19: % of ARR | C19: =INDEX(Inputs_Scenarios!$C16:$F16,1,inp_scen_idx) | D19: 0 | E19: 0.5 | F19: Lost ARR (incl. contraction) from existing Enterprise customers. | G19: =IF(OR(C19<D19,C19>E19),1,0)
A20: Mid-market annual gross churn | B20: % of ARR | C20: =INDEX(Inputs_Scenarios!$C17:$F17,1,inp_scen_idx) | D20: 0 | E20: 0.5 | F20: Lost ARR (incl. contraction) from existing Mid-market customers. | G20: =IF(OR(C20<D20,C20>E20),1,0)
A21: People (hiring plan)
A22: R&D net hires per month | B22: FTE/mo | C22: =INDEX(Inputs_Scenarios!$C19:$F19,1,inp_scen_idx) | D22: 0 | E22: 10 | F22: Drives R&D payroll. | G22: =IF(OR(C22<D22,C22>E22),1,0)
A23: Sales & Marketing net hires per month | B23: FTE/mo | C23: =INDEX(Inputs_Scenarios!$C20:$F20,1,inp_scen_idx) | D23: 0 | E23: 10 | F23: Drives S&M payroll and CAC. | G23: =IF(OR(C23<D23,C23>E23),1,0)
A24: G&A net hires per month | B24: FTE/mo | C24: =INDEX(Inputs_Scenarios!$C21:$F21,1,inp_scen_idx) | D24: 0 | E24: 5 | F24: Drives G&A payroll. | G24: =IF(OR(C24<D24,C24>E24),1,0)
A25: Customer Success net hires per month | B25: FTE/mo | C25: =INDEX(Inputs_Scenarios!$C22:$F22,1,inp_scen_idx) | D25: 0 | E25: 5 | F25: Drives support payroll in COGS. | G25: =IF(OR(C25<D25,C25>E25),1,0)
A26: Cash
A27: Customer payment terms (DSO) | B27: days | C27: =INDEX(Inputs_Scenarios!$C24:$F24,1,inp_scen_idx) | D27: 0 | E27: 90 | F27: Days to collect an invoice. Drives receivables and cash timing. | G27: =IF(OR(C27<D27,C27>E27),1,0)
A28: Timing and opening position (31 Dec before model start)
A29: Model start date (first forecast month) | B29: date | C29: 46388 | F29: Month 1 of the 24-month forecast.
A30: Opening ARR - Enterprise | B30: GBP k | C30: 26000 | D30: 0 | E30: 200000 | F30: Contracted ARR at the opening date. | G30: =IF(OR(C30<D30,C30>E30),1,0)
A31: Opening ARR - Mid-market | B31: GBP k | C31: 14000 | D31: 0 | E31: 200000 | F31: Contracted ARR at the opening date. | G31: =IF(OR(C31<D31,C31>E31),1,0)
A32: Opening customers - Enterprise | B32: # | C32: 130 | D32: 0 | E32: 5000 | F32: Logo count at the opening date. | G32: =IF(OR(C32<D32,C32>E32),1,0)
A33: Opening customers - Mid-market | B33: # | C33: 560 | D33: 0 | E33: 20000 | F33: Logo count at the opening date. | G33: =IF(OR(C33<D33,C33>E33),1,0)
A34: Opening cash | B34: GBP k | C34: 24000 | D34: 0 | E34: 500000 | F34: Cash at the opening date. | G34: =IF(OR(C34<D34,C34>E34),1,0)
A35: Opening trade receivables | B35: GBP k | C35: 5500 | D35: 0 | E35: 100000 | F35: About 1.5 months of billings. | G35: =IF(OR(C35<D35,C35>E35),1,0)
A36: Opening PP&E (net) | B36: GBP k | C36: 2500 | D36: 0 | E36: 100000 | F36: Net book value at the opening date. | G36: =IF(OR(C36<D36,C36>E36),1,0)
A37: Opening trade payables | B37: GBP k | C37: 1100 | D37: 0 | E37: 100000 | F37: About one month of non-payroll spend. | G37: =IF(OR(C37<D37,C37>E37),1,0)
A38: Opening deferred implementation revenue | B38: GBP k | C38: 0 | D38: 0 | E38: 10000 | F38: Subscription deferred revenue is derived from the billing history. | G38: =IF(OR(C38<D38,C38>E38),1,0)
A39: People (static)
A40: Opening headcount - R&D | B40: FTE | C40: 150 | D40: 0 | E40: 2000 | G40: =IF(OR(C40<D40,C40>E40),1,0)
A41: Opening headcount - Sales & Marketing | B41: FTE | C41: 130 | D41: 0 | E41: 2000 | G41: =IF(OR(C41<D41,C41>E41),1,0)
A42: Opening headcount - G&A | B42: FTE | C42: 50 | D42: 0 | E42: 2000 | G42: =IF(OR(C42<D42,C42>E42),1,0)
A43: Opening headcount - Customer Success | B43: FTE | C43: 70 | D43: 0 | E43: 2000 | G43: =IF(OR(C43<D43,C43>E43),1,0)
A44: Fully loaded cost per FTE - R&D | B44: GBP k p.a. | C44: 90 | D44: 30 | E44: 300 | F44: Salary + employer NI + pension + benefits. | G44: =IF(OR(C44<D44,C44>E44),1,0)
A45: Fully loaded cost per FTE - S&M | B45: GBP k p.a. | C45: 88 | D45: 30 | E45: 300 | F45: Excludes commission (modelled separately). | G45: =IF(OR(C45<D45,C45>E45),1,0)
A46: Fully loaded cost per FTE - G&A | B46: GBP k p.a. | C46: 75 | D46: 30 | E46: 300 | G46: =IF(OR(C46<D46,C46>E46),1,0)
A47: Fully loaded cost per FTE - Customer Success | B47: GBP k p.a. | C47: 65 | D47: 30 | E47: 300 | G47: =IF(OR(C47<D47,C47>E47),1,0)
A48: Annual pay rise (applied from month 13) | B48: % p.a. | C48: 0.035 | D48: 0 | E48: 0.15 | G48: =IF(OR(C48<D48,C48>E48),1,0)
A49: Costs
A50: Marketing programmes | B50: GBP k/mo | C50: 480 | D50: 0 | E50: 5000 | F50: Non-headcount S&M. | G50: =IF(OR(C50<D50,C50>E50),1,0)
A51: R&D non-headcount (tools, contractors) | B51: GBP k/mo | C51: 120 | D51: 0 | E51: 5000 | G51: =IF(OR(C51<D51,C51>E51),1,0)
A52: G&A non-headcount (rent, fees, insurance) | B52: GBP k/mo | C52: 320 | D52: 0 | E52: 5000 | G52: =IF(OR(C52<D52,C52>E52),1,0)
A53: Sales commission | B53: % of gross new ARR | C53: 0.1 | D53: 0 | E53: 0.3 | F53: Expensed as incurred in the MVP. Phase 2 capitalises it (IFRS 15 costs to obtain a contract). | G53: =IF(OR(C53<D53,C53>E53),1,0)
A54: Capitalise sales commission (1 = yes, 0 = expense) | B54: 1/0 | C54: 1 | D54: 0 | E54: 1 | F54: IFRS 15 incremental costs of obtaining a contract: capitalised and amortised instead of expensed. | G54: =IF(OR(C54<D54,C54>E54),1,0)
A55: Contract-cost amortisation (declining balance on opening asset) | B55: months | C55: 48 | D55: 6 | E55: 120 | F55: Amortisation = opening asset / this life. Approximates amortising over the expected customer life. | G55: =IF(OR(C55<D55,C55>E55),1,0)
A56: Opening capitalised contract costs | B56: GBP k | C56: 3000 | D56: 0 | E56: 50000 | F56: Asset balance at the opening date. | G56: =IF(OR(C56<D56,C56>E56),1,0)
A57: Hosting cost per Enterprise customer | B57: GBP k/mo | C57: 1.4 | D57: 0 | E57: 10 | G57: =IF(OR(C57<D57,C57>E57),1,0)
A58: Hosting cost per Mid-market customer | B58: GBP k/mo | C58: 0.3 | D58: 0 | E58: 5 | G58: =IF(OR(C58<D58,C58>E58),1,0)
A59: Third-party licences | B59: % of subscription revenue | C59: 0.02 | D59: 0 | E59: 0.2 | G59: =IF(OR(C59<D59,C59>E59),1,0)
A60: Implementation fee | B60: % of new Enterprise ACV | C60: 0.15 | D60: 0 | E60: 0.5 | F60: Separate performance obligation, billed at signing, recognised over 3 months. | G60: =IF(OR(C60<D60,C60>E60),1,0)
A61: Cost of delivering implementation | B61: % of implementation revenue | C61: 0.7 | D61: 0 | E61: 1.5 | G61: =IF(OR(C61<D61,C61>E61),1,0)
A62: Acquisition: Vaultline scenario drivers
A63: Vaultline new logos per month | B63: #/mo | C63: =INDEX(Inputs_Scenarios!$C26:$F26,1,inp_scen_idx) | D63: 0 | E63: 10 | F63: Vaultline's own growth engine, standalone. | G63: =IF(OR(C63<D63,C63>E63),1,0)
A64: Vaultline annual expansion | B64: % of ARR | C64: =INDEX(Inputs_Scenarios!$C27:$F27,1,inp_scen_idx) | D64: 0 | E64: 0.5 | G64: =IF(OR(C64<D64,C64>E64),1,0)
A65: Vaultline annual gross churn | B65: % of ARR | C65: =INDEX(Inputs_Scenarios!$C28:$F28,1,inp_scen_idx) | D65: 0 | E65: 0.5 | F65: Integration risk: customers leave after a change of control. | G65: =IF(OR(C65<D65,C65>E65),1,0)
A66: Synergies achieved | B66: % of plan | C66: =INDEX(Inputs_Scenarios!$C29:$F29,1,inp_scen_idx) | D66: 0 | E66: 2 | F66: Scales both revenue (cross-sell) and cost synergies. Integration costs are not scaled. | G66: =IF(OR(C66<D66,C66>E66),1,0)
A67: Acquisition: deal terms
A68: Include acquisition in the pro-forma (1 = yes, 0 = no) | B68: 1/0 | C68: 1 | D68: 0 | E68: 1 | F68: 0 makes MA_ProForma equal Northgate standalone. | G68: =IF(OR(C68<D68,C68>E68),1,0)
A69: Offer: enterprise value / Vaultline opening ARR | B69: x ARR | C69: 4.5 | D69: 1 | E69: 12 | F69: Sets the offer price (EV). Equity price = EV + cash acquired (Vaultline has no debt). | G69: =IF(OR(C69<D69,C69>E69),1,0)
A70: Acquisition term loan | B70: GBP k | C70: 15000 | D70: 0 | E70: 100000 | F70: Bullet loan; balance of the equity price is paid from Northgate cash. | G70: =IF(OR(C70<D70,C70>E70),1,0)
A71: Acquisition loan interest rate | B71: % p.a. | C71: 0.08 | D71: 0 | E71: 0.25 | F71: Charged on the prior-period balance. | G71: =IF(OR(C71<D71,C71>E71),1,0)
A72: Transaction costs | B72: % of EV | C72: 0.02 | D72: 0 | E72: 0.1 | F72: Expensed in month 1 (IFRS 3.53). | G72: =IF(OR(C72<D72,C72>E72),1,0)
A73: Integration costs, total | B73: GBP k | C73: 3000 | D73: 0 | E73: 20000 | F73: One-off, spread evenly. | G73: =IF(OR(C73<D73,C73>E73),1,0)
A74: Integration period | B74: months | C74: 12 | D74: 1 | E74: 24 | F74: Costs spread evenly over this many months from month 1. | G74: =IF(OR(C74<D74,C74>E74),1,0)
A75: Cross-sell: Vaultline product sold to Northgate customers per month (at full ramp) | B75: #/mo | C75: 0.8 | D75: 0 | E75: 10 | F75: Revenue synergy volume. | G75: =IF(OR(C75<D75,C75>E75),1,0)
A76: Cross-sell ACV | B76: GBP k | C76: 45 | D76: 0 | E76: 500 | G76: =IF(OR(C76<D76,C76>E76),1,0)
A77: Synergies start in month | B77: month | C77: 7 | D77: 1 | E77: 24 | G77: =IF(OR(C77<D77,C77>E77),1,0)
A78: Synergy ramp-up | B78: months | C78: 6 | D78: 1 | E78: 24 | F78: Linear ramp from start to 100%. | G78: =IF(OR(C78<D78,C78>E78),1,0)
A79: Contribution margin on cross-sell revenue | B79: % | C79: 0.65 | D79: 0 | E79: 1 | F79: Revenue synergies are not free: they carry delivery and selling cost. | G79: =IF(OR(C79<D79,C79>E79),1,0)
A80: Cost synergies, annual run-rate | B80: GBP k p.a. | C80: 1200 | D80: 0 | E80: 20000 | F80: Duplicate G&A and hosting. | G80: =IF(OR(C80<D80,C80>E80),1,0)
A81: Intercompany contract: Northgate software sold to Vaultline | B81: GBP k p.a. | C81: 240 | D81: 0 | E81: 5000 | F81: Eliminated on consolidation (revenue and cost). | G81: =IF(OR(C81<D81,C81>E81),1,0)
A82: Acquisition: purchase price allocation (IFRS 3)
A83: Deferred revenue fair-value haircut | B83: % of book | C83: 0.3 | D83: 0 | E83: 0.8 | F83: IFRS 3 measures acquired deferred revenue at fair value; US GAAP (ASU 2021-08) carries it over at book. | G83: =IF(OR(C83<D83,C83>E83),1,0)
A84: Customer relationships | B84: % of EV | C84: 0.3 | D84: 0 | E84: 0.7 | F84: Illustrative; in practice from a valuation specialist (multi-period excess earnings). | G84: =IF(OR(C84<D84,C84>E84),1,0)
A85: Acquired technology | B85: % of EV | C85: 0.12 | D85: 0 | E85: 0.5 | F85: Illustrative (relief from royalty). | G85: =IF(OR(C85<D85,C85>E85),1,0)
A86: Customer relationships: useful life | B86: months | C86: 96 | D86: 24 | E86: 240 | G86: =IF(OR(C86<D86,C86>E86),1,0)
A87: Technology: useful life | B87: months | C87: 60 | D87: 24 | E87: 240 | G87: =IF(OR(C87<D87,C87>E87),1,0)
A88: Acquisition: valuation
A89: Discount rate (WACC) | B89: % | C89: 0.115 | D89: 0.05 | E89: 0.25 | F89: Applied to Vaultline cash flows and synergies. | G89: =IF(OR(C89<D89,C89>E89),1,0)
A90: Terminal growth | B90: % | C90: 0.03 | D90: 0 | E90: 0.06 | F90: Must be below WACC. | G90: =IF(OR(C90<D90,C90>E90),1,0)
A91: DCF sensitivity band on WACC (low / high cases) | B91: pts | C91: 0.01 | D91: 0 | E91: 0.05 | F91: Low case = WACC + band; high case = WACC - band. | G91: =IF(OR(C91<D91,C91>E91),1,0)
A92: DCF sensitivity band on terminal growth | B92: pts | C92: 0.005 | D92: 0 | E92: 0.02 | F92: Low case = growth - band; high case = growth + band. | G92: =IF(OR(C92<D92,C92>E92),1,0)
A93: Vaultline ARR growth fade, years 3-5 | B93: pts p.a. | C93: 0.03 | D93: 0 | E93: 0.2 | F93: Growth falls by this much each year after year 2. | G93: =IF(OR(C93<D93,C93>E93),1,0)
A94: Acquisition: Vaultline standalone (opening position and cost structure)
A95: Vaultline opening ARR | B95: GBP k | C95: 6000 | D95: 0 | E95: 100000 | G95: =IF(OR(C95<D95,C95>E95),1,0)
A96: Vaultline opening customers | B96: # | C96: 150 | D96: 0 | E96: 5000 | G96: =IF(OR(C96<D96,C96>E96),1,0)
A97: Vaultline ACV of new customers | B97: GBP k | C97: 42 | D97: 1 | E97: 500 | G97: =IF(OR(C97<D97,C97>E97),1,0)
A98: Vaultline cost of revenue | B98: % of revenue | C98: 0.2 | D98: 0 | E98: 1 | F98: Includes the intercompany software cost. | G98: =IF(OR(C98<D98,C98>E98),1,0)
A99: Vaultline R&D | B99: % of revenue | C99: 0.17 | D99: 0 | E99: 1 | G99: =IF(OR(C99<D99,C99>E99),1,0)
A100: Vaultline sales & marketing | B100: % of revenue | C100: 0.26 | D100: 0 | E100: 1 | G100: =IF(OR(C100<D100,C100>E100),1,0)
A101: Vaultline G&A | B101: % of revenue | C101: 0.12 | D101: 0 | E101: 1 | G101: =IF(OR(C101<D101,C101>E101),1,0)
A102: Vaultline payment terms (DSO) | B102: days | C102: 40 | D102: 0 | E102: 90 | G102: =IF(OR(C102<D102,C102>E102),1,0)
...

Sheet Inputs_Scenarios
A1: Inputs_Scenarios - scenario values for every scenario-driven input
A2: Blue cells are inputs. The live column on Inputs_Drivers picks one of these columns via the selector.
A4: Driver | B4: Unit | C4: Base | D4: Upside | E4: Downside | F4: Custom
A5: Growth
A6: New Enterprise logos per month | B6: #/mo | C6: 3 | D6: 3.6 | E6: 2.2 | F6: 3
A7: New Mid-market logos per month | B7: #/mo | C7: 14 | D7: 16 | E7: 10 | F7: 14
A8: Annual growth in new-logo volume | B8: % p.a. | C8: 0.05 | D8: 0.1 | E8: 0 | F8: 0.05
A9: Pricing
A10: Enterprise ACV (new logos) | B10: GBP k | C10: 210 | D10: 220 | E10: 195 | F10: 210
A11: Mid-market ACV (new logos) | B11: GBP k | C11: 26 | D11: 27 | E11: 23 | F11: 26
A12: Annual price uplift on new-logo ACV | B12: % p.a. | C12: 0.03 | D12: 0.04 | E12: 0.01 | F12: 0.03
A13: Retention
A14: Enterprise annual expansion | B14: % of ARR | C14: 0.14 | D14: 0.17 | E14: 0.09 | F14: 0.14
A15: Mid-market annual expansion | B15: % of ARR | C15: 0.07 | D15: 0.09 | E15: 0.04 | F15: 0.07
A16: Enterprise annual gross churn | B16: % of ARR | C16: 0.06 | D16: 0.05 | E16: 0.1 | F16: 0.06
A17: Mid-market annual gross churn | B17: % of ARR | C17: 0.12 | D17: 0.1 | E17: 0.18 | F17: 0.12
A18: People (hiring plan)
A19: R&D net hires per month | B19: FTE/mo | C19: 2.5 | D19: 3 | E19: 1 | F19: 2.5
A20: Sales & Marketing net hires per month | B20: FTE/mo | C20: 3 | D20: 4 | E20: 1 | F20: 3
A21: G&A net hires per month | B21: FTE/mo | C21: 0.8 | D21: 1 | E21: 0.3 | F21: 0.8
A22: Customer Success net hires per month | B22: FTE/mo | C22: 1.5 | D22: 2 | E22: 0.8 | F22: 1.5
A23: Cash
A24: Customer payment terms (DSO) | B24: days | C24: 45 | D24: 40 | E24: 60 | F24: 45
A25: Acquisition: Vaultline scenario drivers
A26: Vaultline new logos per month | B26: #/mo | C26: 1.6 | D26: 2 | E26: 1 | F26: 1.6
A27: Vaultline annual expansion | B27: % of ARR | C27: 0.08 | D27: 0.1 | E27: 0.05 | F27: 0.08
A28: Vaultline annual gross churn | B28: % of ARR | C28: 0.06 | D28: 0.05 | E28: 0.12 | F28: 0.06
A29: Synergies achieved | B29: % of plan | C29: 1 | D29: 1.2 | E29: 0.4 | F29: 1

Sheet Rev_Build
A1: Rev_Build - ARR waterfall and customers by segment
A2: GBP thousands unless stated. Blue = input, black = formula, green = link to another tab.
A3: Period # | C3: =COLUMN()-COLUMN($N$1) | D3: =COLUMN()-COLUMN($N$1) | E3: =COLUMN()-COLUMN($N$1) | F3: =COLUMN()-COLUMN($N$1) | G3: =COLUMN()-COLUMN($N$1) | H3: =COLUMN()-COLUMN($N$1) | I3: =COLUMN()-COLUMN($N$1) | J3: =COLUMN()-COLUMN($N$1) | ... AL3: =COLUMN()-COLUMN($N$1) | AN3: Annual | AO3: Annual
A4: Period ending | C4: =EOMONTH(inp_model_start,C3-1) | D4: =EOMONTH(inp_model_start,D3-1) | E4: =EOMONTH(inp_model_start,E3-1) | F4: =EOMONTH(inp_model_start,F3-1) | G4: =EOMONTH(inp_model_start,G3-1) | H4: =EOMONTH(inp_model_start,H3-1) | I4: =EOMONTH(inp_model_start,I3-1) | J4: =EOMONTH(inp_model_start,J3-1) | ... AL4: =EOMONTH(inp_model_start,AL3-1) | AN4: ="FY"&(YEAR(inp_model_start)+AN5-1) | AO4: ="FY"&(YEAR(inp_model_start)+AO5-1)
A5: Year | C5: =IF(C3<1,0,ROUNDUP(C3/12,0)) | D5: =IF(D3<1,0,ROUNDUP(D3/12,0)) | E5: =IF(E3<1,0,ROUNDUP(E3/12,0)) | F5: =IF(F3<1,0,ROUNDUP(F3/12,0)) | G5: =IF(G3<1,0,ROUNDUP(G3/12,0)) | H5: =IF(H3<1,0,ROUNDUP(H3/12,0)) | I5: =IF(I3<1,0,ROUNDUP(I3/12,0)) | J5: =IF(J3<1,0,ROUNDUP(J3/12,0)) | ... AL5: =IF(AL3<1,0,ROUNDUP(AL3/12,0)) | AN5: =COLUMN()-COLUMN($AM$1) | AO5: =COLUMN()-COLUMN($AM$1)
A6: Quarter | C6: =IF(C3<1,0,ROUNDUP(C3/3,0)) | D6: =IF(D3<1,0,ROUNDUP(D3/3,0)) | E6: =IF(E3<1,0,ROUNDUP(E3/3,0)) | F6: =IF(F3<1,0,ROUNDUP(F3/3,0)) | G6: =IF(G3<1,0,ROUNDUP(G3/3,0)) | H6: =IF(H3<1,0,ROUNDUP(H3/3,0)) | I6: =IF(I3<1,0,ROUNDUP(I3/3,0)) | J6: =IF(J3<1,0,ROUNDUP(J3/3,0)) | ... AL6: =IF(AL3<1,0,ROUNDUP(AL3/3,0))
A8: Volume and price drivers
A9: ACV price factor | B9: x | O9: =(1+inp_price_uplift)^(O$5-1) | P9: =(1+inp_price_uplift)^(P$5-1) | Q9: =(1+inp_price_uplift)^(Q$5-1) | R9: =(1+inp_price_uplift)^(R$5-1) | S9: =(1+inp_price_uplift)^(S$5-1) | T9: =(1+inp_price_uplift)^(T$5-1) | U9: =(1+inp_price_uplift)^(U$5-1) | V9: =(1+inp_price_uplift)^(V$5-1) | ... AL9: =(1+inp_price_uplift)^(AL$5-1) | AN9: =INDEX($O9:$AL9,1,AN$5*12) | AO9: =INDEX($O9:$AL9,1,AO$5*12)
A10: New-logo volume factor | B10: x | O10: =(1+inp_logo_growth)^((O$3-1)/12) | P10: =(1+inp_logo_growth)^((P$3-1)/12) | Q10: =(1+inp_logo_growth)^((Q$3-1)/12) | R10: =(1+inp_logo_growth)^((R$3-1)/12) | S10: =(1+inp_logo_growth)^((S$3-1)/12) | T10: =(1+inp_logo_growth)^((T$3-1)/12) | U10: =(1+inp_logo_growth)^((U$3-1)/12) | V10: =(1+inp_logo_growth)^((V$3-1)/12) | ... AL10: =(1+inp_logo_growth)^((AL$3-1)/12) | AN10: =INDEX($O10:$AL10,1,AN$5*12) | AO10: =INDEX($O10:$AL10,1,AO$5*12)
A11: New logos - Enterprise | B11: # | O11: =inp_logos_ent*O10 | P11: =inp_logos_ent*P10 | Q11: =inp_logos_ent*Q10 | R11: =inp_logos_ent*R10 | S11: =inp_logos_ent*S10 | T11: =inp_logos_ent*T10 | U11: =inp_logos_ent*U10 | V11: =inp_logos_ent*V10 | ... AL11: =inp_logos_ent*AL10 | AN11: =SUMIF($O$5:$AL$5,AN$5,$O11:$AL11) | AO11: =SUMIF($O$5:$AL$5,AO$5,$O11:$AL11)
A12: ACV of new logos - Enterprise | B12: GBP k | O12: =inp_acv_ent*O9 | P12: =inp_acv_ent*P9 | Q12: =inp_acv_ent*Q9 | R12: =inp_acv_ent*R9 | S12: =inp_acv_ent*S9 | T12: =inp_acv_ent*T9 | U12: =inp_acv_ent*U9 | V12: =inp_acv_ent*V9 | ... AL12: =inp_acv_ent*AL9 | AN12: =INDEX($O12:$AL12,1,AN$5*12) | AO12: =INDEX($O12:$AL12,1,AO$5*12)
A13: Monthly gross churn rate - Enterprise | B13: %/mo | O13: =1-(1-inp_churn_ent)^(1/12) | P13: =1-(1-inp_churn_ent)^(1/12) | Q13: =1-(1-inp_churn_ent)^(1/12) | R13: =1-(1-inp_churn_ent)^(1/12) | S13: =1-(1-inp_churn_ent)^(1/12) | T13: =1-(1-inp_churn_ent)^(1/12) | U13: =1-(1-inp_churn_ent)^(1/12) | V13: =1-(1-inp_churn_ent)^(1/12) | ... AL13: =1-(1-inp_churn_ent)^(1/12) | AN13: =INDEX($O13:$AL13,1,AN$5*12) | AO13: =INDEX($O13:$AL13,1,AO$5*12)
A14: Monthly expansion rate - Enterprise | B14: %/mo | O14: =(1+inp_exp_ent)^(1/12)-1 | P14: =(1+inp_exp_ent)^(1/12)-1 | Q14: =(1+inp_exp_ent)^(1/12)-1 | R14: =(1+inp_exp_ent)^(1/12)-1 | S14: =(1+inp_exp_ent)^(1/12)-1 | T14: =(1+inp_exp_ent)^(1/12)-1 | U14: =(1+inp_exp_ent)^(1/12)-1 | V14: =(1+inp_exp_ent)^(1/12)-1 | ... AL14: =(1+inp_exp_ent)^(1/12)-1 | AN14: =INDEX($O14:$AL14,1,AN$5*12) | AO14: =INDEX($O14:$AL14,1,AO$5*12)
A15: New logos - Mid-market | B15: # | O15: =inp_logos_mid*O10 | P15: =inp_logos_mid*P10 | Q15: =inp_logos_mid*Q10 | R15: =inp_logos_mid*R10 | S15: =inp_logos_mid*S10 | T15: =inp_logos_mid*T10 | U15: =inp_logos_mid*U10 | V15: =inp_logos_mid*V10 | ... AL15: =inp_logos_mid*AL10 | AN15: =SUMIF($O$5:$AL$5,AN$5,$O15:$AL15) | AO15: =SUMIF($O$5:$AL$5,AO$5,$O15:$AL15)
A16: ACV of new logos - Mid-market | B16: GBP k | O16: =inp_acv_mid*O9 | P16: =inp_acv_mid*P9 | Q16: =inp_acv_mid*Q9 | R16: =inp_acv_mid*R9 | S16: =inp_acv_mid*S9 | T16: =inp_acv_mid*T9 | U16: =inp_acv_mid*U9 | V16: =inp_acv_mid*V9 | ... AL16: =inp_acv_mid*AL9 | AN16: =INDEX($O16:$AL16,1,AN$5*12) | AO16: =INDEX($O16:$AL16,1,AO$5*12)
A17: Monthly gross churn rate - Mid-market | B17: %/mo | O17: =1-(1-inp_churn_mid)^(1/12) | P17: =1-(1-inp_churn_mid)^(1/12) | Q17: =1-(1-inp_churn_mid)^(1/12) | R17: =1-(1-inp_churn_mid)^(1/12) | S17: =1-(1-inp_churn_mid)^(1/12) | T17: =1-(1-inp_churn_mid)^(1/12) | U17: =1-(1-inp_churn_mid)^(1/12) | V17: =1-(1-inp_churn_mid)^(1/12) | ... AL17: =1-(1-inp_churn_mid)^(1/12) | AN17: =INDEX($O17:$AL17,1,AN$5*12) | AO17: =INDEX($O17:$AL17,1,AO$5*12)
A18: Monthly expansion rate - Mid-market | B18: %/mo | O18: =(1+inp_exp_mid)^(1/12)-1 | P18: =(1+inp_exp_mid)^(1/12)-1 | Q18: =(1+inp_exp_mid)^(1/12)-1 | R18: =(1+inp_exp_mid)^(1/12)-1 | S18: =(1+inp_exp_mid)^(1/12)-1 | T18: =(1+inp_exp_mid)^(1/12)-1 | U18: =(1+inp_exp_mid)^(1/12)-1 | V18: =(1+inp_exp_mid)^(1/12)-1 | ... AL18: =(1+inp_exp_mid)^(1/12)-1 | AN18: =INDEX($O18:$AL18,1,AN$5*12) | AO18: =INDEX($O18:$AL18,1,AO$5*12)
A20: ARR waterfall - Enterprise
A21: Opening ARR | B21: GBP k | O21: =N25 | P21: =O25 | Q21: =P25 | R21: =Q25 | S21: =R25 | T21: =S25 | U21: =T25 | V21: =U25 | ... AL21: =AK25 | AN21: =INDEX($O21:$AL21,1,(AN$5-1)*12+1) | AO21: =INDEX($O21:$AL21,1,(AO$5-1)*12+1)
A22: + New logos | B22: GBP k | O22: =O11*O12 | P22: =P11*P12 | Q22: =Q11*Q12 | R22: =R11*R12 | S22: =S11*S12 | T22: =T11*T12 | U22: =U11*U12 | V22: =V11*V12 | ... AL22: =AL11*AL12 | AN22: =SUMIF($O$5:$AL$5,AN$5,$O22:$AL22) | AO22: =SUMIF($O$5:$AL$5,AO$5,$O22:$AL22)
A23: + Expansion | B23: GBP k | O23: =O21*O14 | P23: =P21*P14 | Q23: =Q21*Q14 | R23: =R21*R14 | S23: =S21*S14 | T23: =T21*T14 | U23: =U21*U14 | V23: =V21*V14 | ... AL23: =AL21*AL14 | AN23: =SUMIF($O$5:$AL$5,AN$5,$O23:$AL23) | AO23: =SUMIF($O$5:$AL$5,AO$5,$O23:$AL23)
A24: - Churn | B24: GBP k | O24: =-O21*O13 | P24: =-P21*P13 | Q24: =-Q21*Q13 | R24: =-R21*R13 | S24: =-S21*S13 | T24: =-T21*T13 | U24: =-U21*U13 | V24: =-V21*V13 | ... AL24: =-AL21*AL13 | AN24: =SUMIF($O$5:$AL$5,AN$5,$O24:$AL24) | AO24: =SUMIF($O$5:$AL$5,AO$5,$O24:$AL24)
A25: Closing ARR | B25: GBP k | N25: =inp_arr_open_ent | O25: =SUM(O21:O24) | P25: =SUM(P21:P24) | Q25: =SUM(Q21:Q24) | R25: =SUM(R21:R24) | S25: =SUM(S21:S24) | T25: =SUM(T21:T24) | U25: =SUM(U21:U24) | V25: =SUM(V21:V24) | ... AL25: =SUM(AL21:AL24) | AN25: =INDEX($O25:$AL25,1,AN$5*12) | AO25: =INDEX($O25:$AL25,1,AO$5*12)
A26: Opening customers | B26: # | O26: =N29 | P26: =O29 | Q26: =P29 | R26: =Q29 | S26: =R29 | T26: =S29 | U26: =T29 | V26: =U29 | ... AL26: =AK29 | AN26: =INDEX($O26:$AL26,1,(AN$5-1)*12+1) | AO26: =INDEX($O26:$AL26,1,(AO$5-1)*12+1)
A27: + New customers | B27: # | O27: =O11 | P27: =P11 | Q27: =Q11 | R27: =R11 | S27: =S11 | T27: =T11 | U27: =U11 | V27: =V11 | ... AL27: =AL11 | AN27: =SUMIF($O$5:$AL$5,AN$5,$O27:$AL27) | AO27: =SUMIF($O$5:$AL$5,AO$5,$O27:$AL27)
A28: - Churned customers | B28: # | O28: =-O26*O13 | P28: =-P26*P13 | Q28: =-Q26*Q13 | R28: =-R26*R13 | S28: =-S26*S13 | T28: =-T26*T13 | U28: =-U26*U13 | V28: =-V26*V13 | ... AL28: =-AL26*AL13 | AN28: =SUMIF($O$5:$AL$5,AN$5,$O28:$AL28) | AO28: =SUMIF($O$5:$AL$5,AO$5,$O28:$AL28)
A29: Closing customers | B29: # | N29: =inp_cust_open_ent | O29: =SUM(O26:O28) | P29: =SUM(P26:P28) | Q29: =SUM(Q26:Q28) | R29: =SUM(R26:R28) | S29: =SUM(S26:S28) | T29: =SUM(T26:T28) | U29: =SUM(U26:U28) | V29: =SUM(V26:V28) | ... AL29: =SUM(AL26:AL28) | AN29: =INDEX($O29:$AL29,1,AN$5*12) | AO29: =INDEX($O29:$AL29,1,AO$5*12)
A31: ARR waterfall - Mid-market
A32: Opening ARR | B32: GBP k | O32: =N36 | P32: =O36 | Q32: =P36 | R32: =Q36 | S32: =R36 | T32: =S36 | U32: =T36 | V32: =U36 | ... AL32: =AK36 | AN32: =INDEX($O32:$AL32,1,(AN$5-1)*12+1) | AO32: =INDEX($O32:$AL32,1,(AO$5-1)*12+1)
A33: + New logos | B33: GBP k | O33: =O15*O16 | P33: =P15*P16 | Q33: =Q15*Q16 | R33: =R15*R16 | S33: =S15*S16 | T33: =T15*T16 | U33: =U15*U16 | V33: =V15*V16 | ... AL33: =AL15*AL16 | AN33: =SUMIF($O$5:$AL$5,AN$5,$O33:$AL33) | AO33: =SUMIF($O$5:$AL$5,AO$5,$O33:$AL33)
A34: + Expansion | B34: GBP k | O34: =O32*O18 | P34: =P32*P18 | Q34: =Q32*Q18 | R34: =R32*R18 | S34: =S32*S18 | T34: =T32*T18 | U34: =U32*U18 | V34: =V32*V18 | ... AL34: =AL32*AL18 | AN34: =SUMIF($O$5:$AL$5,AN$5,$O34:$AL34) | AO34: =SUMIF($O$5:$AL$5,AO$5,$O34:$AL34)
A35: - Churn | B35: GBP k | O35: =-O32*O17 | P35: =-P32*P17 | Q35: =-Q32*Q17 | R35: =-R32*R17 | S35: =-S32*S17 | T35: =-T32*T17 | U35: =-U32*U17 | V35: =-V32*V17 | ... AL35: =-AL32*AL17 | AN35: =SUMIF($O$5:$AL$5,AN$5,$O35:$AL35) | AO35: =SUMIF($O$5:$AL$5,AO$5,$O35:$AL35)
A36: Closing ARR | B36: GBP k | N36: =inp_arr_open_mid | O36: =SUM(O32:O35) | P36: =SUM(P32:P35) | Q36: =SUM(Q32:Q35) | R36: =SUM(R32:R35) | S36: =SUM(S32:S35) | T36: =SUM(T32:T35) | U36: =SUM(U32:U35) | V36: =SUM(V32:V35) | ... AL36: =SUM(AL32:AL35) | AN36: =INDEX($O36:$AL36,1,AN$5*12) | AO36: =INDEX($O36:$AL36,1,AO$5*12)
A37: Opening customers | B37: # | O37: =N40 | P37: =O40 | Q37: =P40 | R37: =Q40 | S37: =R40 | T37: =S40 | U37: =T40 | V37: =U40 | ... AL37: =AK40 | AN37: =INDEX($O37:$AL37,1,(AN$5-1)*12+1) | AO37: =INDEX($O37:$AL37,1,(AO$5-1)*12+1)
A38: + New customers | B38: # | O38: =O15 | P38: =P15 | Q38: =Q15 | R38: =R15 | S38: =S15 | T38: =T15 | U38: =U15 | V38: =V15 | ... AL38: =AL15 | AN38: =SUMIF($O$5:$AL$5,AN$5,$O38:$AL38) | AO38: =SUMIF($O$5:$AL$5,AO$5,$O38:$AL38)
A39: - Churned customers | B39: # | O39: =-O37*O17 | P39: =-P37*P17 | Q39: =-Q37*Q17 | R39: =-R37*R17 | S39: =-S37*S17 | T39: =-T37*T17 | U39: =-U37*U17 | V39: =-V37*V17 | ... AL39: =-AL37*AL17 | AN39: =SUMIF($O$5:$AL$5,AN$5,$O39:$AL39) | AO39: =SUMIF($O$5:$AL$5,AO$5,$O39:$AL39)
A40: Closing customers | B40: # | N40: =inp_cust_open_mid | O40: =SUM(O37:O39) | P40: =SUM(P37:P39) | Q40: =SUM(Q37:Q39) | R40: =SUM(R37:R39) | S40: =SUM(S37:S39) | T40: =SUM(T37:T39) | U40: =SUM(U37:U39) | V40: =SUM(V37:V39) | ... AL40: =SUM(AL37:AL39) | AN40: =INDEX($O40:$AL40,1,AN$5*12) | AO40: =INDEX($O40:$AL40,1,AO$5*12)
A42: Total company
A43: Opening ARR | B43: GBP k | O43: =O21+O32 | P43: =P21+P32 | Q43: =Q21+Q32 | R43: =R21+R32 | S43: =S21+S32 | T43: =T21+T32 | U43: =U21+U32 | V43: =V21+V32 | ... AL43: =AL21+AL32 | AN43: =INDEX($O43:$AL43,1,(AN$5-1)*12+1) | AO43: =INDEX($O43:$AL43,1,(AO$5-1)*12+1)
A44: + New logos | B44: GBP k | O44: =O22+O33 | P44: =P22+P33 | Q44: =Q22+Q33 | R44: =R22+R33 | S44: =S22+S33 | T44: =T22+T33 | U44: =U22+U33 | V44: =V22+V33 | ... AL44: =AL22+AL33 | AN44: =SUMIF($O$5:$AL$5,AN$5,$O44:$AL44) | AO44: =SUMIF($O$5:$AL$5,AO$5,$O44:$AL44)
A45: + Expansion | B45: GBP k | O45: =O23+O34 | P45: =P23+P34 | Q45: =Q23+Q34 | R45: =R23+R34 | S45: =S23+S34 | T45: =T23+T34 | U45: =U23+U34 | V45: =V23+V34 | ... AL45: =AL23+AL34 | AN45: =SUMIF($O$5:$AL$5,AN$5,$O45:$AL45) | AO45: =SUMIF($O$5:$AL$5,AO$5,$O45:$AL45)
A46: - Churn | B46: GBP k | O46: =O24+O35 | P46: =P24+P35 | Q46: =Q24+Q35 | R46: =R24+R35 | S46: =S24+S35 | T46: =T24+T35 | U46: =U24+U35 | V46: =V24+V35 | ... AL46: =AL24+AL35 | AN46: =SUMIF($O$5:$AL$5,AN$5,$O46:$AL46) | AO46: =SUMIF($O$5:$AL$5,AO$5,$O46:$AL46)
A47: Closing ARR | B47: GBP k | N47: =N25+N36 | O47: =SUM(O43:O46) | P47: =SUM(P43:P46) | Q47: =SUM(Q43:Q46) | R47: =SUM(R43:R46) | S47: =SUM(S43:S46) | T47: =SUM(T43:T46) | U47: =SUM(U43:U46) | V47: =SUM(V43:V46) | ... AL47: =SUM(AL43:AL46) | AN47: =INDEX($O47:$AL47,1,AN$5*12) | AO47: =INDEX($O47:$AL47,1,AO$5*12)
A48: Opening customers | B48: # | O48: =O26+O37 | P48: =P26+P37 | Q48: =Q26+Q37 | R48: =R26+R37 | S48: =S26+S37 | T48: =T26+T37 | U48: =U26+U37 | V48: =V26+V37 | ... AL48: =AL26+AL37 | AN48: =INDEX($O48:$AL48,1,(AN$5-1)*12+1) | AO48: =INDEX($O48:$AL48,1,(AO$5-1)*12+1)
A49: + New customers | B49: # | O49: =O27+O38 | P49: =P27+P38 | Q49: =Q27+Q38 | R49: =R27+R38 | S49: =S27+S38 | T49: =T27+T38 | U49: =U27+U38 | V49: =V27+V38 | ... AL49: =AL27+AL38 | AN49: =SUMIF($O$5:$AL$5,AN$5,$O49:$AL49) | AO49: =SUMIF($O$5:$AL$5,AO$5,$O49:$AL49)
A50: - Churned customers | B50: # | O50: =O28+O39 | P50: =P28+P39 | Q50: =Q28+Q39 | R50: =R28+R39 | S50: =S28+S39 | T50: =T28+T39 | U50: =U28+U39 | V50: =V28+V39 | ... AL50: =AL28+AL39 | AN50: =SUMIF($O$5:$AL$5,AN$5,$O50:$AL50) | AO50: =SUMIF($O$5:$AL$5,AO$5,$O50:$AL50)
A51: Closing customers | B51: # | N51: =N29+N40 | O51: =SUM(O48:O50) | P51: =SUM(P48:P50) | Q51: =SUM(Q48:Q50) | R51: =SUM(R48:R50) | S51: =SUM(S48:S50) | T51: =SUM(T48:T50) | U51: =SUM(U48:U50) | V51: =SUM(V48:V50) | ... AL51: =SUM(AL48:AL50) | AN51: =INDEX($O51:$AL51,1,AN$5*12) | AO51: =INDEX($O51:$AL51,1,AO$5*12)

Sheet Rev_Rec
A1: Rev_Rec - billings, ratable revenue (IFRS 15) and deferred revenue
A2: GBP thousands unless stated. Blue = input, black = formula, green = link to another tab.
A3: Period # | C3: =COLUMN()-COLUMN($N$1) | D3: =COLUMN()-COLUMN($N$1) | E3: =COLUMN()-COLUMN($N$1) | F3: =COLUMN()-COLUMN($N$1) | G3: =COLUMN()-COLUMN($N$1) | H3: =COLUMN()-COLUMN($N$1) | I3: =COLUMN()-COLUMN($N$1) | J3: =COLUMN()-COLUMN($N$1) | ... AL3: =COLUMN()-COLUMN($N$1) | AN3: Annual | AO3: Annual
A4: Period ending | C4: =EOMONTH(inp_model_start,C3-1) | D4: =EOMONTH(inp_model_start,D3-1) | E4: =EOMONTH(inp_model_start,E3-1) | F4: =EOMONTH(inp_model_start,F3-1) | G4: =EOMONTH(inp_model_start,G3-1) | H4: =EOMONTH(inp_model_start,H3-1) | I4: =EOMONTH(inp_model_start,I3-1) | J4: =EOMONTH(inp_model_start,J3-1) | ... AL4: =EOMONTH(inp_model_start,AL3-1) | AN4: ="FY"&(YEAR(inp_model_start)+AN5-1) | AO4: ="FY"&(YEAR(inp_model_start)+AO5-1)
A5: Year | C5: =IF(C3<1,0,ROUNDUP(C3/12,0)) | D5: =IF(D3<1,0,ROUNDUP(D3/12,0)) | E5: =IF(E3<1,0,ROUNDUP(E3/12,0)) | F5: =IF(F3<1,0,ROUNDUP(F3/12,0)) | G5: =IF(G3<1,0,ROUNDUP(G3/12,0)) | H5: =IF(H3<1,0,ROUNDUP(H3/12,0)) | I5: =IF(I3<1,0,ROUNDUP(I3/12,0)) | J5: =IF(J3<1,0,ROUNDUP(J3/12,0)) | ... AL5: =IF(AL3<1,0,ROUNDUP(AL3/12,0)) | AN5: =COLUMN()-COLUMN($AM$1) | AO5: =COLUMN()-COLUMN($AM$1)
A6: Quarter | C6: =IF(C3<1,0,ROUNDUP(C3/3,0)) | D6: =IF(D3<1,0,ROUNDUP(D3/3,0)) | E6: =IF(E3<1,0,ROUNDUP(E3/3,0)) | F6: =IF(F3<1,0,ROUNDUP(F3/3,0)) | G6: =IF(G3<1,0,ROUNDUP(G3/3,0)) | H6: =IF(H3<1,0,ROUNDUP(H3/3,0)) | I6: =IF(I3<1,0,ROUNDUP(I3/3,0)) | J6: =IF(J3<1,0,ROUNDUP(J3/3,0)) | ... AL6: =IF(AL3<1,0,ROUNDUP(AL3/3,0))
A8: Subscription invoices raised (annual upfront). Columns C:N hold the opening-year billing history
A9: Invoices raised - Enterprise | B9: GBP k | C9: =inp_arr_open_ent/12 | D9: =inp_arr_open_ent/12 | E9: =inp_arr_open_ent/12 | F9: =inp_arr_open_ent/12 | G9: =inp_arr_open_ent/12 | H9: =inp_arr_open_ent/12 | I9: =inp_arr_open_ent/12 | J9: =inp_arr_open_ent/12 | ... N9: =inp_arr_open_ent/12 | O9: =Rev_Build!O22+(1+inp_exp_ent-inp_churn_ent)*C9 | P9: =Rev_Build!P22+(1+inp_exp_ent-inp_churn_ent)*D9 | Q9: =Rev_Build!Q22+(1+inp_exp_ent-inp_churn_ent)*E9 | R9: =Rev_Build!R22+(1+inp_exp_ent-inp_churn_ent)*F9 | S9: =Rev_Build!S22+(1+inp_exp_ent-inp_churn_ent)*G9 | T9: =Rev_Build!T22+(1+inp_exp_ent-inp_churn_ent)*H9 | U9: =Rev_Build!U22+(1+inp_exp_ent-inp_churn_ent)*I9 | V9: =Rev_Build!V22+(1+inp_exp_ent-inp_churn_ent)*J9 | ... AL9: =Rev_Build!AL22+(1+inp_exp_ent-inp_churn_ent)*Z9 | AN9: =SUMIF($O$5:$AL$5,AN$5,$O9:$AL9) | AO9: =SUMIF($O$5:$AL$5,AO$5,$O9:$AL9)
A10: Invoices raised - Mid-market | B10: GBP k | C10: =inp_arr_open_mid/12 | D10: =inp_arr_open_mid/12 | E10: =inp_arr_open_mid/12 | F10: =inp_arr_open_mid/12 | G10: =inp_arr_open_mid/12 | H10: =inp_arr_open_mid/12 | I10: =inp_arr_open_mid/12 | J10: =inp_arr_open_mid/12 | ... N10: =inp_arr_open_mid/12 | O10: =Rev_Build!O33+(1+inp_exp_mid-inp_churn_mid)*C10 | P10: =Rev_Build!P33+(1+inp_exp_mid-inp_churn_mid)*D10 | Q10: =Rev_Build!Q33+(1+inp_exp_mid-inp_churn_mid)*E10 | R10: =Rev_Build!R33+(1+inp_exp_mid-inp_churn_mid)*F10 | S10: =Rev_Build!S33+(1+inp_exp_mid-inp_churn_mid)*G10 | T10: =Rev_Build!T33+(1+inp_exp_mid-inp_churn_mid)*H10 | U10: =Rev_Build!U33+(1+inp_exp_mid-inp_churn_mid)*I10 | V10: =Rev_Build!V33+(1+inp_exp_mid-inp_churn_mid)*J10 | ... AL10: =Rev_Build!AL33+(1+inp_exp_mid-inp_churn_mid)*Z10 | AN10: =SUMIF($O$5:$AL$5,AN$5,$O10:$AL10) | AO10: =SUMIF($O$5:$AL$5,AO$5,$O10:$AL10)
A11: Total subscription invoices | B11: GBP k | C11: =C9+C10 | D11: =D9+D10 | E11: =E9+E10 | F11: =F9+F10 | G11: =G9+G10 | H11: =H9+H10 | I11: =I9+I10 | J11: =J9+J10 | ... AL11: =AL9+AL10 | AN11: =SUMIF($O$5:$AL$5,AN$5,$O11:$AL11) | AO11: =SUMIF($O$5:$AL$5,AO$5,$O11:$AL11)
A12: Unexpired share of each historic invoice at opening date | B12: x | C12: =(C$3+11)/12 | D12: =(D$3+11)/12 | E12: =(E$3+11)/12 | F12: =(F$3+11)/12 | G12: =(G$3+11)/12 | H12: =(H$3+11)/12 | I12: =(I$3+11)/12 | J12: =(J$3+11)/12 | ... N12: =(N$3+11)/12
A14: Implementation fees (separate performance obligation, recognised over 3 months)
A15: Implementation fees billed | B15: GBP k | O15: =inp_impl_fee_pct*Rev_Build!O22 | P15: =inp_impl_fee_pct*Rev_Build!P22 | Q15: =inp_impl_fee_pct*Rev_Build!Q22 | R15: =inp_impl_fee_pct*Rev_Build!R22 | S15: =inp_impl_fee_pct*Rev_Build!S22 | T15: =inp_impl_fee_pct*Rev_Build!T22 | U15: =inp_impl_fee_pct*Rev_Build!U22 | V15: =inp_impl_fee_pct*Rev_Build!V22 | ... AL15: =inp_impl_fee_pct*Rev_Build!AL22 | AN15: =SUMIF($O$5:$AL$5,AN$5,$O15:$AL15) | AO15: =SUMIF($O$5:$AL$5,AO$5,$O15:$AL15)
A17: Revenue recognised
A18: Subscription revenue - Enterprise (each invoice over 12 months) | B18: GBP k | O18: =SUM(D9:O9)/12 | P18: =SUM(E9:P9)/12 | Q18: =SUM(F9:Q9)/12 | R18: =SUM(G9:R9)/12 | S18: =SUM(H9:S9)/12 | T18: =SUM(I9:T9)/12 | U18: =SUM(J9:U9)/12 | V18: =SUM(K9:V9)/12 | ... AL18: =SUM(AA9:AL9)/12 | AN18: =SUMIF($O$5:$AL$5,AN$5,$O18:$AL18) | AO18: =SUMIF($O$5:$AL$5,AO$5,$O18:$AL18)
A19: Subscription revenue - Mid-market (each invoice over 12 months) | B19: GBP k | O19: =SUM(D10:O10)/12 | P19: =SUM(E10:P10)/12 | Q19: =SUM(F10:Q10)/12 | R19: =SUM(G10:R10)/12 | S19: =SUM(H10:S10)/12 | T19: =SUM(I10:T10)/12 | U19: =SUM(J10:U10)/12 | V19: =SUM(K10:V10)/12 | ... AL19: =SUM(AA10:AL10)/12 | AN19: =SUMIF($O$5:$AL$5,AN$5,$O19:$AL19) | AO19: =SUMIF($O$5:$AL$5,AO$5,$O19:$AL19)
A20: Total subscription revenue | B20: GBP k | O20: =O18+O19 | P20: =P18+P19 | Q20: =Q18+Q19 | R20: =R18+R19 | S20: =S18+S19 | T20: =T18+T19 | U20: =U18+U19 | V20: =V18+V19 | ... AL20: =AL18+AL19 | AN20: =SUMIF($O$5:$AL$5,AN$5,$O20:$AL20) | AO20: =SUMIF($O$5:$AL$5,AO$5,$O20:$AL20)
A21: Implementation revenue | B21: GBP k | O21: =SUM(M15:O15)/3 | P21: =SUM(N15:P15)/3 | Q21: =SUM(O15:Q15)/3 | R21: =SUM(P15:R15)/3 | S21: =SUM(Q15:S15)/3 | T21: =SUM(R15:T15)/3 | U21: =SUM(S15:U15)/3 | V21: =SUM(T15:V15)/3 | ... AL21: =SUM(AJ15:AL15)/3 | AN21: =SUMIF($O$5:$AL$5,AN$5,$O21:$AL21) | AO21: =SUMIF($O$5:$AL$5,AO$5,$O21:$AL21)
A22: Total revenue | B22: GBP k | O22: =O20+O21 | P22: =P20+P21 | Q22: =Q20+Q21 | R22: =R20+R21 | S22: =S20+S21 | T22: =T20+T21 | U22: =U20+U21 | V22: =V20+V21 | ... AL22: =AL20+AL21 | AN22: =SUMIF($O$5:$AL$5,AN$5,$O22:$AL22) | AO22: =SUMIF($O$5:$AL$5,AO$5,$O22:$AL22)
A23: Total billings | B23: GBP k | N23: =N11 | O23: =O11+O15 | P23: =P11+P15 | Q23: =Q11+Q15 | R23: =R11+R15 | S23: =S11+S15 | T23: =T11+T15 | U23: =U11+U15 | V23: =V11+V15 | ... AL23: =AL11+AL15 | AN23: =SUMIF($O$5:$AL$5,AN$5,$O23:$AL23) | AO23: =SUMIF($O$5:$AL$5,AO$5,$O23:$AL23)
A25: Deferred revenue roll-forward
A26: Subscription: opening | B26: GBP k | O26: =N29 | P26: =O29 | Q26: =P29 | R26: =Q29 | S26: =R29 | T26: =S29 | U26: =T29 | V26: =U29 | ... AL26: =AK29 | AN26: =INDEX($O26:$AL26,1,(AN$5-1)*12+1) | AO26: =INDEX($O26:$AL26,1,(AO$5-1)*12+1)
A27: + Invoices raised | B27: GBP k | O27: =O11 | P27: =P11 | Q27: =Q11 | R27: =R11 | S27: =S11 | T27: =T11 | U27: =U11 | V27: =V11 | ... AL27: =AL11 | AN27: =SUMIF($O$5:$AL$5,AN$5,$O27:$AL27) | AO27: =SUMIF($O$5:$AL$5,AO$5,$O27:$AL27)
A28: - Revenue recognised | B28: GBP k | O28: =-O20 | P28: =-P20 | Q28: =-Q20 | R28: =-R20 | S28: =-S20 | T28: =-T20 | U28: =-U20 | V28: =-V20 | ... AL28: =-AL20 | AN28: =SUMIF($O$5:$AL$5,AN$5,$O28:$AL28) | AO28: =SUMIF($O$5:$AL$5,AO$5,$O28:$AL28)
A29: Subscription: closing | B29: GBP k | N29: =SUMPRODUCT(C11:N11,C12:N12) | O29: =SUM(O26:O28) | P29: =SUM(P26:P28) | Q29: =SUM(Q26:Q28) | R29: =SUM(R26:R28) | S29: =SUM(S26:S28) | T29: =SUM(T26:T28) | U29: =SUM(U26:U28) | V29: =SUM(V26:V28) | ... AL29: =SUM(AL26:AL28) | AN29: =INDEX($O29:$AL29,1,AN$5*12) | AO29: =INDEX($O29:$AL29,1,AO$5*12)
A30: Implementation: opening | B30: GBP k | O30: =N33 | P30: =O33 | Q30: =P33 | R30: =Q33 | S30: =R33 | T30: =S33 | U30: =T33 | V30: =U33 | ... AL30: =AK33 | AN30: =INDEX($O30:$AL30,1,(AN$5-1)*12+1) | AO30: =INDEX($O30:$AL30,1,(AO$5-1)*12+1)
A31: + Fees billed | B31: GBP k | O31: =O15 | P31: =P15 | Q31: =Q15 | R31: =R15 | S31: =S15 | T31: =T15 | U31: =U15 | V31: =V15 | ... AL31: =AL15 | AN31: =SUMIF($O$5:$AL$5,AN$5,$O31:$AL31) | AO31: =SUMIF($O$5:$AL$5,AO$5,$O31:$AL31)
A32: - Revenue recognised | B32: GBP k | O32: =-O21 | P32: =-P21 | Q32: =-Q21 | R32: =-R21 | S32: =-S21 | T32: =-T21 | U32: =-U21 | V32: =-V21 | ... AL32: =-AL21 | AN32: =SUMIF($O$5:$AL$5,AN$5,$O32:$AL32) | AO32: =SUMIF($O$5:$AL$5,AO$5,$O32:$AL32)
A33: Implementation: closing | B33: GBP k | N33: =inp_open_defrev_impl | O33: =SUM(O30:O32) | P33: =SUM(P30:P32) | Q33: =SUM(Q30:Q32) | R33: =SUM(R30:R32) | S33: =SUM(S30:S32) | T33: =SUM(T30:T32) | U33: =SUM(U30:U32) | V33: =SUM(V30:V32) | ... AL33: =SUM(AL30:AL32) | AN33: =INDEX($O33:$AL33,1,AN$5*12) | AO33: =INDEX($O33:$AL33,1,AO$5*12)
A34: Total deferred revenue | B34: GBP k | N34: =N29+N33 | O34: =O29+O33 | P34: =P29+P33 | Q34: =Q29+Q33 | R34: =R29+R33 | S34: =S29+S33 | T34: =T29+T33 | U34: =U29+U33 | ... AL34: =AL29+AL33 | AN34: =INDEX($O34:$AL34,1,AN$5*12) | AO34: =INDEX($O34:$AL34,1,AO$5*12)
A36: Trade receivables (payment terms)
A37: Trade receivables | B37: GBP k | N37: =inp_open_ar | O37: =O23*MIN(1,inp_dso/30)+N23*MAX(0,MIN(1,(inp_dso-30)/30)) | P37: =P23*MIN(1,inp_dso/30)+O23*MAX(0,MIN(1,(inp_dso-30)/30)) | Q37: =Q23*MIN(1,inp_dso/30)+P23*MAX(0,MIN(1,(inp_dso-30)/30)) | R37: =R23*MIN(1,inp_dso/30)+Q23*MAX(0,MIN(1,(inp_dso-30)/30)) | S37: =S23*MIN(1,inp_dso/30)+R23*MAX(0,MIN(1,(inp_dso-30)/30)) | T37: =T23*MIN(1,inp_dso/30)+S23*MAX(0,MIN(1,(inp_dso-30)/30)) | U37: =U23*MIN(1,inp_dso/30)+T23*MAX(0,MIN(1,(inp_dso-30)/30)) | V37: =V23*MIN(1,inp_dso/30)+U23*MAX(0,MIN(1,(inp_dso-30)/30)) | ... AL37: =AL23*MIN(1,inp_dso/30)+AK23*MAX(0,MIN(1,(inp_dso-30)/30)) | AN37: =INDEX($O37:$AL37,1,AN$5*12) | AO37: =INDEX($O37:$AL37,1,AO$5*12)
A39: Memo
A40: Subscription revenue / (closing ARR / 12) | B40: % | O40: =O20/(Rev_Build!O47/12) | P40: =P20/(Rev_Build!P47/12) | Q40: =Q20/(Rev_Build!Q47/12) | R40: =R20/(Rev_Build!R47/12) | S40: =S20/(Rev_Build!S47/12) | T40: =T20/(Rev_Build!T47/12) | U40: =U20/(Rev_Build!U47/12) | V40: =V20/(Rev_Build!V47/12) | ... AL40: =AL20/(Rev_Build!AL47/12)

Sheet Headcount_Opex
A1: Headcount_Opex - headcount by function, payroll and non-headcount opex
A2: GBP thousands unless stated. Blue = input, black = formula, green = link to another tab.
A3: Period # | C3: =COLUMN()-COLUMN($N$1) | D3: =COLUMN()-COLUMN($N$1) | E3: =COLUMN()-COLUMN($N$1) | F3: =COLUMN()-COLUMN($N$1) | G3: =COLUMN()-COLUMN($N$1) | H3: =COLUMN()-COLUMN($N$1) | I3: =COLUMN()-COLUMN($N$1) | J3: =COLUMN()-COLUMN($N$1) | ... AL3: =COLUMN()-COLUMN($N$1) | AN3: Annual | AO3: Annual
A4: Period ending | C4: =EOMONTH(inp_model_start,C3-1) | D4: =EOMONTH(inp_model_start,D3-1) | E4: =EOMONTH(inp_model_start,E3-1) | F4: =EOMONTH(inp_model_start,F3-1) | G4: =EOMONTH(inp_model_start,G3-1) | H4: =EOMONTH(inp_model_start,H3-1) | I4: =EOMONTH(inp_model_start,I3-1) | J4: =EOMONTH(inp_model_start,J3-1) | ... AL4: =EOMONTH(inp_model_start,AL3-1) | AN4: ="FY"&(YEAR(inp_model_start)+AN5-1) | AO4: ="FY"&(YEAR(inp_model_start)+AO5-1)
A5: Year | C5: =IF(C3<1,0,ROUNDUP(C3/12,0)) | D5: =IF(D3<1,0,ROUNDUP(D3/12,0)) | E5: =IF(E3<1,0,ROUNDUP(E3/12,0)) | F5: =IF(F3<1,0,ROUNDUP(F3/12,0)) | G5: =IF(G3<1,0,ROUNDUP(G3/12,0)) | H5: =IF(H3<1,0,ROUNDUP(H3/12,0)) | I5: =IF(I3<1,0,ROUNDUP(I3/12,0)) | J5: =IF(J3<1,0,ROUNDUP(J3/12,0)) | ... AL5: =IF(AL3<1,0,ROUNDUP(AL3/12,0)) | AN5: =COLUMN()-COLUMN($AM$1) | AO5: =COLUMN()-COLUMN($AM$1)
A6: Quarter | C6: =IF(C3<1,0,ROUNDUP(C3/3,0)) | D6: =IF(D3<1,0,ROUNDUP(D3/3,0)) | E6: =IF(E3<1,0,ROUNDUP(E3/3,0)) | F6: =IF(F3<1,0,ROUNDUP(F3/3,0)) | G6: =IF(G3<1,0,ROUNDUP(G3/3,0)) | H6: =IF(H3<1,0,ROUNDUP(H3/3,0)) | I6: =IF(I3<1,0,ROUNDUP(I3/3,0)) | J6: =IF(J3<1,0,ROUNDUP(J3/3,0)) | ... AL6: =IF(AL3<1,0,ROUNDUP(AL3/3,0))
A8: Headcount - R&D
A9: Opening FTE | B9: FTE | O9: =N11 | P9: =O11 | Q9: =P11 | R9: =Q11 | S9: =R11 | T9: =S11 | U9: =T11 | V9: =U11 | ... AL9: =AK11 | AN9: =INDEX($O9:$AL9,1,(AN$5-1)*12+1) | AO9: =INDEX($O9:$AL9,1,(AO$5-1)*12+1)
A10: + Net hires | B10: FTE | O10: =inp_hires_rd | P10: =inp_hires_rd | Q10: =inp_hires_rd | R10: =inp_hires_rd | S10: =inp_hires_rd | T10: =inp_hires_rd | U10: =inp_hires_rd | V10: =inp_hires_rd | ... AL10: =inp_hires_rd | AN10: =SUMIF($O$5:$AL$5,AN$5,$O10:$AL10) | AO10: =SUMIF($O$5:$AL$5,AO$5,$O10:$AL10)
A11: Closing FTE | B11: FTE | N11: =inp_heads_open_rd | O11: =O9+O10 | P11: =P9+P10 | Q11: =Q9+Q10 | R11: =R9+R10 | S11: =S9+S10 | T11: =T9+T10 | U11: =U9+U10 | V11: =V9+V10 | ... AL11: =AL9+AL10 | AN11: =INDEX($O11:$AL11,1,AN$5*12) | AO11: =INDEX($O11:$AL11,1,AO$5*12)
A12: Payroll cost (average FTE x loaded cost / 12 x pay-rise factor) | B12: GBP k | O12: =(O9+O11)/2*inp_sal_rd/12*(1+inp_merit)^(O$5-1) | P12: =(P9+P11)/2*inp_sal_rd/12*(1+inp_merit)^(P$5-1) | Q12: =(Q9+Q11)/2*inp_sal_rd/12*(1+inp_merit)^(Q$5-1) | R12: =(R9+R11)/2*inp_sal_rd/12*(1+inp_merit)^(R$5-1) | S12: =(S9+S11)/2*inp_sal_rd/12*(1+inp_merit)^(S$5-1) | T12: =(T9+T11)/2*inp_sal_rd/12*(1+inp_merit)^(T$5-1) | U12: =(U9+U11)/2*inp_sal_rd/12*(1+inp_merit)^(U$5-1) | V12: =(V9+V11)/2*inp_sal_rd/12*(1+inp_merit)^(V$5-1) | ... AL12: =(AL9+AL11)/2*inp_sal_rd/12*(1+inp_merit)^(AL$5-1) | AN12: =SUMIF($O$5:$AL$5,AN$5,$O12:$AL12) | AO12: =SUMIF($O$5:$AL$5,AO$5,$O12:$AL12)
A14: Headcount - Sales & Marketing
A15: Opening FTE | B15: FTE | O15: =N17 | P15: =O17 | Q15: =P17 | R15: =Q17 | S15: =R17 | T15: =S17 | U15: =T17 | V15: =U17 | ... AL15: =AK17 | AN15: =INDEX($O15:$AL15,1,(AN$5-1)*12+1) | AO15: =INDEX($O15:$AL15,1,(AO$5-1)*12+1)
A16: + Net hires | B16: FTE | O16: =inp_hires_sm | P16: =inp_hires_sm | Q16: =inp_hires_sm | R16: =inp_hires_sm | S16: =inp_hires_sm | T16: =inp_hires_sm | U16: =inp_hires_sm | V16: =inp_hires_sm | ... AL16: =inp_hires_sm | AN16: =SUMIF($O$5:$AL$5,AN$5,$O16:$AL16) | AO16: =SUMIF($O$5:$AL$5,AO$5,$O16:$AL16)
A17: Closing FTE | B17: FTE | N17: =inp_heads_open_sm | O17: =O15+O16 | P17: =P15+P16 | Q17: =Q15+Q16 | R17: =R15+R16 | S17: =S15+S16 | T17: =T15+T16 | U17: =U15+U16 | V17: =V15+V16 | ... AL17: =AL15+AL16 | AN17: =INDEX($O17:$AL17,1,AN$5*12) | AO17: =INDEX($O17:$AL17,1,AO$5*12)
A18: Payroll cost (average FTE x loaded cost / 12 x pay-rise factor) | B18: GBP k | O18: =(O15+O17)/2*inp_sal_sm/12*(1+inp_merit)^(O$5-1) | P18: =(P15+P17)/2*inp_sal_sm/12*(1+inp_merit)^(P$5-1) | Q18: =(Q15+Q17)/2*inp_sal_sm/12*(1+inp_merit)^(Q$5-1) | R18: =(R15+R17)/2*inp_sal_sm/12*(1+inp_merit)^(R$5-1) | S18: =(S15+S17)/2*inp_sal_sm/12*(1+inp_merit)^(S$5-1) | T18: =(T15+T17)/2*inp_sal_sm/12*(1+inp_merit)^(T$5-1) | U18: =(U15+U17)/2*inp_sal_sm/12*(1+inp_merit)^(U$5-1) | V18: =(V15+V17)/2*inp_sal_sm/12*(1+inp_merit)^(V$5-1) | ... AL18: =(AL15+AL17)/2*inp_sal_sm/12*(1+inp_merit)^(AL$5-1) | AN18: =SUMIF($O$5:$AL$5,AN$5,$O18:$AL18) | AO18: =SUMIF($O$5:$AL$5,AO$5,$O18:$AL18)
A20: Headcount - G&A
A21: Opening FTE | B21: FTE | O21: =N23 | P21: =O23 | Q21: =P23 | R21: =Q23 | S21: =R23 | T21: =S23 | U21: =T23 | V21: =U23 | ... AL21: =AK23 | AN21: =INDEX($O21:$AL21,1,(AN$5-1)*12+1) | AO21: =INDEX($O21:$AL21,1,(AO$5-1)*12+1)
A22: + Net hires | B22: FTE | O22: =inp_hires_ga | P22: =inp_hires_ga | Q22: =inp_hires_ga | R22: =inp_hires_ga | S22: =inp_hires_ga | T22: =inp_hires_ga | U22: =inp_hires_ga | V22: =inp_hires_ga | ... AL22: =inp_hires_ga | AN22: =SUMIF($O$5:$AL$5,AN$5,$O22:$AL22) | AO22: =SUMIF($O$5:$AL$5,AO$5,$O22:$AL22)
A23: Closing FTE | B23: FTE | N23: =inp_heads_open_ga | O23: =O21+O22 | P23: =P21+P22 | Q23: =Q21+Q22 | R23: =R21+R22 | S23: =S21+S22 | T23: =T21+T22 | U23: =U21+U22 | V23: =V21+V22 | ... AL23: =AL21+AL22 | AN23: =INDEX($O23:$AL23,1,AN$5*12) | AO23: =INDEX($O23:$AL23,1,AO$5*12)
A24: Payroll cost (average FTE x loaded cost / 12 x pay-rise factor) | B24: GBP k | O24: =(O21+O23)/2*inp_sal_ga/12*(1+inp_merit)^(O$5-1) | P24: =(P21+P23)/2*inp_sal_ga/12*(1+inp_merit)^(P$5-1) | Q24: =(Q21+Q23)/2*inp_sal_ga/12*(1+inp_merit)^(Q$5-1) | R24: =(R21+R23)/2*inp_sal_ga/12*(1+inp_merit)^(R$5-1) | S24: =(S21+S23)/2*inp_sal_ga/12*(1+inp_merit)^(S$5-1) | T24: =(T21+T23)/2*inp_sal_ga/12*(1+inp_merit)^(T$5-1) | U24: =(U21+U23)/2*inp_sal_ga/12*(1+inp_merit)^(U$5-1) | V24: =(V21+V23)/2*inp_sal_ga/12*(1+inp_merit)^(V$5-1) | ... AL24: =(AL21+AL23)/2*inp_sal_ga/12*(1+inp_merit)^(AL$5-1) | AN24: =SUMIF($O$5:$AL$5,AN$5,$O24:$AL24) | AO24: =SUMIF($O$5:$AL$5,AO$5,$O24:$AL24)
A26: Headcount - Customer Success
A27: Opening FTE | B27: FTE | O27: =N29 | P27: =O29 | Q27: =P29 | R27: =Q29 | S27: =R29 | T27: =S29 | U27: =T29 | V27: =U29 | ... AL27: =AK29 | AN27: =INDEX($O27:$AL27,1,(AN$5-1)*12+1) | AO27: =INDEX($O27:$AL27,1,(AO$5-1)*12+1)
A28: + Net hires | B28: FTE | O28: =inp_hires_cs | P28: =inp_hires_cs | Q28: =inp_hires_cs | R28: =inp_hires_cs | S28: =inp_hires_cs | T28: =inp_hires_cs | U28: =inp_hires_cs | V28: =inp_hires_cs | ... AL28: =inp_hires_cs | AN28: =SUMIF($O$5:$AL$5,AN$5,$O28:$AL28) | AO28: =SUMIF($O$5:$AL$5,AO$5,$O28:$AL28)
A29: Closing FTE | B29: FTE | N29: =inp_heads_open_cs | O29: =O27+O28 | P29: =P27+P28 | Q29: =Q27+Q28 | R29: =R27+R28 | S29: =S27+S28 | T29: =T27+T28 | U29: =U27+U28 | V29: =V27+V28 | ... AL29: =AL27+AL28 | AN29: =INDEX($O29:$AL29,1,AN$5*12) | AO29: =INDEX($O29:$AL29,1,AO$5*12)
A30: Payroll cost (average FTE x loaded cost / 12 x pay-rise factor) | B30: GBP k | O30: =(O27+O29)/2*inp_sal_cs/12*(1+inp_merit)^(O$5-1) | P30: =(P27+P29)/2*inp_sal_cs/12*(1+inp_merit)^(P$5-1) | Q30: =(Q27+Q29)/2*inp_sal_cs/12*(1+inp_merit)^(Q$5-1) | R30: =(R27+R29)/2*inp_sal_cs/12*(1+inp_merit)^(R$5-1) | S30: =(S27+S29)/2*inp_sal_cs/12*(1+inp_merit)^(S$5-1) | T30: =(T27+T29)/2*inp_sal_cs/12*(1+inp_merit)^(T$5-1) | U30: =(U27+U29)/2*inp_sal_cs/12*(1+inp_merit)^(U$5-1) | V30: =(V27+V29)/2*inp_sal_cs/12*(1+inp_merit)^(V$5-1) | ... AL30: =(AL27+AL29)/2*inp_sal_cs/12*(1+inp_merit)^(AL$5-1) | AN30: =SUMIF($O$5:$AL$5,AN$5,$O30:$AL30) | AO30: =SUMIF($O$5:$AL$5,AO$5,$O30:$AL30)
A32: Totals
A33: Total closing FTE | B33: FTE | N33: =N11+N17+N23+N29 | O33: =O11+O17+O23+O29 | P33: =P11+P17+P23+P29 | Q33: =Q11+Q17+Q23+Q29 | R33: =R11+R17+R23+R29 | S33: =S11+S17+S23+S29 | T33: =T11+T17+T23+T29 | U33: =U11+U17+U23+U29 | ... AL33: =AL11+AL17+AL23+AL29 | AN33: =INDEX($O33:$AL33,1,AN$5*12) | AO33: =INDEX($O33:$AL33,1,AO$5*12)
A34: Total payroll | B34: GBP k | O34: =O12+O18+O24+O30 | P34: =P12+P18+P24+P30 | Q34: =Q12+Q18+Q24+Q30 | R34: =R12+R18+R24+R30 | S34: =S12+S18+S24+S30 | T34: =T12+T18+T24+T30 | U34: =U12+U18+U24+U30 | V34: =V12+V18+V24+V30 | ... AL34: =AL12+AL18+AL24+AL30 | AN34: =SUMIF($O$5:$AL$5,AN$5,$O34:$AL34) | AO34: =SUMIF($O$5:$AL$5,AO$5,$O34:$AL34)
A36: Non-headcount opex
A37: Marketing programmes | B37: GBP k | O37: =inp_marketing_m | P37: =inp_marketing_m | Q37: =inp_marketing_m | R37: =inp_marketing_m | S37: =inp_marketing_m | T37: =inp_marketing_m | U37: =inp_marketing_m | V37: =inp_marketing_m | ... AL37: =inp_marketing_m | AN37: =SUMIF($O$5:$AL$5,AN$5,$O37:$AL37) | AO37: =SUMIF($O$5:$AL$5,AO$5,$O37:$AL37)
A38: R&D non-headcount | B38: GBP k | O38: =inp_rd_other_m | P38: =inp_rd_other_m | Q38: =inp_rd_other_m | R38: =inp_rd_other_m | S38: =inp_rd_other_m | T38: =inp_rd_other_m | U38: =inp_rd_other_m | V38: =inp_rd_other_m | ... AL38: =inp_rd_other_m | AN38: =SUMIF($O$5:$AL$5,AN$5,$O38:$AL38) | AO38: =SUMIF($O$5:$AL$5,AO$5,$O38:$AL38)
A39: G&A non-headcount | B39: GBP k | O39: =inp_ga_other_m | P39: =inp_ga_other_m | Q39: =inp_ga_other_m | R39: =inp_ga_other_m | S39: =inp_ga_other_m | T39: =inp_ga_other_m | U39: =inp_ga_other_m | V39: =inp_ga_other_m | ... AL39: =inp_ga_other_m | AN39: =SUMIF($O$5:$AL$5,AN$5,$O39:$AL39) | AO39: =SUMIF($O$5:$AL$5,AO$5,$O39:$AL39)
A40: Sales commission earned (cash; accounting treatment on Contract_Costs) | B40: GBP k | O40: =inp_commission_pct*(Rev_Build!O44+Rev_Build!O45) | P40: =inp_commission_pct*(Rev_Build!P44+Rev_Build!P45) | Q40: =inp_commission_pct*(Rev_Build!Q44+Rev_Build!Q45) | R40: =inp_commission_pct*(Rev_Build!R44+Rev_Build!R45) | S40: =inp_commission_pct*(Rev_Build!S44+Rev_Build!S45) | T40: =inp_commission_pct*(Rev_Build!T44+Rev_Build!T45) | U40: =inp_commission_pct*(Rev_Build!U44+Rev_Build!U45) | V40: =inp_commission_pct*(Rev_Build!V44+Rev_Build!V45) | ... AL40: =inp_commission_pct*(Rev_Build!AL44+Rev_Build!AL45) | AN40: =SUMIF($O$5:$AL$5,AN$5,$O40:$AL40) | AO40: =SUMIF($O$5:$AL$5,AO$5,$O40:$AL40)
A42: Operating expense by function (Customer Success payroll sits in COGS)
A43: R&D | B43: GBP k | O43: =O12+O38 | P43: =P12+P38 | Q43: =Q12+Q38 | R43: =R12+R38 | S43: =S12+S38 | T43: =T12+T38 | U43: =U12+U38 | V43: =V12+V38 | ... AL43: =AL12+AL38 | AN43: =SUMIF($O$5:$AL$5,AN$5,$O43:$AL43) | AO43: =SUMIF($O$5:$AL$5,AO$5,$O43:$AL43)
A44: Sales & Marketing | B44: GBP k | O44: =O18+O37+Contract_Costs!O20 | P44: =P18+P37+Contract_Costs!P20 | Q44: =Q18+Q37+Contract_Costs!Q20 | R44: =R18+R37+Contract_Costs!R20 | S44: =S18+S37+Contract_Costs!S20 | T44: =T18+T37+Contract_Costs!T20 | U44: =U18+U37+Contract_Costs!U20 | V44: =V18+V37+Contract_Costs!V20 | ... AL44: =AL18+AL37+Contract_Costs!AL20 | AN44: =SUMIF($O$5:$AL$5,AN$5,$O44:$AL44) | AO44: =SUMIF($O$5:$AL$5,AO$5,$O44:$AL44)
A45: G&A | B45: GBP k | O45: =O24+O39 | P45: =P24+P39 | Q45: =Q24+Q39 | R45: =R24+R39 | S45: =S24+S39 | T45: =T24+T39 | U45: =U24+U39 | V45: =V24+V39 | ... AL45: =AL24+AL39 | AN45: =SUMIF($O$5:$AL$5,AN$5,$O45:$AL45) | AO45: =SUMIF($O$5:$AL$5,AO$5,$O45:$AL45)
A46: Total operating expense | B46: GBP k | O46: =SUM(O43:O45) | P46: =SUM(P43:P45) | Q46: =SUM(Q43:Q45) | R46: =SUM(R43:R45) | S46: =SUM(S43:S45) | T46: =SUM(T43:T45) | U46: =SUM(U43:U45) | V46: =SUM(V43:V45) | ... AL46: =SUM(AL43:AL45) | AN46: =SUMIF($O$5:$AL$5,AN$5,$O46:$AL46) | AO46: =SUMIF($O$5:$AL$5,AO$5,$O46:$AL46)

Sheet Contract_Costs
A1: Contract_Costs - capitalised sales commission (IFRS 15.91)
A2: GBP thousands unless stated. Blue = input, black = formula, green = link to another tab.
A3: Period # | C3: =COLUMN()-COLUMN($N$1) | D3: =COLUMN()-COLUMN($N$1) | E3: =COLUMN()-COLUMN($N$1) | F3: =COLUMN()-COLUMN($N$1) | G3: =COLUMN()-COLUMN($N$1) | H3: =COLUMN()-COLUMN($N$1) | I3: =COLUMN()-COLUMN($N$1) | J3: =COLUMN()-COLUMN($N$1) | ... AL3: =COLUMN()-COLUMN($N$1) | AN3: Annual | AO3: Annual
A4: Period ending | C4: =EOMONTH(inp_model_start,C3-1) | D4: =EOMONTH(inp_model_start,D3-1) | E4: =EOMONTH(inp_model_start,E3-1) | F4: =EOMONTH(inp_model_start,F3-1) | G4: =EOMONTH(inp_model_start,G3-1) | H4: =EOMONTH(inp_model_start,H3-1) | I4: =EOMONTH(inp_model_start,I3-1) | J4: =EOMONTH(inp_model_start,J3-1) | ... AL4: =EOMONTH(inp_model_start,AL3-1) | AN4: ="FY"&(YEAR(inp_model_start)+AN5-1) | AO4: ="FY"&(YEAR(inp_model_start)+AO5-1)
A5: Year | C5: =IF(C3<1,0,ROUNDUP(C3/12,0)) | D5: =IF(D3<1,0,ROUNDUP(D3/12,0)) | E5: =IF(E3<1,0,ROUNDUP(E3/12,0)) | F5: =IF(F3<1,0,ROUNDUP(F3/12,0)) | G5: =IF(G3<1,0,ROUNDUP(G3/12,0)) | H5: =IF(H3<1,0,ROUNDUP(H3/12,0)) | I5: =IF(I3<1,0,ROUNDUP(I3/12,0)) | J5: =IF(J3<1,0,ROUNDUP(J3/12,0)) | ... AL5: =IF(AL3<1,0,ROUNDUP(AL3/12,0)) | AN5: =COLUMN()-COLUMN($AM$1) | AO5: =COLUMN()-COLUMN($AM$1)
A6: Quarter | C6: =IF(C3<1,0,ROUNDUP(C3/3,0)) | D6: =IF(D3<1,0,ROUNDUP(D3/3,0)) | E6: =IF(E3<1,0,ROUNDUP(E3/3,0)) | F6: =IF(F3<1,0,ROUNDUP(F3/3,0)) | G6: =IF(G3<1,0,ROUNDUP(G3/3,0)) | H6: =IF(H3<1,0,ROUNDUP(H3/3,0)) | I6: =IF(I3<1,0,ROUNDUP(I3/3,0)) | J6: =IF(J3<1,0,ROUNDUP(J3/3,0)) | ... AL6: =IF(AL3<1,0,ROUNDUP(AL3/3,0))
A8: Commission earned and treatment
A9: Commission earned (cash cost) | B9: GBP k | O9: =Headcount_Opex!O40 | P9: =Headcount_Opex!P40 | Q9: =Headcount_Opex!Q40 | R9: =Headcount_Opex!R40 | S9: =Headcount_Opex!S40 | T9: =Headcount_Opex!T40 | U9: =Headcount_Opex!U40 | V9: =Headcount_Opex!V40 | ... AL9: =Headcount_Opex!AL40 | AN9: =SUMIF($O$5:$AL$5,AN$5,$O9:$AL9) | AO9: =SUMIF($O$5:$AL$5,AO$5,$O9:$AL9)
A10: Capitalised | B10: GBP k | O10: =inp_capitalise_commission*O9 | P10: =inp_capitalise_commission*P9 | Q10: =inp_capitalise_commission*Q9 | R10: =inp_capitalise_commission*R9 | S10: =inp_capitalise_commission*S9 | T10: =inp_capitalise_commission*T9 | U10: =inp_capitalise_commission*U9 | V10: =inp_capitalise_commission*V9 | ... AL10: =inp_capitalise_commission*AL9 | AN10: =SUMIF($O$5:$AL$5,AN$5,$O10:$AL10) | AO10: =SUMIF($O$5:$AL$5,AO$5,$O10:$AL10)
A11: Expensed immediately | B11: GBP k | O11: =O9-O10 | P11: =P9-P10 | Q11: =Q9-Q10 | R11: =R9-R10 | S11: =S9-S10 | T11: =T9-T10 | U11: =U9-U10 | V11: =V9-V10 | ... AL11: =AL9-AL10 | AN11: =SUMIF($O$5:$AL$5,AN$5,$O11:$AL11) | AO11: =SUMIF($O$5:$AL$5,AO$5,$O11:$AL11)
A13: Asset roll-forward
A14: Opening asset | B14: GBP k | O14: =N17 | P14: =O17 | Q14: =P17 | R14: =Q17 | S14: =R17 | T14: =S17 | U14: =T17 | V14: =U17 | ... AL14: =AK17 | AN14: =INDEX($O14:$AL14,1,(AN$5-1)*12+1) | AO14: =INDEX($O14:$AL14,1,(AO$5-1)*12+1)
A15: + Capitalised | B15: GBP k | O15: =O10 | P15: =P10 | Q15: =Q10 | R15: =R10 | S15: =S10 | T15: =T10 | U15: =U10 | V15: =V10 | ... AL15: =AL10 | AN15: =SUMIF($O$5:$AL$5,AN$5,$O15:$AL15) | AO15: =SUMIF($O$5:$AL$5,AO$5,$O15:$AL15)
A16: - Amortisation | B16: GBP k | O16: =-O14/inp_cc_life | P16: =-P14/inp_cc_life | Q16: =-Q14/inp_cc_life | R16: =-R14/inp_cc_life | S16: =-S14/inp_cc_life | T16: =-T14/inp_cc_life | U16: =-U14/inp_cc_life | V16: =-V14/inp_cc_life | ... AL16: =-AL14/inp_cc_life | AN16: =SUMIF($O$5:$AL$5,AN$5,$O16:$AL16) | AO16: =SUMIF($O$5:$AL$5,AO$5,$O16:$AL16)
A17: Closing asset | B17: GBP k | N17: =inp_open_cca | O17: =SUM(O14:O16) | P17: =SUM(P14:P16) | Q17: =SUM(Q14:Q16) | R17: =SUM(R14:R16) | S17: =SUM(S14:S16) | T17: =SUM(T14:T16) | U17: =SUM(U14:U16) | V17: =SUM(V14:V16) | ... AL17: =SUM(AL14:AL16) | AN17: =INDEX($O17:$AL17,1,AN$5*12) | AO17: =INDEX($O17:$AL17,1,AO$5*12)
A19: Charge to the income statement (S&M)
A20: Commission expense = expensed now + amortisation | B20: GBP k | O20: =O11-O16 | P20: =P11-P16 | Q20: =Q11-Q16 | R20: =R11-R16 | S20: =S11-S16 | T20: =T11-T16 | U20: =U11-U16 | V20: =V11-V16 | ... AL20: =AL11-AL16 | AN20: =SUMIF($O$5:$AL$5,AN$5,$O20:$AL20) | AO20: =SUMIF($O$5:$AL$5,AO$5,$O20:$AL20)

Sheet COGS
A1: COGS - hosting, licences, support and services; gross margin by stream
A2: GBP thousands unless stated. Blue = input, black = formula, green = link to another tab.
A3: Period # | C3: =COLUMN()-COLUMN($N$1) | D3: =COLUMN()-COLUMN($N$1) | E3: =COLUMN()-COLUMN($N$1) | F3: =COLUMN()-COLUMN($N$1) | G3: =COLUMN()-COLUMN($N$1) | H3: =COLUMN()-COLUMN($N$1) | I3: =COLUMN()-COLUMN($N$1) | J3: =COLUMN()-COLUMN($N$1) | ... AL3: =COLUMN()-COLUMN($N$1) | AN3: Annual | AO3: Annual
A4: Period ending | C4: =EOMONTH(inp_model_start,C3-1) | D4: =EOMONTH(inp_model_start,D3-1) | E4: =EOMONTH(inp_model_start,E3-1) | F4: =EOMONTH(inp_model_start,F3-1) | G4: =EOMONTH(inp_model_start,G3-1) | H4: =EOMONTH(inp_model_start,H3-1) | I4: =EOMONTH(inp_model_start,I3-1) | J4: =EOMONTH(inp_model_start,J3-1) | ... AL4: =EOMONTH(inp_model_start,AL3-1) | AN4: ="FY"&(YEAR(inp_model_start)+AN5-1) | AO4: ="FY"&(YEAR(inp_model_start)+AO5-1)
A5: Year | C5: =IF(C3<1,0,ROUNDUP(C3/12,0)) | D5: =IF(D3<1,0,ROUNDUP(D3/12,0)) | E5: =IF(E3<1,0,ROUNDUP(E3/12,0)) | F5: =IF(F3<1,0,ROUNDUP(F3/12,0)) | G5: =IF(G3<1,0,ROUNDUP(G3/12,0)) | H5: =IF(H3<1,0,ROUNDUP(H3/12,0)) | I5: =IF(I3<1,0,ROUNDUP(I3/12,0)) | J5: =IF(J3<1,0,ROUNDUP(J3/12,0)) | ... AL5: =IF(AL3<1,0,ROUNDUP(AL3/12,0)) | AN5: =COLUMN()-COLUMN($AM$1) | AO5: =COLUMN()-COLUMN($AM$1)
A6: Quarter | C6: =IF(C3<1,0,ROUNDUP(C3/3,0)) | D6: =IF(D3<1,0,ROUNDUP(D3/3,0)) | E6: =IF(E3<1,0,ROUNDUP(E3/3,0)) | F6: =IF(F3<1,0,ROUNDUP(F3/3,0)) | G6: =IF(G3<1,0,ROUNDUP(G3/3,0)) | H6: =IF(H3<1,0,ROUNDUP(H3/3,0)) | I6: =IF(I3<1,0,ROUNDUP(I3/3,0)) | J6: =IF(J3<1,0,ROUNDUP(J3/3,0)) | ... AL6: =IF(AL3<1,0,ROUNDUP(AL3/3,0))
A8: Cost of revenue
A9: Hosting (closing customers x cost per customer) | B9: GBP k | O9: =Rev_Build!O29*inp_host_ent+Rev_Build!O40*inp_host_mid | P9: =Rev_Build!P29*inp_host_ent+Rev_Build!P40*inp_host_mid | Q9: =Rev_Build!Q29*inp_host_ent+Rev_Build!Q40*inp_host_mid | R9: =Rev_Build!R29*inp_host_ent+Rev_Build!R40*inp_host_mid | S9: =Rev_Build!S29*inp_host_ent+Rev_Build!S40*inp_host_mid | T9: =Rev_Build!T29*inp_host_ent+Rev_Build!T40*inp_host_mid | U9: =Rev_Build!U29*inp_host_ent+Rev_Build!U40*inp_host_mid | V9: =Rev_Build!V29*inp_host_ent+Rev_Build!V40*inp_host_mid | ... AL9: =Rev_Build!AL29*inp_host_ent+Rev_Build!AL40*inp_host_mid | AN9: =SUMIF($O$5:$AL$5,AN$5,$O9:$AL9) | AO9: =SUMIF($O$5:$AL$5,AO$5,$O9:$AL9)
A10: Third-party licences | B10: GBP k | O10: =inp_licence_pct*Rev_Rec!O20 | P10: =inp_licence_pct*Rev_Rec!P20 | Q10: =inp_licence_pct*Rev_Rec!Q20 | R10: =inp_licence_pct*Rev_Rec!R20 | S10: =inp_licence_pct*Rev_Rec!S20 | T10: =inp_licence_pct*Rev_Rec!T20 | U10: =inp_licence_pct*Rev_Rec!U20 | V10: =inp_licence_pct*Rev_Rec!V20 | ... AL10: =inp_licence_pct*Rev_Rec!AL20 | AN10: =SUMIF($O$5:$AL$5,AN$5,$O10:$AL10) | AO10: =SUMIF($O$5:$AL$5,AO$5,$O10:$AL10)
A11: Customer Success payroll | B11: GBP k | O11: =Headcount_Opex!O30 | P11: =Headcount_Opex!P30 | Q11: =Headcount_Opex!Q30 | R11: =Headcount_Opex!R30 | S11: =Headcount_Opex!S30 | T11: =Headcount_Opex!T30 | U11: =Headcount_Opex!U30 | V11: =Headcount_Opex!V30 | ... AL11: =Headcount_Opex!AL30 | AN11: =SUMIF($O$5:$AL$5,AN$5,$O11:$AL11) | AO11: =SUMIF($O$5:$AL$5,AO$5,$O11:$AL11)
A12: Implementation delivery cost | B12: GBP k | O12: =inp_services_cost_pct*Rev_Rec!O21 | P12: =inp_services_cost_pct*Rev_Rec!P21 | Q12: =inp_services_cost_pct*Rev_Rec!Q21 | R12: =inp_services_cost_pct*Rev_Rec!R21 | S12: =inp_services_cost_pct*Rev_Rec!S21 | T12: =inp_services_cost_pct*Rev_Rec!T21 | U12: =inp_services_cost_pct*Rev_Rec!U21 | V12: =inp_services_cost_pct*Rev_Rec!V21 | ... AL12: =inp_services_cost_pct*Rev_Rec!AL21 | AN12: =SUMIF($O$5:$AL$5,AN$5,$O12:$AL12) | AO12: =SUMIF($O$5:$AL$5,AO$5,$O12:$AL12)
A13: Total COGS | B13: GBP k | O13: =SUM(O9:O12) | P13: =SUM(P9:P12) | Q13: =SUM(Q9:Q12) | R13: =SUM(R9:R12) | S13: =SUM(S9:S12) | T13: =SUM(T9:T12) | U13: =SUM(U9:U12) | V13: =SUM(V9:V12) | ... AL13: =SUM(AL9:AL12) | AN13: =SUMIF($O$5:$AL$5,AN$5,$O13:$AL13) | AO13: =SUMIF($O$5:$AL$5,AO$5,$O13:$AL13)
A15: Gross margin by stream
A16: Subscription revenue | B16: GBP k | O16: =Rev_Rec!O20 | P16: =Rev_Rec!P20 | Q16: =Rev_Rec!Q20 | R16: =Rev_Rec!R20 | S16: =Rev_Rec!S20 | T16: =Rev_Rec!T20 | U16: =Rev_Rec!U20 | V16: =Rev_Rec!V20 | ... AL16: =Rev_Rec!AL20 | AN16: =SUMIF($O$5:$AL$5,AN$5,$O16:$AL16) | AO16: =SUMIF($O$5:$AL$5,AO$5,$O16:$AL16)
A17: Subscription gross profit | B17: GBP k | O17: =O16-O9-O10-O11 | P17: =P16-P9-P10-P11 | Q17: =Q16-Q9-Q10-Q11 | R17: =R16-R9-R10-R11 | S17: =S16-S9-S10-S11 | T17: =T16-T9-T10-T11 | U17: =U16-U9-U10-U11 | V17: =V16-V9-V10-V11 | ... AL17: =AL16-AL9-AL10-AL11 | AN17: =SUMIF($O$5:$AL$5,AN$5,$O17:$AL17) | AO17: =SUMIF($O$5:$AL$5,AO$5,$O17:$AL17)
A18: Subscription gross margin | B18: % | O18: =O17/O16 | P18: =P17/P16 | Q18: =Q17/Q16 | R18: =R17/R16 | S18: =S17/S16 | T18: =T17/T16 | U18: =U17/U16 | V18: =V17/V16 | ... AL18: =AL17/AL16 | AN18: =INDEX($O18:$AL18,1,AN$5*12) | AO18: =INDEX($O18:$AL18,1,AO$5*12)
A19: Implementation revenue | B19: GBP k | O19: =Rev_Rec!O21 | P19: =Rev_Rec!P21 | Q19: =Rev_Rec!Q21 | R19: =Rev_Rec!R21 | S19: =Rev_Rec!S21 | T19: =Rev_Rec!T21 | U19: =Rev_Rec!U21 | V19: =Rev_Rec!V21 | ... AL19: =Rev_Rec!AL21 | AN19: =SUMIF($O$5:$AL$5,AN$5,$O19:$AL19) | AO19: =SUMIF($O$5:$AL$5,AO$5,$O19:$AL19)
A20: Implementation gross profit | B20: GBP k | O20: =O19-O12 | P20: =P19-P12 | Q20: =Q19-Q12 | R20: =R19-R12 | S20: =S19-S12 | T20: =T19-T12 | U20: =U19-U12 | V20: =V19-V12 | ... AL20: =AL19-AL12 | AN20: =SUMIF($O$5:$AL$5,AN$5,$O20:$AL20) | AO20: =SUMIF($O$5:$AL$5,AO$5,$O20:$AL20)
A21: Implementation gross margin | B21: % | O21: =IF(O19=0,0,O20/O19) | P21: =IF(P19=0,0,P20/P19) | Q21: =IF(Q19=0,0,Q20/Q19) | R21: =IF(R19=0,0,R20/R19) | S21: =IF(S19=0,0,S20/S19) | T21: =IF(T19=0,0,T20/T19) | U21: =IF(U19=0,0,U20/U19) | V21: =IF(V19=0,0,V20/V19) | ... AL21: =IF(AL19=0,0,AL20/AL19) | AN21: =INDEX($O21:$AL21,1,AN$5*12) | AO21: =INDEX($O21:$AL21,1,AO$5*12)
A22: Total gross profit | B22: GBP k | O22: =O17+O20 | P22: =P17+P20 | Q22: =Q17+Q20 | R22: =R17+R20 | S22: =S17+S20 | T22: =T17+T20 | U22: =U17+U20 | V22: =V17+V20 | ... AL22: =AL17+AL20 | AN22: =SUMIF($O$5:$AL$5,AN$5,$O22:$AL22) | AO22: =SUMIF($O$5:$AL$5,AO$5,$O22:$AL22)
A23: Blended gross margin | B23: % | O23: =O22/(O16+O19) | P23: =P22/(P16+P19) | Q23: =Q22/(Q16+Q19) | R23: =R22/(R16+R19) | S23: =S22/(S16+S19) | T23: =T22/(T16+T19) | U23: =U22/(U16+U19) | V23: =V22/(V16+V19) | ... AL23: =AL22/(AL16+AL19) | AN23: =INDEX($O23:$AL23,1,AN$5*12) | AO23: =INDEX($O23:$AL23,1,AO$5*12)

Sheet IS
A1: IS - income statement
A2: GBP thousands unless stated. Blue = input, black = formula, green = link to another tab.
A3: Period # | C3: =COLUMN()-COLUMN($N$1) | D3: =COLUMN()-COLUMN($N$1) | E3: =COLUMN()-COLUMN($N$1) | F3: =COLUMN()-COLUMN($N$1) | G3: =COLUMN()-COLUMN($N$1) | H3: =COLUMN()-COLUMN($N$1) | I3: =COLUMN()-COLUMN($N$1) | J3: =COLUMN()-COLUMN($N$1) | ... AL3: =COLUMN()-COLUMN($N$1) | AN3: Annual | AO3: Annual
A4: Period ending | C4: =EOMONTH(inp_model_start,C3-1) | D4: =EOMONTH(inp_model_start,D3-1) | E4: =EOMONTH(inp_model_start,E3-1) | F4: =EOMONTH(inp_model_start,F3-1) | G4: =EOMONTH(inp_model_start,G3-1) | H4: =EOMONTH(inp_model_start,H3-1) | I4: =EOMONTH(inp_model_start,I3-1) | J4: =EOMONTH(inp_model_start,J3-1) | ... AL4: =EOMONTH(inp_model_start,AL3-1) | AN4: ="FY"&(YEAR(inp_model_start)+AN5-1) | AO4: ="FY"&(YEAR(inp_model_start)+AO5-1)
A5: Year | C5: =IF(C3<1,0,ROUNDUP(C3/12,0)) | D5: =IF(D3<1,0,ROUNDUP(D3/12,0)) | E5: =IF(E3<1,0,ROUNDUP(E3/12,0)) | F5: =IF(F3<1,0,ROUNDUP(F3/12,0)) | G5: =IF(G3<1,0,ROUNDUP(G3/12,0)) | H5: =IF(H3<1,0,ROUNDUP(H3/12,0)) | I5: =IF(I3<1,0,ROUNDUP(I3/12,0)) | J5: =IF(J3<1,0,ROUNDUP(J3/12,0)) | ... AL5: =IF(AL3<1,0,ROUNDUP(AL3/12,0)) | AN5: =COLUMN()-COLUMN($AM$1) | AO5: =COLUMN()-COLUMN($AM$1)
A6: Quarter | C6: =IF(C3<1,0,ROUNDUP(C3/3,0)) | D6: =IF(D3<1,0,ROUNDUP(D3/3,0)) | E6: =IF(E3<1,0,ROUNDUP(E3/3,0)) | F6: =IF(F3<1,0,ROUNDUP(F3/3,0)) | G6: =IF(G3<1,0,ROUNDUP(G3/3,0)) | H6: =IF(H3<1,0,ROUNDUP(H3/3,0)) | I6: =IF(I3<1,0,ROUNDUP(I3/3,0)) | J6: =IF(J3<1,0,ROUNDUP(J3/3,0)) | ... AL6: =IF(AL3<1,0,ROUNDUP(AL3/3,0))
A8: Revenue
A9: Subscription - Enterprise | B9: GBP k | O9: =Rev_Rec!O18 | P9: =Rev_Rec!P18 | Q9: =Rev_Rec!Q18 | R9: =Rev_Rec!R18 | S9: =Rev_Rec!S18 | T9: =Rev_Rec!T18 | U9: =Rev_Rec!U18 | V9: =Rev_Rec!V18 | ... AL9: =Rev_Rec!AL18 | AN9: =SUMIF($O$5:$AL$5,AN$5,$O9:$AL9) | AO9: =SUMIF($O$5:$AL$5,AO$5,$O9:$AL9)
A10: Subscription - Mid-market | B10: GBP k | O10: =Rev_Rec!O19 | P10: =Rev_Rec!P19 | Q10: =Rev_Rec!Q19 | R10: =Rev_Rec!R19 | S10: =Rev_Rec!S19 | T10: =Rev_Rec!T19 | U10: =Rev_Rec!U19 | V10: =Rev_Rec!V19 | ... AL10: =Rev_Rec!AL19 | AN10: =SUMIF($O$5:$AL$5,AN$5,$O10:$AL10) | AO10: =SUMIF($O$5:$AL$5,AO$5,$O10:$AL10)
A11: Implementation | B11: GBP k | O11: =Rev_Rec!O21 | P11: =Rev_Rec!P21 | Q11: =Rev_Rec!Q21 | R11: =Rev_Rec!R21 | S11: =Rev_Rec!S21 | T11: =Rev_Rec!T21 | U11: =Rev_Rec!U21 | V11: =Rev_Rec!V21 | ... AL11: =Rev_Rec!AL21 | AN11: =SUMIF($O$5:$AL$5,AN$5,$O11:$AL11) | AO11: =SUMIF($O$5:$AL$5,AO$5,$O11:$AL11)
A12: Total revenue | B12: GBP k | O12: =SUM(O9:O11) | P12: =SUM(P9:P11) | Q12: =SUM(Q9:Q11) | R12: =SUM(R9:R11) | S12: =SUM(S9:S11) | T12: =SUM(T9:T11) | U12: =SUM(U9:U11) | V12: =SUM(V9:V11) | ... AL12: =SUM(AL9:AL11) | AN12: =SUMIF($O$5:$AL$5,AN$5,$O12:$AL12) | AO12: =SUMIF($O$5:$AL$5,AO$5,$O12:$AL12)
A14: Cost of revenue
A15: Hosting | B15: GBP k | O15: =COGS!O9 | P15: =COGS!P9 | Q15: =COGS!Q9 | R15: =COGS!R9 | S15: =COGS!S9 | T15: =COGS!T9 | U15: =COGS!U9 | V15: =COGS!V9 | ... AL15: =COGS!AL9 | AN15: =SUMIF($O$5:$AL$5,AN$5,$O15:$AL15) | AO15: =SUMIF($O$5:$AL$5,AO$5,$O15:$AL15)
A16: Third-party licences | B16: GBP k | O16: =COGS!O10 | P16: =COGS!P10 | Q16: =COGS!Q10 | R16: =COGS!R10 | S16: =COGS!S10 | T16: =COGS!T10 | U16: =COGS!U10 | V16: =COGS!V10 | ... AL16: =COGS!AL10 | AN16: =SUMIF($O$5:$AL$5,AN$5,$O16:$AL16) | AO16: =SUMIF($O$5:$AL$5,AO$5,$O16:$AL16)
A17: Customer Success | B17: GBP k | O17: =COGS!O11 | P17: =COGS!P11 | Q17: =COGS!Q11 | R17: =COGS!R11 | S17: =COGS!S11 | T17: =COGS!T11 | U17: =COGS!U11 | V17: =COGS!V11 | ... AL17: =COGS!AL11 | AN17: =SUMIF($O$5:$AL$5,AN$5,$O17:$AL17) | AO17: =SUMIF($O$5:$AL$5,AO$5,$O17:$AL17)
A18: Implementation delivery | B18: GBP k | O18: =COGS!O12 | P18: =COGS!P12 | Q18: =COGS!Q12 | R18: =COGS!R12 | S18: =COGS!S12 | T18: =COGS!T12 | U18: =COGS!U12 | V18: =COGS!V12 | ... AL18: =COGS!AL12 | AN18: =SUMIF($O$5:$AL$5,AN$5,$O18:$AL18) | AO18: =SUMIF($O$5:$AL$5,AO$5,$O18:$AL18)
A19: Total cost of revenue | B19: GBP k | O19: =SUM(O15:O18) | P19: =SUM(P15:P18) | Q19: =SUM(Q15:Q18) | R19: =SUM(R15:R18) | S19: =SUM(S15:S18) | T19: =SUM(T15:T18) | U19: =SUM(U15:U18) | V19: =SUM(V15:V18) | ... AL19: =SUM(AL15:AL18) | AN19: =SUMIF($O$5:$AL$5,AN$5,$O19:$AL19) | AO19: =SUMIF($O$5:$AL$5,AO$5,$O19:$AL19)
A20: Gross profit | B20: GBP k | O20: =O12-O19 | P20: =P12-P19 | Q20: =Q12-Q19 | R20: =R12-R19 | S20: =S12-S19 | T20: =T12-T19 | U20: =U12-U19 | V20: =V12-V19 | ... AL20: =AL12-AL19 | AN20: =SUMIF($O$5:$AL$5,AN$5,$O20:$AL20) | AO20: =SUMIF($O$5:$AL$5,AO$5,$O20:$AL20)
A21: Gross margin | B21: % | O21: =O20/O12 | P21: =P20/P12 | Q21: =Q20/Q12 | R21: =R20/R12 | S21: =S20/S12 | T21: =T20/T12 | U21: =U20/U12 | V21: =V20/V12 | ... AL21: =AL20/AL12 | AN21: =AN20/AN12 | AO21: =AO20/AO12
A23: Operating expense
A24: Research & development | B24: GBP k | O24: =Headcount_Opex!O43 | P24: =Headcount_Opex!P43 | Q24: =Headcount_Opex!Q43 | R24: =Headcount_Opex!R43 | S24: =Headcount_Opex!S43 | T24: =Headcount_Opex!T43 | U24: =Headcount_Opex!U43 | V24: =Headcount_Opex!V43 | ... AL24: =Headcount_Opex!AL43 | AN24: =SUMIF($O$5:$AL$5,AN$5,$O24:$AL24) | AO24: =SUMIF($O$5:$AL$5,AO$5,$O24:$AL24)
A25: Sales & marketing | B25: GBP k | O25: =Headcount_Opex!O44 | P25: =Headcount_Opex!P44 | Q25: =Headcount_Opex!Q44 | R25: =Headcount_Opex!R44 | S25: =Headcount_Opex!S44 | T25: =Headcount_Opex!T44 | U25: =Headcount_Opex!U44 | V25: =Headcount_Opex!V44 | ... AL25: =Headcount_Opex!AL44 | AN25: =SUMIF($O$5:$AL$5,AN$5,$O25:$AL25) | AO25: =SUMIF($O$5:$AL$5,AO$5,$O25:$AL25)
A26: General & administrative | B26: GBP k | O26: =Headcount_Opex!O45 | P26: =Headcount_Opex!P45 | Q26: =Headcount_Opex!Q45 | R26: =Headcount_Opex!R45 | S26: =Headcount_Opex!S45 | T26: =Headcount_Opex!T45 | U26: =Headcount_Opex!U45 | V26: =Headcount_Opex!V45 | ... AL26: =Headcount_Opex!AL45 | AN26: =SUMIF($O$5:$AL$5,AN$5,$O26:$AL26) | AO26: =SUMIF($O$5:$AL$5,AO$5,$O26:$AL26)
A27: Total operating expense | B27: GBP k | O27: =SUM(O24:O26) | P27: =SUM(P24:P26) | Q27: =SUM(Q24:Q26) | R27: =SUM(R24:R26) | S27: =SUM(S24:S26) | T27: =SUM(T24:T26) | U27: =SUM(U24:U26) | V27: =SUM(V24:V26) | ... AL27: =SUM(AL24:AL26) | AN27: =SUMIF($O$5:$AL$5,AN$5,$O27:$AL27) | AO27: =SUMIF($O$5:$AL$5,AO$5,$O27:$AL27)
A29: EBITDA | B29: GBP k | O29: =O20-O27 | P29: =P20-P27 | Q29: =Q20-Q27 | R29: =R20-R27 | S29: =S20-S27 | T29: =T20-T27 | U29: =U20-U27 | V29: =V20-V27 | ... AL29: =AL20-AL27 | AN29: =SUMIF($O$5:$AL$5,AN$5,$O29:$AL29) | AO29: =SUMIF($O$5:$AL$5,AO$5,$O29:$AL29)
A30: EBITDA margin | B30: % | O30: =O29/O12 | P30: =P29/P12 | Q30: =Q29/Q12 | R30: =R29/R12 | S30: =S29/S12 | T30: =T29/T12 | U30: =U29/U12 | V30: =V29/V12 | ... AL30: =AL29/AL12 | AN30: =AN29/AN12 | AO30: =AO29/AO12
A31: Depreciation | B31: GBP k | O31: =BS!O28 | P31: =BS!P28 | Q31: =BS!Q28 | R31: =BS!R28 | S31: =BS!S28 | T31: =BS!T28 | U31: =BS!U28 | V31: =BS!V28 | ... AL31: =BS!AL28 | AN31: =SUMIF($O$5:$AL$5,AN$5,$O31:$AL31) | AO31: =SUMIF($O$5:$AL$5,AO$5,$O31:$AL31)
A32: Operating profit (EBIT) | B32: GBP k | O32: =O29-O31 | P32: =P29-P31 | Q32: =Q29-Q31 | R32: =R29-R31 | S32: =S29-S31 | T32: =T29-T31 | U32: =U29-U31 | V32: =V29-V31 | ... AL32: =AL29-AL31 | AN32: =SUMIF($O$5:$AL$5,AN$5,$O32:$AL32) | AO32: =SUMIF($O$5:$AL$5,AO$5,$O32:$AL32)
A33: Interest income (on prior-period cash) | B33: GBP k | O33: =BS!N9*inp_interest/12 | P33: =BS!O9*inp_interest/12 | Q33: =BS!P9*inp_interest/12 | R33: =BS!Q9*inp_interest/12 | S33: =BS!R9*inp_interest/12 | T33: =BS!S9*inp_interest/12 | U33: =BS!T9*inp_interest/12 | V33: =BS!U9*inp_interest/12 | ... AL33: =BS!AK9*inp_interest/12 | AN33: =SUMIF($O$5:$AL$5,AN$5,$O33:$AL33) | AO33: =SUMIF($O$5:$AL$5,AO$5,$O33:$AL33)
A34: Profit before tax | B34: GBP k | O34: =O32+O33 | P34: =P32+P33 | Q34: =Q32+Q33 | R34: =R32+R33 | S34: =S32+S33 | T34: =T32+T33 | U34: =U32+U33 | V34: =V32+V33 | ... AL34: =AL32+AL33 | AN34: =SUMIF($O$5:$AL$5,AN$5,$O34:$AL34) | AO34: =SUMIF($O$5:$AL$5,AO$5,$O34:$AL34)
A35: Tax | B35: GBP k | O35: =MAX(0,O34)*inp_tax | P35: =MAX(0,P34)*inp_tax | Q35: =MAX(0,Q34)*inp_tax | R35: =MAX(0,R34)*inp_tax | S35: =MAX(0,S34)*inp_tax | T35: =MAX(0,T34)*inp_tax | U35: =MAX(0,U34)*inp_tax | V35: =MAX(0,V34)*inp_tax | ... AL35: =MAX(0,AL34)*inp_tax | AN35: =SUMIF($O$5:$AL$5,AN$5,$O35:$AL35) | AO35: =SUMIF($O$5:$AL$5,AO$5,$O35:$AL35)
A36: Net income | B36: GBP k | O36: =O34-O35 | P36: =P34-P35 | Q36: =Q34-Q35 | R36: =R34-R35 | S36: =S34-S35 | T36: =T34-T35 | U36: =U34-U35 | V36: =V34-V35 | ... AL36: =AL34-AL35 | AN36: =SUMIF($O$5:$AL$5,AN$5,$O36:$AL36) | AO36: =SUMIF($O$5:$AL$5,AO$5,$O36:$AL36)

Sheet BS
A1: BS - balance sheet
A2: GBP thousands unless stated. Blue = input, black = formula, green = link to another tab.
A3: Period # | C3: =COLUMN()-COLUMN($N$1) | D3: =COLUMN()-COLUMN($N$1) | E3: =COLUMN()-COLUMN($N$1) | F3: =COLUMN()-COLUMN($N$1) | G3: =COLUMN()-COLUMN($N$1) | H3: =COLUMN()-COLUMN($N$1) | I3: =COLUMN()-COLUMN($N$1) | J3: =COLUMN()-COLUMN($N$1) | ... AL3: =COLUMN()-COLUMN($N$1) | AN3: Annual | AO3: Annual
A4: Period ending | C4: =EOMONTH(inp_model_start,C3-1) | D4: =EOMONTH(inp_model_start,D3-1) | E4: =EOMONTH(inp_model_start,E3-1) | F4: =EOMONTH(inp_model_start,F3-1) | G4: =EOMONTH(inp_model_start,G3-1) | H4: =EOMONTH(inp_model_start,H3-1) | I4: =EOMONTH(inp_model_start,I3-1) | J4: =EOMONTH(inp_model_start,J3-1) | ... AL4: =EOMONTH(inp_model_start,AL3-1) | AN4: ="FY"&(YEAR(inp_model_start)+AN5-1) | AO4: ="FY"&(YEAR(inp_model_start)+AO5-1)
A5: Year | C5: =IF(C3<1,0,ROUNDUP(C3/12,0)) | D5: =IF(D3<1,0,ROUNDUP(D3/12,0)) | E5: =IF(E3<1,0,ROUNDUP(E3/12,0)) | F5: =IF(F3<1,0,ROUNDUP(F3/12,0)) | G5: =IF(G3<1,0,ROUNDUP(G3/12,0)) | H5: =IF(H3<1,0,ROUNDUP(H3/12,0)) | I5: =IF(I3<1,0,ROUNDUP(I3/12,0)) | J5: =IF(J3<1,0,ROUNDUP(J3/12,0)) | ... AL5: =IF(AL3<1,0,ROUNDUP(AL3/12,0)) | AN5: =COLUMN()-COLUMN($AM$1) | AO5: =COLUMN()-COLUMN($AM$1)
A6: Quarter | C6: =IF(C3<1,0,ROUNDUP(C3/3,0)) | D6: =IF(D3<1,0,ROUNDUP(D3/3,0)) | E6: =IF(E3<1,0,ROUNDUP(E3/3,0)) | F6: =IF(F3<1,0,ROUNDUP(F3/3,0)) | G6: =IF(G3<1,0,ROUNDUP(G3/3,0)) | H6: =IF(H3<1,0,ROUNDUP(H3/3,0)) | I6: =IF(I3<1,0,ROUNDUP(I3/3,0)) | J6: =IF(J3<1,0,ROUNDUP(J3/3,0)) | ... AL6: =IF(AL3<1,0,ROUNDUP(AL3/3,0))
A8: Assets
A9: Cash | B9: GBP k | N9: =CF!N24 | O9: =CF!O24 | P9: =CF!P24 | Q9: =CF!Q24 | R9: =CF!R24 | S9: =CF!S24 | T9: =CF!T24 | U9: =CF!U24 | ... AL9: =CF!AL24 | AN9: =INDEX($O9:$AL9,1,AN$5*12) | AO9: =INDEX($O9:$AL9,1,AO$5*12)
A10: Trade receivables | B10: GBP k | N10: =Rev_Rec!N37 | O10: =Rev_Rec!O37 | P10: =Rev_Rec!P37 | Q10: =Rev_Rec!Q37 | R10: =Rev_Rec!R37 | S10: =Rev_Rec!S37 | T10: =Rev_Rec!T37 | U10: =Rev_Rec!U37 | ... AL10: =Rev_Rec!AL37 | AN10: =INDEX($O10:$AL10,1,AN$5*12) | AO10: =INDEX($O10:$AL10,1,AO$5*12)
A11: PP&E (net) | B11: GBP k | N11: =N29 | O11: =O29 | P11: =P29 | Q11: =Q29 | R11: =R29 | S11: =S29 | T11: =T29 | U11: =U29 | ... AL11: =AL29 | AN11: =INDEX($O11:$AL11,1,AN$5*12) | AO11: =INDEX($O11:$AL11,1,AO$5*12)
A12: Capitalised contract costs | B12: GBP k | N12: =Contract_Costs!N17 | O12: =Contract_Costs!O17 | P12: =Contract_Costs!P17 | Q12: =Contract_Costs!Q17 | R12: =Contract_Costs!R17 | S12: =Contract_Costs!S17 | T12: =Contract_Costs!T17 | U12: =Contract_Costs!U17 | ... AL12: =Contract_Costs!AL17 | AN12: =INDEX($O12:$AL12,1,AN$5*12) | AO12: =INDEX($O12:$AL12,1,AO$5*12)
A13: Total assets | B13: GBP k | N13: =SUM(N9:N12) | O13: =SUM(O9:O12) | P13: =SUM(P9:P12) | Q13: =SUM(Q9:Q12) | R13: =SUM(R9:R12) | S13: =SUM(S9:S12) | T13: =SUM(T9:T12) | U13: =SUM(U9:U12) | ... AL13: =SUM(AL9:AL12) | AN13: =INDEX($O13:$AL13,1,AN$5*12) | AO13: =INDEX($O13:$AL13,1,AO$5*12)
A15: Liabilities
A16: Trade payables | B16: GBP k | N16: =inp_open_ap | O16: =O32*inp_dpo/30 | P16: =P32*inp_dpo/30 | Q16: =Q32*inp_dpo/30 | R16: =R32*inp_dpo/30 | S16: =S32*inp_dpo/30 | T16: =T32*inp_dpo/30 | U16: =U32*inp_dpo/30 | V16: =V32*inp_dpo/30 | ... AL16: =AL32*inp_dpo/30 | AN16: =INDEX($O16:$AL16,1,AN$5*12) | AO16: =INDEX($O16:$AL16,1,AO$5*12)
A17: Deferred revenue | B17: GBP k | N17: =Rev_Rec!N34 | O17: =Rev_Rec!O34 | P17: =Rev_Rec!P34 | Q17: =Rev_Rec!Q34 | R17: =Rev_Rec!R34 | S17: =Rev_Rec!S34 | T17: =Rev_Rec!T34 | U17: =Rev_Rec!U34 | ... AL17: =Rev_Rec!AL34 | AN17: =INDEX($O17:$AL17,1,AN$5*12) | AO17: =INDEX($O17:$AL17,1,AO$5*12)
A18: Total liabilities | B18: GBP k | N18: =N16+N17 | O18: =O16+O17 | P18: =P16+P17 | Q18: =Q16+Q17 | R18: =R16+R17 | S18: =S16+S17 | T18: =T16+T17 | U18: =U16+U17 | ... AL18: =AL16+AL17 | AN18: =INDEX($O18:$AL18,1,AN$5*12) | AO18: =INDEX($O18:$AL18,1,AO$5*12)
A20: Equity
A21: Total equity (opening net assets + cumulative net income) | B21: GBP k | N21: =N13-N18 | O21: =N21+IS!O36 | P21: =O21+IS!P36 | Q21: =P21+IS!Q36 | R21: =Q21+IS!R36 | S21: =R21+IS!S36 | T21: =S21+IS!T36 | U21: =T21+IS!U36 | V21: =U21+IS!V36 | ... AL21: =AK21+IS!AL36 | AN21: =INDEX($O21:$AL21,1,AN$5*12) | AO21: =INDEX($O21:$AL21,1,AO$5*12)
A23: Balance check (assets - liabilities - equity) | B23: GBP k | N23: =N13-N18-N21 | O23: =O13-O18-O21 | P23: =P13-P18-P21 | Q23: =Q13-Q18-Q21 | R23: =R13-R18-R21 | S23: =S13-S18-S21 | T23: =T13-T18-T21 | U23: =U13-U18-U21 | ... AL23: =AL13-AL18-AL21 | AN23: =INDEX($O23:$AL23,1,AN$5*12) | AO23: =INDEX($O23:$AL23,1,AO$5*12)
A25: Supporting schedule: PP&E
A26: Opening net book value | B26: GBP k | O26: =N29 | P26: =O29 | Q26: =P29 | R26: =Q29 | S26: =R29 | T26: =S29 | U26: =T29 | V26: =U29 | ... AL26: =AK29 | AN26: =INDEX($O26:$AL26,1,(AN$5-1)*12+1) | AO26: =INDEX($O26:$AL26,1,(AO$5-1)*12+1)
A27: + Capex | B27: GBP k | O27: =inp_capex_pct*IS!O12 | P27: =inp_capex_pct*IS!P12 | Q27: =inp_capex_pct*IS!Q12 | R27: =inp_capex_pct*IS!R12 | S27: =inp_capex_pct*IS!S12 | T27: =inp_capex_pct*IS!T12 | U27: =inp_capex_pct*IS!U12 | V27: =inp_capex_pct*IS!V12 | ... AL27: =inp_capex_pct*IS!AL12 | AN27: =SUMIF($O$5:$AL$5,AN$5,$O27:$AL27) | AO27: =SUMIF($O$5:$AL$5,AO$5,$O27:$AL27)
A28: - Depreciation | B28: GBP k | O28: =O26/inp_dep_life | P28: =P26/inp_dep_life | Q28: =Q26/inp_dep_life | R28: =R26/inp_dep_life | S28: =S26/inp_dep_life | T28: =T26/inp_dep_life | U28: =U26/inp_dep_life | V28: =V26/inp_dep_life | ... AL28: =AL26/inp_dep_life | AN28: =SUMIF($O$5:$AL$5,AN$5,$O28:$AL28) | AO28: =SUMIF($O$5:$AL$5,AO$5,$O28:$AL28)
A29: Closing net book value | B29: GBP k | N29: =inp_open_ppe | O29: =O26+O27-O28 | P29: =P26+P27-P28 | Q29: =Q26+Q27-Q28 | R29: =R26+R27-R28 | S29: =S26+S27-S28 | T29: =T26+T27-T28 | U29: =U26+U27-U28 | V29: =V26+V27-V28 | ... AL29: =AL26+AL27-AL28 | AN29: =INDEX($O29:$AL29,1,AN$5*12) | AO29: =INDEX($O29:$AL29,1,AO$5*12)
A31: Supporting schedule: non-payroll spend (drives payables)
A32: Hosting, licences, delivery, marketing, other opex | B32: GBP k | O32: =COGS!O9+COGS!O10+COGS!O12+Headcount_Opex!O37+Headcount_Opex!O38+Headcount_Opex!O39 | P32: =COGS!P9+COGS!P10+COGS!P12+Headcount_Opex!P37+Headcount_Opex!P38+Headcount_Opex!P39 | Q32: =COGS!Q9+COGS!Q10+COGS!Q12+Headcount_Opex!Q37+Headcount_Opex!Q38+Headcount_Opex!Q39 | R32: =COGS!R9+COGS!R10+COGS!R12+Headcount_Opex!R37+Headcount_Opex!R38+Headcount_Opex!R39 | S32: =COGS!S9+COGS!S10+COGS!S12+Headcount_Opex!S37+Headcount_Opex!S38+Headcount_Opex!S39 | T32: =COGS!T9+COGS!T10+COGS!T12+Headcount_Opex!T37+Headcount_Opex!T38+Headcount_Opex!T39 | U32: =COGS!U9+COGS!U10+COGS!U12+Headcount_Opex!U37+Headcount_Opex!U38+Headcount_Opex!U39 | V32: =COGS!V9+COGS!V10+COGS!V12+Headcount_Opex!V37+Headcount_Opex!V38+Headcount_Opex!V39 | ... AL32: =COGS!AL9+COGS!AL10+COGS!AL12+Headcount_Opex!AL37+Headcount_Opex!AL38+Headcount_Opex!AL39 | AN32: =SUMIF($O$5:$AL$5,AN$5,$O32:$AL32) | AO32: =SUMIF($O$5:$AL$5,AO$5,$O32:$AL32)

Sheet CF
A1: CF - cash flow statement (indirect)
A2: GBP thousands unless stated. Blue = input, black = formula, green = link to another tab.
A3: Period # | C3: =COLUMN()-COLUMN($N$1) | D3: =COLUMN()-COLUMN($N$1) | E3: =COLUMN()-COLUMN($N$1) | F3: =COLUMN()-COLUMN($N$1) | G3: =COLUMN()-COLUMN($N$1) | H3: =COLUMN()-COLUMN($N$1) | I3: =COLUMN()-COLUMN($N$1) | J3: =COLUMN()-COLUMN($N$1) | ... AL3: =COLUMN()-COLUMN($N$1) | AN3: Annual | AO3: Annual
A4: Period ending | C4: =EOMONTH(inp_model_start,C3-1) | D4: =EOMONTH(inp_model_start,D3-1) | E4: =EOMONTH(inp_model_start,E3-1) | F4: =EOMONTH(inp_model_start,F3-1) | G4: =EOMONTH(inp_model_start,G3-1) | H4: =EOMONTH(inp_model_start,H3-1) | I4: =EOMONTH(inp_model_start,I3-1) | J4: =EOMONTH(inp_model_start,J3-1) | ... AL4: =EOMONTH(inp_model_start,AL3-1) | AN4: ="FY"&(YEAR(inp_model_start)+AN5-1) | AO4: ="FY"&(YEAR(inp_model_start)+AO5-1)
A5: Year | C5: =IF(C3<1,0,ROUNDUP(C3/12,0)) | D5: =IF(D3<1,0,ROUNDUP(D3/12,0)) | E5: =IF(E3<1,0,ROUNDUP(E3/12,0)) | F5: =IF(F3<1,0,ROUNDUP(F3/12,0)) | G5: =IF(G3<1,0,ROUNDUP(G3/12,0)) | H5: =IF(H3<1,0,ROUNDUP(H3/12,0)) | I5: =IF(I3<1,0,ROUNDUP(I3/12,0)) | J5: =IF(J3<1,0,ROUNDUP(J3/12,0)) | ... AL5: =IF(AL3<1,0,ROUNDUP(AL3/12,0)) | AN5: =COLUMN()-COLUMN($AM$1) | AO5: =COLUMN()-COLUMN($AM$1)
A6: Quarter | C6: =IF(C3<1,0,ROUNDUP(C3/3,0)) | D6: =IF(D3<1,0,ROUNDUP(D3/3,0)) | E6: =IF(E3<1,0,ROUNDUP(E3/3,0)) | F6: =IF(F3<1,0,ROUNDUP(F3/3,0)) | G6: =IF(G3<1,0,ROUNDUP(G3/3,0)) | H6: =IF(H3<1,0,ROUNDUP(H3/3,0)) | I6: =IF(I3<1,0,ROUNDUP(I3/3,0)) | J6: =IF(J3<1,0,ROUNDUP(J3/3,0)) | ... AL6: =IF(AL3<1,0,ROUNDUP(AL3/3,0))
A8: Operating activities
A9: Net income | B9: GBP k | O9: =IS!O36 | P9: =IS!P36 | Q9: =IS!Q36 | R9: =IS!R36 | S9: =IS!S36 | T9: =IS!T36 | U9: =IS!U36 | V9: =IS!V36 | ... AL9: =IS!AL36 | AN9: =SUMIF($O$5:$AL$5,AN$5,$O9:$AL9) | AO9: =SUMIF($O$5:$AL$5,AO$5,$O9:$AL9)
A10: + Depreciation | B10: GBP k | O10: =IS!O31 | P10: =IS!P31 | Q10: =IS!Q31 | R10: =IS!R31 | S10: =IS!S31 | T10: =IS!T31 | U10: =IS!U31 | V10: =IS!V31 | ... AL10: =IS!AL31 | AN10: =SUMIF($O$5:$AL$5,AN$5,$O10:$AL10) | AO10: =SUMIF($O$5:$AL$5,AO$5,$O10:$AL10)
A11: (Increase) / decrease in receivables | B11: GBP k | O11: =-(BS!O10-BS!N10) | P11: =-(BS!P10-BS!O10) | Q11: =-(BS!Q10-BS!P10) | R11: =-(BS!R10-BS!Q10) | S11: =-(BS!S10-BS!R10) | T11: =-(BS!T10-BS!S10) | U11: =-(BS!U10-BS!T10) | V11: =-(BS!V10-BS!U10) | ... AL11: =-(BS!AL10-BS!AK10) | AN11: =SUMIF($O$5:$AL$5,AN$5,$O11:$AL11) | AO11: =SUMIF($O$5:$AL$5,AO$5,$O11:$AL11)
A12: Increase / (decrease) in payables | B12: GBP k | O12: =BS!O16-BS!N16 | P12: =BS!P16-BS!O16 | Q12: =BS!Q16-BS!P16 | R12: =BS!R16-BS!Q16 | S12: =BS!S16-BS!R16 | T12: =BS!T16-BS!S16 | U12: =BS!U16-BS!T16 | V12: =BS!V16-BS!U16 | ... AL12: =BS!AL16-BS!AK16 | AN12: =SUMIF($O$5:$AL$5,AN$5,$O12:$AL12) | AO12: =SUMIF($O$5:$AL$5,AO$5,$O12:$AL12)
A13: Increase / (decrease) in deferred revenue | B13: GBP k | O13: =BS!O17-BS!N17 | P13: =BS!P17-BS!O17 | Q13: =BS!Q17-BS!P17 | R13: =BS!R17-BS!Q17 | S13: =BS!S17-BS!R17 | T13: =BS!T17-BS!S17 | U13: =BS!U17-BS!T17 | V13: =BS!V17-BS!U17 | ... AL13: =BS!AL17-BS!AK17 | AN13: =SUMIF($O$5:$AL$5,AN$5,$O13:$AL13) | AO13: =SUMIF($O$5:$AL$5,AO$5,$O13:$AL13)
A14: (Increase) / decrease in capitalised contract costs | B14: GBP k | O14: =-(BS!O12-BS!N12) | P14: =-(BS!P12-BS!O12) | Q14: =-(BS!Q12-BS!P12) | R14: =-(BS!R12-BS!Q12) | S14: =-(BS!S12-BS!R12) | T14: =-(BS!T12-BS!S12) | U14: =-(BS!U12-BS!T12) | V14: =-(BS!V12-BS!U12) | ... AL14: =-(BS!AL12-BS!AK12) | AN14: =SUMIF($O$5:$AL$5,AN$5,$O14:$AL14) | AO14: =SUMIF($O$5:$AL$5,AO$5,$O14:$AL14)
A15: Cash flow from operations | B15: GBP k | O15: =SUM(O9:O14) | P15: =SUM(P9:P14) | Q15: =SUM(Q9:Q14) | R15: =SUM(R9:R14) | S15: =SUM(S9:S14) | T15: =SUM(T9:T14) | U15: =SUM(U9:U14) | V15: =SUM(V9:V14) | ... AL15: =SUM(AL9:AL14) | AN15: =SUMIF($O$5:$AL$5,AN$5,$O15:$AL15) | AO15: =SUMIF($O$5:$AL$5,AO$5,$O15:$AL15)
A17: Investing activities
A18: Capex | B18: GBP k | O18: =-BS!O27 | P18: =-BS!P27 | Q18: =-BS!Q27 | R18: =-BS!R27 | S18: =-BS!S27 | T18: =-BS!T27 | U18: =-BS!U27 | V18: =-BS!V27 | ... AL18: =-BS!AL27 | AN18: =SUMIF($O$5:$AL$5,AN$5,$O18:$AL18) | AO18: =SUMIF($O$5:$AL$5,AO$5,$O18:$AL18)
A19: Cash flow from investing | B19: GBP k | O19: =O18 | P19: =P18 | Q19: =Q18 | R19: =R18 | S19: =S18 | T19: =T18 | U19: =U18 | V19: =V18 | ... AL19: =AL18 | AN19: =SUMIF($O$5:$AL$5,AN$5,$O19:$AL19) | AO19: =SUMIF($O$5:$AL$5,AO$5,$O19:$AL19)
A21: Net cash flow and cash balance (no financing flows in the MVP)
A22: Net change in cash (= free cash flow) | B22: GBP k | O22: =O15+O19 | P22: =P15+P19 | Q22: =Q15+Q19 | R22: =R15+R19 | S22: =S15+S19 | T22: =T15+T19 | U22: =U15+U19 | V22: =V15+V19 | ... AL22: =AL15+AL19 | AN22: =SUMIF($O$5:$AL$5,AN$5,$O22:$AL22) | AO22: =SUMIF($O$5:$AL$5,AO$5,$O22:$AL22)
A23: Opening cash | B23: GBP k | O23: =N24 | P23: =O24 | Q23: =P24 | R23: =Q24 | S23: =R24 | T23: =S24 | U23: =T24 | V23: =U24 | ... AL23: =AK24 | AN23: =INDEX($O23:$AL23,1,(AN$5-1)*12+1) | AO23: =INDEX($O23:$AL23,1,(AO$5-1)*12+1)
A24: Closing cash | B24: GBP k | N24: =inp_open_cash | O24: =O23+O22 | P24: =P23+P22 | Q24: =Q23+Q22 | R24: =R23+R22 | S24: =S23+S22 | T24: =T23+T22 | U24: =U23+U22 | V24: =V23+V22 | ... AL24: =AL23+AL22 | AN24: =INDEX($O24:$AL24,1,AN$5*12) | AO24: =INDEX($O24:$AL24,1,AO$5*12)

Sheet SaaS_Metrics
A1: SaaS_Metrics - ARR bridge and unit economics
A2: GBP thousands unless stated. Blue = input, black = formula, green = link to another tab.
A3: Period # | C3: =COLUMN()-COLUMN($N$1) | D3: =COLUMN()-COLUMN($N$1) | E3: =COLUMN()-COLUMN($N$1) | F3: =COLUMN()-COLUMN($N$1) | G3: =COLUMN()-COLUMN($N$1) | H3: =COLUMN()-COLUMN($N$1) | I3: =COLUMN()-COLUMN($N$1) | J3: =COLUMN()-COLUMN($N$1) | ... AL3: =COLUMN()-COLUMN($N$1) | AN3: Annual | AO3: Annual
A4: Period ending | C4: =EOMONTH(inp_model_start,C3-1) | D4: =EOMONTH(inp_model_start,D3-1) | E4: =EOMONTH(inp_model_start,E3-1) | F4: =EOMONTH(inp_model_start,F3-1) | G4: =EOMONTH(inp_model_start,G3-1) | H4: =EOMONTH(inp_model_start,H3-1) | I4: =EOMONTH(inp_model_start,I3-1) | J4: =EOMONTH(inp_model_start,J3-1) | ... AL4: =EOMONTH(inp_model_start,AL3-1) | AN4: ="FY"&(YEAR(inp_model_start)+AN5-1) | AO4: ="FY"&(YEAR(inp_model_start)+AO5-1)
A5: Year | C5: =IF(C3<1,0,ROUNDUP(C3/12,0)) | D5: =IF(D3<1,0,ROUNDUP(D3/12,0)) | E5: =IF(E3<1,0,ROUNDUP(E3/12,0)) | F5: =IF(F3<1,0,ROUNDUP(F3/12,0)) | G5: =IF(G3<1,0,ROUNDUP(G3/12,0)) | H5: =IF(H3<1,0,ROUNDUP(H3/12,0)) | I5: =IF(I3<1,0,ROUNDUP(I3/12,0)) | J5: =IF(J3<1,0,ROUNDUP(J3/12,0)) | ... AL5: =IF(AL3<1,0,ROUNDUP(AL3/12,0)) | AN5: =COLUMN()-COLUMN($AM$1) | AO5: =COLUMN()-COLUMN($AM$1)
A6: Quarter | C6: =IF(C3<1,0,ROUNDUP(C3/3,0)) | D6: =IF(D3<1,0,ROUNDUP(D3/3,0)) | E6: =IF(E3<1,0,ROUNDUP(E3/3,0)) | F6: =IF(F3<1,0,ROUNDUP(F3/3,0)) | G6: =IF(G3<1,0,ROUNDUP(G3/3,0)) | H6: =IF(H3<1,0,ROUNDUP(H3/3,0)) | I6: =IF(I3<1,0,ROUNDUP(I3/3,0)) | J6: =IF(J3<1,0,ROUNDUP(J3/3,0)) | ... AL6: =IF(AL3<1,0,ROUNDUP(AL3/3,0))
A8: ARR bridge
A9: Opening ARR | B9: GBP k | O9: =Rev_Build!O43 | P9: =Rev_Build!P43 | Q9: =Rev_Build!Q43 | R9: =Rev_Build!R43 | S9: =Rev_Build!S43 | T9: =Rev_Build!T43 | U9: =Rev_Build!U43 | V9: =Rev_Build!V43 | ... AL9: =Rev_Build!AL43 | AN9: =INDEX($O9:$AL9,1,(AN$5-1)*12+1) | AO9: =INDEX($O9:$AL9,1,(AO$5-1)*12+1)
A10: + New logos | B10: GBP k | O10: =Rev_Build!O44 | P10: =Rev_Build!P44 | Q10: =Rev_Build!Q44 | R10: =Rev_Build!R44 | S10: =Rev_Build!S44 | T10: =Rev_Build!T44 | U10: =Rev_Build!U44 | V10: =Rev_Build!V44 | ... AL10: =Rev_Build!AL44 | AN10: =SUMIF($O$5:$AL$5,AN$5,$O10:$AL10) | AO10: =SUMIF($O$5:$AL$5,AO$5,$O10:$AL10)
A11: + Expansion | B11: GBP k | O11: =Rev_Build!O45 | P11: =Rev_Build!P45 | Q11: =Rev_Build!Q45 | R11: =Rev_Build!R45 | S11: =Rev_Build!S45 | T11: =Rev_Build!T45 | U11: =Rev_Build!U45 | V11: =Rev_Build!V45 | ... AL11: =Rev_Build!AL45 | AN11: =SUMIF($O$5:$AL$5,AN$5,$O11:$AL11) | AO11: =SUMIF($O$5:$AL$5,AO$5,$O11:$AL11)
A12: - Churn | B12: GBP k | O12: =Rev_Build!O46 | P12: =Rev_Build!P46 | Q12: =Rev_Build!Q46 | R12: =Rev_Build!R46 | S12: =Rev_Build!S46 | T12: =Rev_Build!T46 | U12: =Rev_Build!U46 | V12: =Rev_Build!V46 | ... AL12: =Rev_Build!AL46 | AN12: =SUMIF($O$5:$AL$5,AN$5,$O12:$AL12) | AO12: =SUMIF($O$5:$AL$5,AO$5,$O12:$AL12)
A13: Closing ARR | B13: GBP k | N13: =Rev_Build!N47 | O13: =SUM(O9:O12) | P13: =SUM(P9:P12) | Q13: =SUM(Q9:Q12) | R13: =SUM(R9:R12) | S13: =SUM(S9:S12) | T13: =SUM(T9:T12) | U13: =SUM(U9:U12) | V13: =SUM(V9:V12) | ... AL13: =SUM(AL9:AL12) | AN13: =INDEX($O13:$AL13,1,AN$5*12) | AO13: =INDEX($O13:$AL13,1,AO$5*12)
A14: Check: segment ARR - total ARR | B14: GBP k | N14: =Rev_Build!N25+Rev_Build!N36-N13 | O14: =Rev_Build!O25+Rev_Build!O36-O13 | P14: =Rev_Build!P25+Rev_Build!P36-P13 | Q14: =Rev_Build!Q25+Rev_Build!Q36-Q13 | R14: =Rev_Build!R25+Rev_Build!R36-R13 | S14: =Rev_Build!S25+Rev_Build!S36-S13 | T14: =Rev_Build!T25+Rev_Build!T36-T13 | U14: =Rev_Build!U25+Rev_Build!U36-U13 | ... AL14: =Rev_Build!AL25+Rev_Build!AL36-AL13
A15: Net new ARR | B15: GBP k | O15: =O10+O11+O12 | P15: =P10+P11+P12 | Q15: =Q10+Q11+Q12 | R15: =R10+R11+R12 | S15: =S10+S11+S12 | T15: =T10+T11+T12 | U15: =U10+U11+U12 | V15: =V10+V11+V12 | ... AL15: =AL10+AL11+AL12 | AN15: =SUMIF($O$5:$AL$5,AN$5,$O15:$AL15) | AO15: =SUMIF($O$5:$AL$5,AO$5,$O15:$AL15)
A16: ARR growth, year on year | B16: % | O16: =IF(O$3<12,"",O13/INDEX($N13:$AL13,1,O$3-12+1)-1) | P16: =IF(P$3<12,"",P13/INDEX($N13:$AL13,1,P$3-12+1)-1) | Q16: =IF(Q$3<12,"",Q13/INDEX($N13:$AL13,1,Q$3-12+1)-1) | R16: =IF(R$3<12,"",R13/INDEX($N13:$AL13,1,R$3-12+1)-1) | S16: =IF(S$3<12,"",S13/INDEX($N13:$AL13,1,S$3-12+1)-1) | T16: =IF(T$3<12,"",T13/INDEX($N13:$AL13,1,T$3-12+1)-1) | U16: =IF(U$3<12,"",U13/INDEX($N13:$AL13,1,U$3-12+1)-1) | V16: =IF(V$3<12,"",V13/INDEX($N13:$AL13,1,V$3-12+1)-1) | ... AL16: =IF(AL$3<12,"",AL13/INDEX($N13:$AL13,1,AL$3-12+1)-1) | AN16: =INDEX($O16:$AL16,1,AN$5*12) | AO16: =INDEX($O16:$AL16,1,AO$5*12)
A18: Retention (annualised from each month's flows)
A19: Net revenue retention (NRR) | B19: % | O19: =(1+(O11+O12)/O9)^12 | P19: =(1+(P11+P12)/P9)^12 | Q19: =(1+(Q11+Q12)/Q9)^12 | R19: =(1+(R11+R12)/R9)^12 | S19: =(1+(S11+S12)/S9)^12 | T19: =(1+(T11+T12)/T9)^12 | U19: =(1+(U11+U12)/U9)^12 | V19: =(1+(V11+V12)/V9)^12 | ... AL19: =(1+(AL11+AL12)/AL9)^12 | AN19: =INDEX($O19:$AL19,1,AN$5*12) | AO19: =INDEX($O19:$AL19,1,AO$5*12)
A20: Gross revenue retention (GRR) | B20: % | O20: =(1+O12/O9)^12 | P20: =(1+P12/P9)^12 | Q20: =(1+Q12/Q9)^12 | R20: =(1+R12/R9)^12 | S20: =(1+S12/S9)^12 | T20: =(1+T12/T9)^12 | U20: =(1+U12/U9)^12 | V20: =(1+V12/V9)^12 | ... AL20: =(1+AL12/AL9)^12 | AN20: =INDEX($O20:$AL20,1,AN$5*12) | AO20: =INDEX($O20:$AL20,1,AO$5*12)
A21: Logo churn (annualised) | B21: % | O21: =1-(1+Rev_Build!O50/Rev_Build!O48)^12 | P21: =1-(1+Rev_Build!P50/Rev_Build!P48)^12 | Q21: =1-(1+Rev_Build!Q50/Rev_Build!Q48)^12 | R21: =1-(1+Rev_Build!R50/Rev_Build!R48)^12 | S21: =1-(1+Rev_Build!S50/Rev_Build!S48)^12 | T21: =1-(1+Rev_Build!T50/Rev_Build!T48)^12 | U21: =1-(1+Rev_Build!U50/Rev_Build!U48)^12 | V21: =1-(1+Rev_Build!V50/Rev_Build!V48)^12 | ... AL21: =1-(1+Rev_Build!AL50/Rev_Build!AL48)^12 | AN21: =INDEX($O21:$AL21,1,AN$5*12) | AO21: =INDEX($O21:$AL21,1,AO$5*12)
A23: Customer acquisition and unit economics
A24: Sales & marketing spend (cash basis: P&L + capitalised - amortised commission) | B24: GBP k | O24: =IS!O25+Contract_Costs!O10+Contract_Costs!O16 | P24: =IS!P25+Contract_Costs!P10+Contract_Costs!P16 | Q24: =IS!Q25+Contract_Costs!Q10+Contract_Costs!Q16 | R24: =IS!R25+Contract_Costs!R10+Contract_Costs!R16 | S24: =IS!S25+Contract_Costs!S10+Contract_Costs!S16 | T24: =IS!T25+Contract_Costs!T10+Contract_Costs!T16 | U24: =IS!U25+Contract_Costs!U10+Contract_Costs!U16 | V24: =IS!V25+Contract_Costs!V10+Contract_Costs!V16 | ... AL24: =IS!AL25+Contract_Costs!AL10+Contract_Costs!AL16 | AN24: =SUMIF($O$5:$AL$5,AN$5,$O24:$AL24) | AO24: =SUMIF($O$5:$AL$5,AO$5,$O24:$AL24)
A25: New logos | B25: # | O25: =Rev_Build!O49 | P25: =Rev_Build!P49 | Q25: =Rev_Build!Q49 | R25: =Rev_Build!R49 | S25: =Rev_Build!S49 | T25: =Rev_Build!T49 | U25: =Rev_Build!U49 | V25: =Rev_Build!V49 | ... AL25: =Rev_Build!AL49 | AN25: =SUMIF($O$5:$AL$5,AN$5,$O25:$AL25) | AO25: =SUMIF($O$5:$AL$5,AO$5,$O25:$AL25)
A26: CAC per new logo (blended) | B26: GBP k | O26: =O24/O25 | P26: =P24/P25 | Q26: =Q24/Q25 | R26: =R24/R25 | S26: =S24/S25 | T26: =T24/T25 | U26: =U24/U25 | V26: =V24/V25 | ... AL26: =AL24/AL25 | AN26: =AN24/AN25 | AO26: =AO24/AO25
A27: Gross margin | B27: % | O27: =IS!O21 | P27: =IS!P21 | Q27: =IS!Q21 | R27: =IS!R21 | S27: =IS!S21 | T27: =IS!T21 | U27: =IS!U21 | V27: =IS!V21 | ... AL27: =IS!AL21 | AN27: =INDEX($O27:$AL27,1,AN$5*12) | AO27: =INDEX($O27:$AL27,1,AO$5*12)
A28: CAC payback (months of gross-margin on new + expansion ARR) | B28: months | O28: =O24/((O10+O11)*O27/12) | P28: =P24/((P10+P11)*P27/12) | Q28: =Q24/((Q10+Q11)*Q27/12) | R28: =R24/((R10+R11)*R27/12) | S28: =S24/((S10+S11)*S27/12) | T28: =T24/((T10+T11)*T27/12) | U28: =U24/((U10+U11)*U27/12) | V28: =V24/((V10+V11)*V27/12) | ... AL28: =AL24/((AL10+AL11)*AL27/12) | AN28: =INDEX($O28:$AL28,1,AN$5*12) | AO28: =INDEX($O28:$AL28,1,AO$5*12)
A29: ARR per customer | B29: GBP k | O29: =O13/Rev_Build!O51 | P29: =P13/Rev_Build!P51 | Q29: =Q13/Rev_Build!Q51 | R29: =R13/Rev_Build!R51 | S29: =S13/Rev_Build!S51 | T29: =T13/Rev_Build!T51 | U29: =U13/Rev_Build!U51 | V29: =V13/Rev_Build!V51 | ... AL29: =AL13/Rev_Build!AL51 | AN29: =INDEX($O29:$AL29,1,AN$5*12) | AO29: =INDEX($O29:$AL29,1,AO$5*12)
A30: Customer lifetime value (ARPA x GM / logo churn) | B30: GBP k | O30: =O29*O27/O21 | P30: =P29*P27/P21 | Q30: =Q29*Q27/Q21 | R30: =R29*R27/R21 | S30: =S29*S27/S21 | T30: =T29*T27/T21 | U30: =U29*U27/U21 | V30: =V29*V27/V21 | ... AL30: =AL29*AL27/AL21 | AN30: =INDEX($O30:$AL30,1,AN$5*12) | AO30: =INDEX($O30:$AL30,1,AO$5*12)
A31: LTV / CAC | B31: x | O31: =O30/O26 | P31: =P30/P26 | Q31: =Q30/Q26 | R31: =R30/R26 | S31: =S30/S26 | T31: =T30/T26 | U31: =U30/U26 | V31: =V30/V26 | ... AL31: =AL30/AL26 | AN31: =INDEX($O31:$AL31,1,AN$5*12) | AO31: =INDEX($O31:$AL31,1,AO$5*12)
A32: Magic number (3m net new ARR / prior 3m S&M) | B32: x | O32: =IF(O$3<6,"",SUM(M15:O15)/SUM(J24:L24)) | P32: =IF(P$3<6,"",SUM(N15:P15)/SUM(K24:M24)) | Q32: =IF(Q$3<6,"",SUM(O15:Q15)/SUM(L24:N24)) | R32: =IF(R$3<6,"",SUM(P15:R15)/SUM(M24:O24)) | S32: =IF(S$3<6,"",SUM(Q15:S15)/SUM(N24:P24)) | T32: =IF(T$3<6,"",SUM(R15:T15)/SUM(O24:Q24)) | U32: =IF(U$3<6,"",SUM(S15:U15)/SUM(P24:R24)) | V32: =IF(V$3<6,"",SUM(T15:V15)/SUM(Q24:S24)) | ... AL32: =IF(AL$3<6,"",SUM(AJ15:AL15)/SUM(AG24:AI24)) | AN32: =INDEX($O32:$AL32,1,AN$5*12) | AO32: =INDEX($O32:$AL32,1,AO$5*12)
A34: Cash efficiency
A35: Net burn (positive = cash consumed) | B35: GBP k | O35: =-CF!O22 | P35: =-CF!P22 | Q35: =-CF!Q22 | R35: =-CF!R22 | S35: =-CF!S22 | T35: =-CF!T22 | U35: =-CF!U22 | V35: =-CF!V22 | ... AL35: =-CF!AL22 | AN35: =SUMIF($O$5:$AL$5,AN$5,$O35:$AL35) | AO35: =SUMIF($O$5:$AL$5,AO$5,$O35:$AL35)
A36: Burn multiple (net burn / net new ARR) | B36: x | O36: =IF(O15<=0,"n/a",MAX(0,O35)/O15) | P36: =IF(P15<=0,"n/a",MAX(0,P35)/P15) | Q36: =IF(Q15<=0,"n/a",MAX(0,Q35)/Q15) | R36: =IF(R15<=0,"n/a",MAX(0,R35)/R15) | S36: =IF(S15<=0,"n/a",MAX(0,S35)/S15) | T36: =IF(T15<=0,"n/a",MAX(0,T35)/T15) | U36: =IF(U15<=0,"n/a",MAX(0,U35)/U15) | V36: =IF(V15<=0,"n/a",MAX(0,V35)/V15) | ... AL36: =IF(AL15<=0,"n/a",MAX(0,AL35)/AL15) | AN36: =INDEX($O36:$AL36,1,AN$5*12) | AO36: =INDEX($O36:$AL36,1,AO$5*12)
A37: Closing cash | B37: GBP k | O37: =BS!O9 | P37: =BS!P9 | Q37: =BS!Q9 | R37: =BS!R9 | S37: =BS!S9 | T37: =BS!T9 | U37: =BS!U9 | V37: =BS!V9 | ... AL37: =BS!AL9 | AN37: =INDEX($O37:$AL37,1,AN$5*12) | AO37: =INDEX($O37:$AL37,1,AO$5*12)
A38: Cash runway (months at trailing 3m average burn) | B38: months | O38: =IF(AVERAGE(M35:O35)<=0,"n/a",O37/AVERAGE(M35:O35)) | P38: =IF(AVERAGE(N35:P35)<=0,"n/a",P37/AVERAGE(N35:P35)) | Q38: =IF(AVERAGE(O35:Q35)<=0,"n/a",Q37/AVERAGE(O35:Q35)) | R38: =IF(AVERAGE(P35:R35)<=0,"n/a",R37/AVERAGE(P35:R35)) | S38: =IF(AVERAGE(Q35:S35)<=0,"n/a",S37/AVERAGE(Q35:S35)) | T38: =IF(AVERAGE(R35:T35)<=0,"n/a",T37/AVERAGE(R35:T35)) | U38: =IF(AVERAGE(S35:U35)<=0,"n/a",U37/AVERAGE(S35:U35)) | V38: =IF(AVERAGE(T35:V35)<=0,"n/a",V37/AVERAGE(T35:V35)) | ... AL38: =IF(AVERAGE(AJ35:AL35)<=0,"n/a",AL37/AVERAGE(AJ35:AL35)) | AN38: =INDEX($O38:$AL38,1,AN$5*12) | AO38: =INDEX($O38:$AL38,1,AO$5*12)
A39: Rule of 40 (ARR growth + EBITDA margin) | B39: % | O39: =IF(O$3<12,"",O16+IS!O30) | P39: =IF(P$3<12,"",P16+IS!P30) | Q39: =IF(Q$3<12,"",Q16+IS!Q30) | R39: =IF(R$3<12,"",R16+IS!R30) | S39: =IF(S$3<12,"",S16+IS!S30) | T39: =IF(T$3<12,"",T16+IS!T30) | U39: =IF(U$3<12,"",U16+IS!U30) | V39: =IF(V$3<12,"",V16+IS!V30) | ... AL39: =IF(AL$3<12,"",AL16+IS!AL30) | AN39: =INDEX($O39:$AL39,1,AN$5*12) | AO39: =INDEX($O39:$AL39,1,AO$5*12)
A40: ARR per FTE | B40: GBP k | O40: =O13/Headcount_Opex!O33 | P40: =P13/Headcount_Opex!P33 | Q40: =Q13/Headcount_Opex!Q33 | R40: =R13/Headcount_Opex!R33 | S40: =S13/Headcount_Opex!S33 | T40: =T13/Headcount_Opex!T33 | U40: =U13/Headcount_Opex!U33 | V40: =V13/Headcount_Opex!V33 | ... AL40: =AL13/Headcount_Opex!AL33 | AN40: =INDEX($O40:$AL40,1,AN$5*12) | AO40: =INDEX($O40:$AL40,1,AO$5*12)
A43: What moves each metric (levers). Quantified lever impacts arrive in Lever_Analysis (Phase 2).
A44: ARR growth | C44: inp_logos_ent / inp_logos_mid (volume), inp_acv_* and inp_price_uplift (price), inp_churn_* and inp_exp_* (existing base)
A45: NRR | C45: inp_exp_ent / inp_exp_mid (up), inp_churn_ent / inp_churn_mid (down). Mix shifts toward Enterprise raise it
A46: GRR | C46: inp_churn_ent and inp_churn_mid only
A47: CAC | C47: inp_hires_sm and inp_sal_sm (team cost), inp_marketing_m, inp_commission_pct, new-logo volume
A48: CAC payback | C48: CAC levers, plus gross margin and gross new ARR (new logos, ACV, expansion)
A49: LTV / CAC | C49: ARR per customer, gross margin, logo churn (inp_churn_*) and every CAC lever
A50: Burn multiple | C50: Net burn (opex, hiring, collections via inp_dso) over net new ARR (growth and churn levers)
A51: Rule of 40 | C51: ARR growth levers plus EBITDA margin (hiring plan, hosting cost per customer, marketing spend)
A52: Cash runway | C52: Cash balance and burn: hiring plan, DSO, churn, new logos, billing terms
A53: Gross margin | C53: inp_host_ent / inp_host_mid, inp_licence_pct, inp_hires_cs, inp_sal_cs, inp_services_cost_pct

Sheet LT_Model
A1: LT_Model - five-year view (years 1-2 from the monthly model, years 3-5 driver-based)
A2: GBP thousands. Years 1-2 are links to the monthly tabs; years 3-5 use the inp_lt_* drivers. Simplified cash view: no interest income, no full balance sheet.
A4: Year | B4: Unit | C4: ="FY"&(YEAR(inp_model_start)+C5-1) | D4: ="FY"&(YEAR(inp_model_start)+D5-1) | E4: ="FY"&(YEAR(inp_model_start)+E5-1) | F4: ="FY"&(YEAR(inp_model_start)+F5-1) | G4: ="FY"&(YEAR(inp_model_start)+G5-1)
A5: Year index | C5: =COLUMN()-COLUMN($B$1) | D5: =COLUMN()-COLUMN($B$1) | E5: =COLUMN()-COLUMN($B$1) | F5: =COLUMN()-COLUMN($B$1) | G5: =COLUMN()-COLUMN($B$1)
A7: ARR
A8: Opening ARR | B8: GBP k | C8: =Rev_Build!AN43 | D8: =Rev_Build!AO43 | E8: =D12 | F8: =E12 | G8: =F12
A9: + New logos | B9: GBP k | C9: =Rev_Build!AN44 | D9: =Rev_Build!AO44 | E9: =D9*(1+inp_lt_newarr_growth) | F9: =E9*(1+inp_lt_newarr_growth) | G9: =F9*(1+inp_lt_newarr_growth)
A10: + Expansion | B10: GBP k | C10: =Rev_Build!AN45 | D10: =Rev_Build!AO45 | E10: =E8*E13 | F10: =F8*F13 | G10: =G8*G13
A11: - Churn | B11: GBP k | C11: =Rev_Build!AN46 | D11: =Rev_Build!AO46 | E11: =-E8*E14 | F11: =-F8*F14 | G11: =-G8*G14
A12: Closing ARR | B12: GBP k | C12: =Rev_Build!AN47 | D12: =Rev_Build!AO47 | E12: =SUM(E8:E11) | F12: =SUM(F8:F11) | G12: =SUM(G8:G11)
A13: Expansion rate (% of opening ARR) | B13: % | C13: =C10/C8 | D13: =D10/D8 | E13: =D13+inp_lt_nrr_step | F13: =E13+inp_lt_nrr_step | G13: =F13+inp_lt_nrr_step
A14: Gross churn rate (% of opening ARR) | B14: % | C14: =-C11/C8 | D14: =-D11/D8 | E14: =D14 | F14: =E14 | G14: =F14
A15: ARR growth | B15: % | C15: =C12/C8-1 | D15: =D12/D8-1 | E15: =E12/E8-1 | F15: =F12/F8-1 | G15: =G12/G8-1
A16: Net revenue retention | B16: % | C16: =1+(C10+C11)/C8 | D16: =1+(D10+D11)/D8 | E16: =1+(E10+E11)/E8 | F16: =1+(F10+F11)/F8 | G16: =1+(G10+G11)/G8
A18: Income statement
A19: Revenue | B19: GBP k | C19: =IS!AN12 | D19: =IS!AO12 | E19: =(E8+E12)/2*E20 | F19: =(F8+F12)/2*F20 | G19: =(G8+G12)/2*G20
A20: Revenue / average ARR | B20: x | C20: =C19/((C8+C12)/2) | D20: =D19/((D8+D12)/2) | E20: =D20 | F20: =E20 | G20: =F20
A21: Gross margin | B21: % | C21: =IS!AN21 | D21: =IS!AO21 | E21: =D21+inp_lt_gm_step | F21: =E21+inp_lt_gm_step | G21: =F21+inp_lt_gm_step
A22: Gross profit | B22: GBP k | C22: =IS!AN20 | D22: =IS!AO20 | E22: =E19*E21 | F22: =F19*F21 | G22: =G19*G21
A23: R&D as % of revenue | B23: % | C23: =C24/C19 | D23: =D24/D19 | E23: =D23-inp_lt_rd_step | F23: =E23-inp_lt_rd_step | G23: =F23-inp_lt_rd_step
A24: R&D expense | B24: GBP k | C24: =IS!AN24 | D24: =IS!AO24 | E24: =E19*E23 | F24: =F19*F23 | G24: =G19*G23
A25: S&M as % of revenue | B25: % | C25: =C26/C19 | D25: =D26/D19 | E25: =D25-inp_lt_sm_step | F25: =E25-inp_lt_sm_step | G25: =F25-inp_lt_sm_step
A26: S&M expense | B26: GBP k | C26: =IS!AN25 | D26: =IS!AO25 | E26: =E19*E25 | F26: =F19*F25 | G26: =G19*G25
A27: G&A as % of revenue | B27: % | C27: =C28/C19 | D27: =D28/D19 | E27: =D27-inp_lt_ga_step | F27: =E27-inp_lt_ga_step | G27: =F27-inp_lt_ga_step
A28: G&A expense | B28: GBP k | C28: =IS!AN26 | D28: =IS!AO26 | E28: =E19*E27 | F28: =F19*F27 | G28: =G19*G27
A29: EBITDA | B29: GBP k | C29: =C22-C24-C26-C28 | D29: =D22-D24-D26-D28 | E29: =E22-E24-E26-E28 | F29: =F22-F24-F26-F28 | G29: =G22-G24-G26-G28
A30: EBITDA margin | B30: % | C30: =C29/C19 | D30: =D29/D19 | E30: =E29/E19 | F30: =F29/F19 | G30: =G29/G19
A31: Depreciation as % of revenue | B31: % | C31: =C32/C19 | D31: =D32/D19 | E31: =D31 | F31: =E31 | G31: =F31
A32: Depreciation | B32: GBP k | C32: =IS!AN31 | D32: =IS!AO31 | E32: =E19*E31 | F32: =F19*F31 | G32: =G19*G31
A33: Tax (on EBITDA less depreciation, if positive) | B33: GBP k | C33: =IS!AN35 | D33: =IS!AO35 | E33: =MAX(0,E29-E32)*inp_tax | F33: =MAX(0,F29-F32)*inp_tax | G33: =MAX(0,G29-G32)*inp_tax
A35: Cash (simplified)
A36: Capex | B36: GBP k | C36: =BS!AN27 | D36: =BS!AO27 | E36: =E19*inp_capex_pct | F36: =F19*inp_capex_pct | G36: =G19*inp_capex_pct
A37: Deferred revenue as % of closing ARR | B37: % | C37: =C38/C12 | D37: =D38/D12 | E37: =D37 | F37: =E37 | G37: =F37
A38: Deferred revenue (closing) | B38: GBP k | C38: =BS!AN17 | D38: =BS!AO17 | E38: =E12*E37 | F38: =F12*F37 | G38: =G12*G37
A39: Receivables as % of closing ARR | B39: % | C39: =C40/C12 | D39: =D40/D12 | E39: =D39 | F39: =E39 | G39: =F39
A40: Receivables (closing) | B40: GBP k | C40: =BS!AN10 | D40: =BS!AO10 | E40: =E12*E39 | F40: =F12*F39 | G40: =G12*G39
A41: Contract-cost asset as % of closing ARR | B41: % | C41: =C42/C12 | D41: =D42/D12 | E41: =D41 | F41: =E41 | G41: =F41
A42: Capitalised contract costs (closing) | B42: GBP k | C42: =BS!AN12 | D42: =BS!AO12 | E42: =E12*E41 | F42: =F12*F41 | G42: =G12*G41
A43: Free cash flow | B43: GBP k | C43: =CF!AN22 | D43: =CF!AO22 | E43: =E29-E33-E36+(E38-D38)-(E40-D40)-(E42-D42) | F43: =F29-F33-F36+(F38-E38)-(F40-E40)-(F42-E42) | G43: =G29-G33-G36+(G38-F38)-(G40-F40)-(G42-F42)
A44: Closing cash | B44: GBP k | C44: =CF!AN24 | D44: =CF!AO24 | E44: =D44+E43 | F44: =E44+F43 | G44: =F44+G43
A46: Headline metrics
A47: Burn multiple | B47: x | C47: =IF((C12-C8)<=0,"n/a",MAX(0,-C43)/(C12-C8)) | D47: =IF((D12-D8)<=0,"n/a",MAX(0,-D43)/(D12-D8)) | E47: =IF((E12-E8)<=0,"n/a",MAX(0,-E43)/(E12-E8)) | F47: =IF((F12-F8)<=0,"n/a",MAX(0,-F43)/(F12-F8)) | G47: =IF((G12-G8)<=0,"n/a",MAX(0,-G43)/(G12-G8))
A48: Rule of 40 (ARR growth + EBITDA margin) | B48: % | C48: =C15+C30 | D48: =D15+D30 | E48: =E15+E30 | F48: =F15+F30 | G48: =G15+G30

Sheet Inputs_Budget
A1: Inputs_Budget - board-approved FY1 budget, as received
A2: Board-pack layout: GBP millions, quarters across, costs shown as negatives, different line names from the model. Mapped on Budget_vs_Forecast. Totals are the only formulas.
A4: GBP m | B4: Q1 | C4: Q2 | D4: Q3 | E4: Q4 | F4: FY
A5: Subscription revenue | B5: 10.7 | C5: 11.55 | D5: 12.45 | E5: 13.35 | F5: =SUM(B5:E5)
A6: Professional services revenue | B6: 0.25 | C6: 0.3 | D6: 0.3 | E6: 0.3 | F6: =SUM(B6:E6)
A7: Total revenue | B7: =B5+B6 | C7: =C5+C6 | D7: =D5+D6 | E7: =E5+E6 | F7: =SUM(B7:E7)
A8: Cost of sales | B8: -2.55 | C8: -2.75 | D8: -2.9 | E8: -3.05 | F8: =SUM(B8:E8)
A9: Gross profit | B9: =B7+B8 | C9: =C7+C8 | D9: =D7+D8 | E9: =E7+E8 | F9: =SUM(B9:E9)
A10: Sales & marketing | B10: -4.8 | C10: -4.95 | D10: -5.1 | E10: -5.25 | F10: =SUM(B10:E10)
A11: Research & development | B11: -3.75 | C11: -3.9 | D11: -4.05 | E11: -4.2 | F11: =SUM(B11:E11)
A12: General & administrative | B12: -1.85 | C12: -1.9 | D12: -1.95 | E12: -2 | F12: =SUM(B12:E12)
A13: Total operating costs | B13: =SUM(B10:B12) | C13: =SUM(C10:C12) | D13: =SUM(D10:D12) | E13: =SUM(E10:E12) | F13: =SUM(B13:E13)
A14: EBITDA | B14: =B9+B13 | C14: =C9+C13 | D14: =D9+D13 | E14: =E9+E13 | F14: =SUM(B14:E14)
A16: Operating KPIs, full year (GBP m unless stated)
A17: Opening ARR | B17: 40
A18: New-customer ARR | B18: 12.93
A19: Expansion ARR | B19: 4.5
A20: Churned ARR | B20: -2.9
A21: Closing ARR | B21: =SUM(B17:B20)
A22: New customers (number) | B22: 226
A23: Closing headcount (FTE) | B23: 485

Sheet Budget_vs_Forecast
A1: Budget_vs_Forecast - FY1 budget mapped to the model, with variance bridges
A2: GBP thousands. Budget (GBP m, costs negative) x 1,000 vs model forecast on the same sign basis. Variance = forecast - budget, so a positive number is favourable on every line.
A3: Treat a variance within this % of budget as 'On budget' | B3: 0.005
A4: FY1 P&L | B4: Budget | C4: Forecast | D4: Variance | E4: Var % | F4: Flag | G4: Commentary (owner)
A5: Subscription revenue | B5: =Inputs_Budget!F5*1000 | C5: =IS!AN9+IS!AN10 | D5: =C5-B5 | E5: =IF(B5=0,0,D5/ABS(B5)) | F5: =IF(ABS(E5)<$B$3,"On budget",IF(D5>0,"Favourable","Adverse")) | G5: Budget assumed faster new-logo conversion and lower early-year churn than the forecast; see the ARR bridge below.
A6: Professional services revenue | B6: =Inputs_Budget!F6*1000 | C6: =IS!AN11 | D6: =C6-B6 | E6: =IF(B6=0,0,D6/ABS(B6)) | F6: =IF(ABS(E6)<$B$3,"On budget",IF(D6>0,"Favourable","Adverse")) | G6: Implementation fees follow Enterprise new-logo volume.
A7: Total revenue | B7: =B5+B6 | C7: =C5+C6 | D7: =C7-B7 | E7: =IF(B7=0,0,D7/ABS(B7)) | F7: =IF(ABS(E7)<$B$3,"On budget",IF(D7>0,"Favourable","Adverse"))
A8: Cost of sales | B8: =Inputs_Budget!F8*1000 | C8: =-IS!AN19 | D8: =C8-B8 | E8: =IF(B8=0,0,D8/ABS(B8)) | F8: =IF(ABS(E8)<$B$3,"On budget",IF(D8>0,"Favourable","Adverse")) | G8: Hosting and Customer Success run slightly above the budgeted unit costs.
A9: Gross profit | B9: =B7+B8 | C9: =C7+C8 | D9: =C9-B9 | E9: =IF(B9=0,0,D9/ABS(B9)) | F9: =IF(ABS(E9)<$B$3,"On budget",IF(D9>0,"Favourable","Adverse"))
A10: Sales & marketing | B10: =Inputs_Budget!F10*1000 | C10: =-IS!AN25 | D10: =C10-B10 | E10: =IF(B10=0,0,D10/ABS(B10)) | F10: =IF(ABS(E10)<$B$3,"On budget",IF(D10>0,"Favourable","Adverse")) | G10: Favourable largely because commission is now capitalised (IFRS 15); cash S&M is higher than the P&L shows.
A11: Research & development | B11: =Inputs_Budget!F11*1000 | C11: =-IS!AN24 | D11: =C11-B11 | E11: =IF(B11=0,0,D11/ABS(B11)) | F11: =IF(ABS(E11)<$B$3,"On budget",IF(D11>0,"Favourable","Adverse")) | G11: Hiring ahead of the budgeted profile.
A12: General & administrative | B12: =Inputs_Budget!F12*1000 | C12: =-IS!AN26 | D12: =C12-B12 | E12: =IF(B12=0,0,D12/ABS(B12)) | F12: =IF(ABS(E12)<$B$3,"On budget",IF(D12>0,"Favourable","Adverse")) | G12: Professional fees and G&A hiring above budget.
A13: Total operating costs | B13: =SUM(B10:B12) | C13: =SUM(C10:C12) | D13: =C13-B13 | E13: =IF(B13=0,0,D13/ABS(B13)) | F13: =IF(ABS(E13)<$B$3,"On budget",IF(D13>0,"Favourable","Adverse"))
A14: EBITDA | B14: =B9+B13 | C14: =C9+C13 | D14: =C14-B14 | E14: =IF(B14=0,0,D14/ABS(B14)) | F14: =IF(ABS(E14)<$B$3,"On budget",IF(D14>0,"Favourable","Adverse")) | G14: Net of the above.
A16: Variance by quarter (forecast - budget, GBP k)
A17: Line | B17: Q1 | C17: Q2 | D17: Q3 | E17: Q4 | F17: FY1
A18: Subscription revenue | B18: =(SUMIF(IS!$O$6:$AL$6,COLUMN()-COLUMN($A$1),IS!$O$9:$AL$9)+SUMIF(IS!$O$6:$AL$6,COLUMN()-COLUMN($A$1),IS!$O$10:$AL$10))-Inputs_Budget!B5*1000 | C18: =(SUMIF(IS!$O$6:$AL$6,COLUMN()-COLUMN($A$1),IS!$O$9:$AL$9)+SUMIF(IS!$O$6:$AL$6,COLUMN()-COLUMN($A$1),IS!$O$10:$AL$10))-Inputs_Budget!C5*1000 | D18: =(SUMIF(IS!$O$6:$AL$6,COLUMN()-COLUMN($A$1),IS!$O$9:$AL$9)+SUMIF(IS!$O$6:$AL$6,COLUMN()-COLUMN($A$1),IS!$O$10:$AL$10))-Inputs_Budget!D5*1000 | E18: =(SUMIF(IS!$O$6:$AL$6,COLUMN()-COLUMN($A$1),IS!$O$9:$AL$9)+SUMIF(IS!$O$6:$AL$6,COLUMN()-COLUMN($A$1),IS!$O$10:$AL$10))-Inputs_Budget!E5*1000 | F18: =SUM(B18:E18)
A19: Professional services revenue | B19: =(SUMIF(IS!$O$6:$AL$6,COLUMN()-COLUMN($A$1),IS!$O$11:$AL$11))-Inputs_Budget!B6*1000 | C19: =(SUMIF(IS!$O$6:$AL$6,COLUMN()-COLUMN($A$1),IS!$O$11:$AL$11))-Inputs_Budget!C6*1000 | D19: =(SUMIF(IS!$O$6:$AL$6,COLUMN()-COLUMN($A$1),IS!$O$11:$AL$11))-Inputs_Budget!D6*1000 | E19: =(SUMIF(IS!$O$6:$AL$6,COLUMN()-COLUMN($A$1),IS!$O$11:$AL$11))-Inputs_Budget!E6*1000 | F19: =SUM(B19:E19)
A20: Cost of sales | B20: =-(SUMIF(IS!$O$6:$AL$6,COLUMN()-COLUMN($A$1),IS!$O$19:$AL$19))-Inputs_Budget!B8*1000 | C20: =-(SUMIF(IS!$O$6:$AL$6,COLUMN()-COLUMN($A$1),IS!$O$19:$AL$19))-Inputs_Budget!C8*1000 | D20: =-(SUMIF(IS!$O$6:$AL$6,COLUMN()-COLUMN($A$1),IS!$O$19:$AL$19))-Inputs_Budget!D8*1000 | E20: =-(SUMIF(IS!$O$6:$AL$6,COLUMN()-COLUMN($A$1),IS!$O$19:$AL$19))-Inputs_Budget!E8*1000 | F20: =SUM(B20:E20)
A21: Sales & marketing | B21: =-(SUMIF(IS!$O$6:$AL$6,COLUMN()-COLUMN($A$1),IS!$O$25:$AL$25))-Inputs_Budget!B10*1000 | C21: =-(SUMIF(IS!$O$6:$AL$6,COLUMN()-COLUMN($A$1),IS!$O$25:$AL$25))-Inputs_Budget!C10*1000 | D21: =-(SUMIF(IS!$O$6:$AL$6,COLUMN()-COLUMN($A$1),IS!$O$25:$AL$25))-Inputs_Budget!D10*1000 | E21: =-(SUMIF(IS!$O$6:$AL$6,COLUMN()-COLUMN($A$1),IS!$O$25:$AL$25))-Inputs_Budget!E10*1000 | F21: =SUM(B21:E21)
A22: Research & development | B22: =-(SUMIF(IS!$O$6:$AL$6,COLUMN()-COLUMN($A$1),IS!$O$24:$AL$24))-Inputs_Budget!B11*1000 | C22: =-(SUMIF(IS!$O$6:$AL$6,COLUMN()-COLUMN($A$1),IS!$O$24:$AL$24))-Inputs_Budget!C11*1000 | D22: =-(SUMIF(IS!$O$6:$AL$6,COLUMN()-COLUMN($A$1),IS!$O$24:$AL$24))-Inputs_Budget!D11*1000 | E22: =-(SUMIF(IS!$O$6:$AL$6,COLUMN()-COLUMN($A$1),IS!$O$24:$AL$24))-Inputs_Budget!E11*1000 | F22: =SUM(B22:E22)
A23: General & administrative | B23: =-(SUMIF(IS!$O$6:$AL$6,COLUMN()-COLUMN($A$1),IS!$O$26:$AL$26))-Inputs_Budget!B12*1000 | C23: =-(SUMIF(IS!$O$6:$AL$6,COLUMN()-COLUMN($A$1),IS!$O$26:$AL$26))-Inputs_Budget!C12*1000 | D23: =-(SUMIF(IS!$O$6:$AL$6,COLUMN()-COLUMN($A$1),IS!$O$26:$AL$26))-Inputs_Budget!D12*1000 | E23: =-(SUMIF(IS!$O$6:$AL$6,COLUMN()-COLUMN($A$1),IS!$O$26:$AL$26))-Inputs_Budget!E12*1000 | F23: =SUM(B23:E23)
A24: EBITDA variance | B24: =B18+B19+B20+B21+B22+B23 | C24: =C18+C19+C20+C21+C22+C23 | D24: =D18+D19+D20+D21+D22+D23 | E24: =E18+E19+E20+E21+E22+E23 | F24: =F18+F19+F20+F21+F22+F23
A26: FY1 ARR drivers: budget vs forecast (GBP k)
A27: Driver | B27: Budget | C27: Forecast | D27: Variance
A28: Opening ARR | B28: =Inputs_Budget!B17*1000 | C28: =Rev_Build!AN43 | D28: =C28-B28
A29: New-customer ARR | B29: =Inputs_Budget!B18*1000 | C29: =Rev_Build!AN44 | D29: =C29-B29
A30: Expansion ARR | B30: =Inputs_Budget!B19*1000 | C30: =Rev_Build!AN45 | D30: =C30-B30
A31: Churned ARR | B31: =Inputs_Budget!B20*1000 | C31: =Rev_Build!AN46 | D31: =C31-B31
A32: Closing ARR | B32: =SUM(B28:B31) | C32: =SUM(C28:C31) | D32: =C32-B32
A33: New customers (number) | B33: =Inputs_Budget!B22 | C33: =Rev_Build!AN49 | D33: =C33-B33
A34: Average ACV of new customers | B34: =B29/B33 | C34: =C29/C33 | D34: =C34-B34
A35: Closing headcount (FTE) | B35: =Inputs_Budget!B23 | C35: =Headcount_Opex!AN33 | D35: =C35-B35
A37: Bridge 1: FY1 closing ARR, budget to forecast (GBP k)
A38: Step | B38: GBP k | C38: Cumulative | G38: How it is calculated
A39: Budget closing ARR | B39: =B32 | C39: =B39 | G39: Budget
A40: Opening ARR difference | B40: =C28-B28 | C40: =C39+B40 | G40: Forecast opening ARR - budget opening ARR
A41: Volume: number of new customers | B41: =(C33-B33)*B34 | C41: =C40+B41 | G41: (forecast customers - budget customers) x budget ACV
A42: Price: ACV of new customers | B42: =C33*(C34-B34) | C42: =C41+B42 | G42: forecast customers x (forecast ACV - budget ACV)
A43: Expansion | B43: =C30-B30 | C43: =C42+B43 | G43: Forecast expansion - budget expansion
A44: Churn | B44: =C31-B31 | C44: =C43+B44 | G44: Forecast churn - budget churn (negative = more churn than budget)
A45: Forecast closing ARR | B45: =C32 | C45: =C44 | G45: Bridge ends here; tie-out below must be zero
A47: Bridge 2: FY1 revenue, budget to forecast (GBP k)
A48: Step | B48: GBP k | C48: Cumulative | G48: How it is calculated
A49: Budget revenue | B49: =B7 | C49: =B49 | G49: Budget
A50: Volume | B50: =B41*0.5 | C50: =C49+B50 | G50: ARR volume effect x 0.5: flows land mid-year on average, so about half reaches FY1 revenue
A51: Price | B51: =B42*0.5 | C51: =C50+B51 | G51: ARR price effect x 0.5 (same mid-year convention)
A52: Expansion | B52: =B43*0.5 | C52: =C51+B52 | G52: ARR expansion effect x 0.5
A53: Churn | B53: =B44*0.5 | C53: =C52+B53 | G53: ARR churn effect x 0.5
A54: Timing / other (residual) | B54: =C7-C53 | C54: =C53+B54 | G54: Billing-to-revenue timing, implementation fees, intra-year phasing: whatever the ARR effects do not explain
A55: Forecast revenue | B55: =C7 | C55: =C54
A57: Bridge 3: FY1 EBITDA, budget to forecast (GBP k)
A58: Step | B58: GBP k | C58: Cumulative | G58: How it is calculated
A59: Budget EBITDA | B59: =B14 | C59: =B59 | G59: Budget
A60: Revenue | B60: =D7 | C60: =C59+B60 | G60: Total revenue variance
A61: Cost of sales | B61: =D8 | C61: =C60+B61 | G61: Positive = lower cost than budget
A62: Sales & marketing | B62: =D10 | C62: =C61+B62 | G62: Includes the effect of capitalising commission
A63: Research & development | B63: =D11 | C63: =C62+B63
A64: General & administrative | B64: =D12 | C64: =C63+B64
A65: Forecast EBITDA | B65: =C14 | C65: =C64

Sheet Lever_Analysis
A1: Lever_Analysis - which drivers move each metric, and by how much
A2: Static, engine-run: each driver is moved one step down and up with everything else at Base, and the whole workbook is recalculated (validation/snapshots.py). Grey italic = pasted engine output. Section A shows whether the snapshot still matches the live model.
A4: A. Snapshot check: live model vs Base snapshot
A5: Metric | B5: Live | C5: Snapshot | D5: Gap | E5: Status
A6: FY1 revenue | B6: =IS!AN12 | C6: 48367.078 | D6: =IF(ISNUMBER(B6),B6-C6,0) | E6: =IF(inp_scenario<>"Base","switch to Base to check",IF(ABS(D6)<=IF(ABS(C6)<10,chk_tol/100,chk_tol),"OK","STALE"))
A7: FY2 revenue | B7: =IS!AO12 | C7: 62987.254 | D7: =IF(ISNUMBER(B7),B7-C7,0) | E7: =IF(inp_scenario<>"Base","switch to Base to check",IF(ABS(D7)<=IF(ABS(C7)<10,chk_tol/100,chk_tol),"OK","STALE"))
A8: FY1 EBITDA | B8: =IS!AN29 | C8: -6972.479 | D8: =IF(ISNUMBER(B8),B8-C8,0) | E8: =IF(inp_scenario<>"Base","switch to Base to check",IF(ABS(D8)<=IF(ABS(C8)<10,chk_tol/100,chk_tol),"OK","STALE"))
A9: FY2 EBITDA | B9: =IS!AO29 | C9: -3129.3066 | D9: =IF(ISNUMBER(B9),B9-C9,0) | E9: =IF(inp_scenario<>"Base","switch to Base to check",IF(ABS(D9)<=IF(ABS(C9)<10,chk_tol/100,chk_tol),"OK","STALE"))
A10: ARR, month 12 | B10: =SaaS_Metrics!Z13 | C10: 53403.649 | D10: =IF(ISNUMBER(B10),B10-C10,0) | E10: =IF(inp_scenario<>"Base","switch to Base to check",IF(ABS(D10)<=IF(ABS(C10)<10,chk_tol/100,chk_tol),"OK","STALE"))
A11: ARR, month 24 | B11: =SaaS_Metrics!AL13 | C11: 68321.239 | D11: =IF(ISNUMBER(B11),B11-C11,0) | E11: =IF(inp_scenario<>"Base","switch to Base to check",IF(ABS(D11)<=IF(ABS(C11)<10,chk_tol/100,chk_tol),"OK","STALE"))
A12: ARR growth, month 12 | B12: =SaaS_Metrics!Z16 | C12: 0.33509122 | D12: =IF(ISNUMBER(B12),B12-C12,0) | E12: =IF(inp_scenario<>"Base","switch to Base to check",IF(ABS(D12)<=IF(ABS(C12)<10,chk_tol/100,chk_tol),"OK","STALE"))
A13: NRR (annualised), month 12 | B13: =SaaS_Metrics!Z19 | C13: 1.0276837 | D13: =IF(ISNUMBER(B13),B13-C13,0) | E13: =IF(inp_scenario<>"Base","switch to Base to check",IF(ABS(D13)<=IF(ABS(C13)<10,chk_tol/100,chk_tol),"OK","STALE"))
A14: GRR (annualised), month 12 | B14: =SaaS_Metrics!Z20 | C14: 0.91979261 | D14: =IF(ISNUMBER(B14),B14-C14,0) | E14: =IF(inp_scenario<>"Base","switch to Base to check",IF(ABS(D14)<=IF(ABS(C14)<10,chk_tol/100,chk_tol),"OK","STALE"))
A15: CAC payback (months), month 12 | B15: =SaaS_Metrics!Z28 | C15: 18.828614 | D15: =IF(ISNUMBER(B15),B15-C15,0) | E15: =IF(inp_scenario<>"Base","switch to Base to check",IF(ABS(D15)<=IF(ABS(C15)<10,chk_tol/100,chk_tol),"OK","STALE"))
A16: LTV / CAC, month 12 | B16: =SaaS_Metrics!Z31 | C16: 4.5027222 | D16: =IF(ISNUMBER(B16),B16-C16,0) | E16: =IF(inp_scenario<>"Base","switch to Base to check",IF(ABS(D16)<=IF(ABS(C16)<10,chk_tol/100,chk_tol),"OK","STALE"))
A17: Cash, month 24 | B17: =BS!AL9 | C17: 22579.061 | D17: =IF(ISNUMBER(B17),B17-C17,0) | E17: =IF(inp_scenario<>"Base","switch to Base to check",IF(ABS(D17)<=IF(ABS(C17)<10,chk_tol/100,chk_tol),"OK","STALE"))
A18: Lowest month-end cash | B18: =Sensitivity!B4 | C18: 20882.233 | D18: =IF(ISNUMBER(B18),B18-C18,0) | E18: =IF(inp_scenario<>"Base","switch to Base to check",IF(ABS(D18)<=IF(ABS(C18)<10,chk_tol/100,chk_tol),"OK","STALE"))
A19: Headcount (FTE), month 24 | B19: =Headcount_Opex!AL33 | C19: 587.2 | D19: =IF(ISNUMBER(B19),B19-C19,0) | E19: =IF(inp_scenario<>"Base","switch to Base to check",IF(ABS(D19)<=IF(ABS(C19)<10,chk_tol/100,chk_tol),"OK","STALE"))
A20: Rule of 40, month 24 | B20: =SaaS_Metrics!AL39 | C20: 0.27355604 | D20: =IF(ISNUMBER(B20),B20-C20,0) | E20: =IF(inp_scenario<>"Base","switch to Base to check",IF(ABS(D20)<=IF(ABS(C20)<10,chk_tol/100,chk_tol),"OK","STALE"))
A21: Deal value created (NPV) | B21: =MA_Returns!C25 | C21: 7332.7917 | D21: =IF(ISNUMBER(B21),B21-C21,0) | E21: =IF(inp_scenario<>"Base","switch to Base to check",IF(ABS(D21)<=IF(ABS(C21)<10,chk_tol/100,chk_tol),"OK","STALE"))
A22: Pro-forma ARR, month 24 | B22: =MA_ProForma!AL94 | C22: 76704.905 | D22: =IF(ISNUMBER(B22),B22-C22,0) | E22: =IF(inp_scenario<>"Base","switch to Base to check",IF(ABS(D22)<=IF(ABS(C22)<10,chk_tol/100,chk_tol),"OK","STALE"))
A23: Pro-forma cash, month 24 | B23: =MA_ProForma!AL74 | C23: 8913.3283 | D23: =IF(ISNUMBER(B23),B23-C23,0) | E23: =IF(inp_scenario<>"Base","switch to Base to check",IF(ABS(D23)<=IF(ABS(C23)<10,chk_tol/100,chk_tol),"OK","STALE"))
A24: Pro-forma lowest month-end cash | B24: =MA_Returns!C49 | C24: 6024.437 | D24: =IF(ISNUMBER(B24),B24-C24,0) | E24: =IF(inp_scenario<>"Base","switch to Base to check",IF(ABS(D24)<=IF(ABS(C24)<10,chk_tol/100,chk_tol),"OK","STALE"))
A27: B. Impact matrix: metric value with the driver one step DOWN / UP; impact = (up - down) / 2 per step | C27: ARR, month 24 | F27: NRR (annualised), month 12 | I27: CAC payback (months), month 12 | L27: Cash, month 24 | O27: FY2 EBITDA
A28: Driver | B28: Step | C28: down | D28: up | E28: impact | F28: down | G28: up | H28: impact | I28: down | J28: up | K28: impact | L28: down | M28: up | N28: impact | O28: down | P28: up | Q28: impact | S28: |ARR, month 24| | T28: |NRR (annualise| | U28: |CAC payback (m| | V28: |Cash, month 24| | W28: |FY2 EBITDA|
A29: Enterprise gross churn | B29: 0.01 | C29: 69127.241 | D29: 67522.328 | E29: =(D29-C29)/2 | F29: 1.035213 | G29: 1.0201717 | H29: =(G29-F29)/2 | I29: 18.778184 | J29: 18.879449 | K29: =(J29-I29)/2 | L29: 23335.524 | M29: 21821.202 | N29: =(M29-L29)/2 | O29: -2713.0779 | P29: -3542.9832 | Q29: =(P29-O29)/2 | S29: =ABS(E29) | T29: =ABS(H29) | U29: =ABS(K29) | V29: =ABS(N29) | W29: =ABS(Q29)
A30: Mid-market gross churn | B30: 0.01 | C30: 68694.853 | D30: 67951.063 | E30: =(D30-C30)/2 | F30: 1.0312338 | G30: 1.0241531 | H30: =(G30-F30)/2 | I30: 18.81584 | J30: 18.841427 | K30: =(J30-I30)/2 | L30: 22944.131 | M30: 22216.31 | N30: =(M30-L30)/2 | O30: -2937.3054 | P30: -3320.0165 | Q30: =(P30-O30)/2 | S30: =ABS(E30) | T30: =ABS(H30) | U30: =ABS(K30) | V30: =ABS(N30) | W30: =ABS(Q30)
A31: Enterprise expansion | B31: 0.01 | C31: 67651.375 | D31: 68996.17 | E31: =(D31-C31)/2 | F31: 1.0213885 | G31: 1.0339919 | H31: =(G31-F31)/2 | I31: 19.183745 | J31: 18.485029 | K31: =(J31-I31)/2 | L31: 21835.374 | M31: 23320.136 | N31: =(M31-L31)/2 | O31: -3573.6073 | P31: -2682.2887 | Q31: =(P31-O31)/2 | S31: =ABS(E31) | T31: =ABS(H31) | U31: =ABS(K31) | V31: =ABS(N31) | W31: =ABS(Q31)
A32: Mid-market expansion | B32: 0.01 | C32: 68011.581 | D32: 68633.343 | E32: =(D32-C32)/2 | F32: 1.0247312 | G32: 1.0306503 | H32: =(G32-F32)/2 | I32: 19.004603 | J32: 18.65497 | K32: =(J32-I32)/2 | L32: 22204.179 | M32: 22956.123 | N32: =(M32-L32)/2 | O32: -3351.1589 | P32: -2905.9897 | Q32: =(P32-O32)/2 | S32: =ABS(E32) | T32: =ABS(H32) | U32: =ABS(K32) | V32: =ABS(N32) | W32: =ABS(Q32)
A33: Enterprise new logos / month | B33: 0.5 | C33: 65455.747 | D33: 71186.731 | E33: =(D33-C33)/2 | F33: 1.0266432 | G33: 1.0286778 | H33: =(G33-F33)/2 | I33: 20.388083 | J33: 17.504111 | K33: =(J33-I33)/2 | L33: 19251.968 | M33: 25790.713 | N33: =(M33-L33)/2 | O33: -5044.3721 | P33: -1214.2411 | Q33: =(P33-O33)/2 | S33: =ABS(E33) | T33: =ABS(H33) | U33: =ABS(K33) | V33: =ABS(N33) | W33: =ABS(Q33)
A34: Mid-market new logos / month | B34: 2 | C34: 67063.947 | D34: 69578.531 | E34: =(D34-C34)/2 | F34: 1.0286635 | G34: 1.0267258 | H34: =(G34-F34)/2 | I34: 19.531912 | J34: 18.177053 | K34: =(J34-I34)/2 | L34: 21116.64 | M34: 24019.393 | N34: =(M34-L34)/2 | O34: -3954.5974 | P34: -2304.0159 | Q34: =(P34-O34)/2 | S34: =ABS(E34) | T34: =ABS(H34) | U34: =ABS(K34) | V34: =ABS(N34) | W34: =ABS(Q34)
A35: Enterprise ACV (GBP k) | B35: 10 | C35: 67502.527 | D35: 69139.951 | E35: =(D35-C35)/2 | F35: 1.0273913 | G35: 1.0279723 | H35: =(G35-F35)/2 | I35: 19.260829 | J35: 18.416249 | K35: =(J35-I35)/2 | L35: 21572.456 | M35: 23575.421 | N35: =(M35-L35)/2 | O35: -3720.4899 | P35: -2538.1233 | Q35: =(P35-O35)/2 | S35: =ABS(E35) | T35: =ABS(H35) | U35: =ABS(K35) | V35: =ABS(N35) | W35: =ABS(Q35)
A36: Mid-market ACV (GBP k) | B36: 2 | C36: 67644.236 | D36: 68998.243 | E36: =(D36-C36)/2 | F36: 1.0282085 | G36: 1.0271652 | H36: =(G36-F36)/2 | I36: 19.221117 | J36: 18.452193 | K36: =(J36-I36)/2 | L36: 21704.542 | M36: 23445.746 | N36: =(M36-L36)/2 | O36: -3641.4901 | P36: -2617.1231 | Q36: =(P36-O36)/2 | S36: =ABS(E36) | T36: =ABS(H36) | U36: =ABS(K36) | V36: =ABS(N36) | W36: =ABS(Q36)
A37: Annual price uplift | B37: 0.01 | C37: 68191.76 | D37: 68450.718 | E37: =(D37-C37)/2 | F37: 1.0276837 | G37: 1.0276837 | H37: =(G37-F37)/2 | I37: 18.828614 | J37: 18.828614 | K37: =(J37-I37)/2 | L37: 22478.214 | M37: 22679.908 | N37: =(M37-L37)/2 | O37: -3198.7354 | P37: -3059.8779 | Q37: =(P37-O37)/2 | S37: =ABS(E37) | T37: =ABS(H37) | U37: =ABS(K37) | V37: =ABS(N37) | W37: =ABS(Q37)
A38: S&M net hires / month | B38: 0.5 | C38: 68321.239 | D38: 68321.239 | E38: =(D38-C38)/2 | F38: 1.0276837 | G38: 1.0276837 | H38: =(G38-F38)/2 | I38: 18.396763 | J38: 19.260465 | K38: =(J38-I38)/2 | L38: 23665.396 | M38: 21471.458 | N38: =(M38-L38)/2 | O38: -2309.5866 | P38: -3949.0266 | Q38: =(P38-O38)/2 | S38: =ABS(E38) | T38: =ABS(H38) | U38: =ABS(K38) | V38: =ABS(N38) | W38: =ABS(Q38)
A39: R&D net hires / month | B39: 0.5 | C39: 68321.239 | D39: 68321.239 | E39: =(D39-C39)/2 | F39: 1.0276837 | G39: 1.0276837 | H39: =(G39-F39)/2 | I39: 18.828614 | J39: 18.828614 | K39: =(J39-I39)/2 | L39: 23689.544 | M39: 21446.285 | N39: =(M39-L39)/2 | O39: -2290.9566 | P39: -3967.6566 | Q39: =(P39-O39)/2 | S39: =ABS(E39) | T39: =ABS(H39) | U39: =ABS(K39) | V39: =ABS(N39) | W39: =ABS(Q39)
A40: Customer payment terms (days) | B40: 5 | C40: 68321.239 | D40: 68321.239 | E40: =(D40-C40)/2 | F40: 1.0276837 | G40: 1.0276837 | H40: =(G40-F40)/2 | I40: 18.828614 | J40: 18.828614 | K40: =(J40-I40)/2 | L40: 23616.474 | M40: 21541.648 | N40: =(M40-L40)/2 | O40: -3129.3066 | P40: -3129.3066 | Q40: =(P40-O40)/2 | S40: =ABS(E40) | T40: =ABS(H40) | U40: =ABS(K40) | V40: =ABS(N40) | W40: =ABS(Q40)
A41: Step sizes (blue) are labels for the snapshot run; changing them here does not rerun it.
A44: C. Top three levers per metric (ranked by absolute impact per step; live formulas on the matrix above)
A45: Metric | B45: Rank 1 | C45: Rank 2 | D45: Rank 3
A46: ARR, month 24 | B46: =INDEX($A$29:$A$40,MATCH(LARGE(S$29:S$40,1),S$29:S$40,0),1) | C46: =INDEX($A$29:$A$40,MATCH(LARGE(S$29:S$40,2),S$29:S$40,0),1) | D46: =INDEX($A$29:$A$40,MATCH(LARGE(S$29:S$40,3),S$29:S$40,0),1)
A47: NRR (annualised), month 12 | B47: =INDEX($A$29:$A$40,MATCH(LARGE(T$29:T$40,1),T$29:T$40,0),1) | C47: =INDEX($A$29:$A$40,MATCH(LARGE(T$29:T$40,2),T$29:T$40,0),1) | D47: =INDEX($A$29:$A$40,MATCH(LARGE(T$29:T$40,3),T$29:T$40,0),1)
A48: CAC payback (months), month 12 | B48: =INDEX($A$29:$A$40,MATCH(LARGE(U$29:U$40,1),U$29:U$40,0),1) | C48: =INDEX($A$29:$A$40,MATCH(LARGE(U$29:U$40,2),U$29:U$40,0),1) | D48: =INDEX($A$29:$A$40,MATCH(LARGE(U$29:U$40,3),U$29:U$40,0),1)
A49: Cash, month 24 | B49: =INDEX($A$29:$A$40,MATCH(LARGE(V$29:V$40,1),V$29:V$40,0),1) | C49: =INDEX($A$29:$A$40,MATCH(LARGE(V$29:V$40,2),V$29:V$40,0),1) | D49: =INDEX($A$29:$A$40,MATCH(LARGE(V$29:V$40,3),V$29:V$40,0),1)
A50: FY2 EBITDA | B50: =INDEX($A$29:$A$40,MATCH(LARGE(W$29:W$40,1),W$29:W$40,0),1) | C50: =INDEX($A$29:$A$40,MATCH(LARGE(W$29:W$40,2),W$29:W$40,0),1) | D50: =INDEX($A$29:$A$40,MATCH(LARGE(W$29:W$40,3),W$29:W$40,0),1)

Sheet Sensitivity
A1: Sensitivity - two-way grids (static, engine-run)
A2: Sheets and Excel can't re-run the whole model per cell without data tables, so grid values below were produced by recalculating the full workbook (validation/snapshots.py) and pasted as grey values. A staleness check on the Checks tab flags them if the model changes.
A4: Lowest month-end cash over the 24 months (live) | B4: =MIN(BS!$O$9:$AL$9)
A6: Grid 1: lowest month-end cash (GBP k) - churn shift (rows, pts added to both segments) x new-logo volume (columns)
A7: Churn shift \ new-logo volume | B7: 0.8 | C7: 0.9 | D7: 1 | E7: 1.1 | F7: 1.2
A8: -0.04
A9: -0.02
A10: 0
A11: 0.02
A12: 0.04
A13: Highlighted cell = Base case. Grey italic = pasted engine output.
A15: Grid 2: enterprise value (GBP m) - ARR multiple (rows) x new-logo volume (columns), on month-24 ARR
A16: ARR multiple \ new-logo volume | B16: 0.8 | C16: 0.9 | D16: 1 | E16: 1.1 | F16: 1.2
A17: Month-24 ARR at that volume (GBP k, engine-run)
A18: 4 | B18: =$A18*B$17/1000 | C18: =$A18*C$17/1000 | D18: =$A18*D$17/1000 | E18: =$A18*E$17/1000 | F18: =$A18*F$17/1000
A19: 5 | B19: =$A19*B$17/1000 | C19: =$A19*C$17/1000 | D19: =$A19*D$17/1000 | E19: =$A19*E$17/1000 | F19: =$A19*F$17/1000
A20: 6 | B20: =$A20*B$17/1000 | C20: =$A20*C$17/1000 | D20: =$A20*D$17/1000 | E20: =$A20*E$17/1000 | F20: =$A20*F$17/1000
A21: 7 | B21: =$A21*B$17/1000 | C21: =$A21*C$17/1000 | D21: =$A21*D$17/1000 | E21: =$A21*E$17/1000 | F21: =$A21*F$17/1000
A22: 8 | B22: =$A22*B$17/1000 | C22: =$A22*C$17/1000 | D22: =$A22*D$17/1000 | E22: =$A22*E$17/1000 | F22: =$A22*F$17/1000
A24: EV = multiple (blue, editable) x snapshot ARR. Multiples are illustrative, synthetic.
A27: Grid 3 (live formulas): deal value created (GBP k) - offer multiple (rows) x synergies achieved (columns)
A28: Offer EV / ARR \ synergies achieved | B28: 0 | C28: 0.4 | D28: 0.7 | E28: 1 | F28: 1.3 | G28: Break-even synergies
A29: 3.5 | B29: =MA_Returns!$C$19+B$28*MA_Returns!$C$20-MA_Returns!$C$22-$A29*MA_PPA!$C$6*(1+inp_ma_deal_cost_pct) | C29: =MA_Returns!$C$19+C$28*MA_Returns!$C$20-MA_Returns!$C$22-$A29*MA_PPA!$C$6*(1+inp_ma_deal_cost_pct) | D29: =MA_Returns!$C$19+D$28*MA_Returns!$C$20-MA_Returns!$C$22-$A29*MA_PPA!$C$6*(1+inp_ma_deal_cost_pct) | E29: =MA_Returns!$C$19+E$28*MA_Returns!$C$20-MA_Returns!$C$22-$A29*MA_PPA!$C$6*(1+inp_ma_deal_cost_pct) | F29: =MA_Returns!$C$19+F$28*MA_Returns!$C$20-MA_Returns!$C$22-$A29*MA_PPA!$C$6*(1+inp_ma_deal_cost_pct) | G29: =($A29*MA_PPA!$C$6*(1+inp_ma_deal_cost_pct)+MA_Returns!$C$22-MA_Returns!$C$19)/MA_Returns!$C$20
A30: 4 | B30: =MA_Returns!$C$19+B$28*MA_Returns!$C$20-MA_Returns!$C$22-$A30*MA_PPA!$C$6*(1+inp_ma_deal_cost_pct) | C30: =MA_Returns!$C$19+C$28*MA_Returns!$C$20-MA_Returns!$C$22-$A30*MA_PPA!$C$6*(1+inp_ma_deal_cost_pct) | D30: =MA_Returns!$C$19+D$28*MA_Returns!$C$20-MA_Returns!$C$22-$A30*MA_PPA!$C$6*(1+inp_ma_deal_cost_pct) | E30: =MA_Returns!$C$19+E$28*MA_Returns!$C$20-MA_Returns!$C$22-$A30*MA_PPA!$C$6*(1+inp_ma_deal_cost_pct) | F30: =MA_Returns!$C$19+F$28*MA_Returns!$C$20-MA_Returns!$C$22-$A30*MA_PPA!$C$6*(1+inp_ma_deal_cost_pct) | G30: =($A30*MA_PPA!$C$6*(1+inp_ma_deal_cost_pct)+MA_Returns!$C$22-MA_Returns!$C$19)/MA_Returns!$C$20
A31: 4.5 | B31: =MA_Returns!$C$19+B$28*MA_Returns!$C$20-MA_Returns!$C$22-$A31*MA_PPA!$C$6*(1+inp_ma_deal_cost_pct) | C31: =MA_Returns!$C$19+C$28*MA_Returns!$C$20-MA_Returns!$C$22-$A31*MA_PPA!$C$6*(1+inp_ma_deal_cost_pct) | D31: =MA_Returns!$C$19+D$28*MA_Returns!$C$20-MA_Returns!$C$22-$A31*MA_PPA!$C$6*(1+inp_ma_deal_cost_pct) | E31: =MA_Returns!$C$19+E$28*MA_Returns!$C$20-MA_Returns!$C$22-$A31*MA_PPA!$C$6*(1+inp_ma_deal_cost_pct) | F31: =MA_Returns!$C$19+F$28*MA_Returns!$C$20-MA_Returns!$C$22-$A31*MA_PPA!$C$6*(1+inp_ma_deal_cost_pct) | G31: =($A31*MA_PPA!$C$6*(1+inp_ma_deal_cost_pct)+MA_Returns!$C$22-MA_Returns!$C$19)/MA_Returns!$C$20
A32: 5 | B32: =MA_Returns!$C$19+B$28*MA_Returns!$C$20-MA_Returns!$C$22-$A32*MA_PPA!$C$6*(1+inp_ma_deal_cost_pct) | C32: =MA_Returns!$C$19+C$28*MA_Returns!$C$20-MA_Returns!$C$22-$A32*MA_PPA!$C$6*(1+inp_ma_deal_cost_pct) | D32: =MA_Returns!$C$19+D$28*MA_Returns!$C$20-MA_Returns!$C$22-$A32*MA_PPA!$C$6*(1+inp_ma_deal_cost_pct) | E32: =MA_Returns!$C$19+E$28*MA_Returns!$C$20-MA_Returns!$C$22-$A32*MA_PPA!$C$6*(1+inp_ma_deal_cost_pct) | F32: =MA_Returns!$C$19+F$28*MA_Returns!$C$20-MA_Returns!$C$22-$A32*MA_PPA!$C$6*(1+inp_ma_deal_cost_pct) | G32: =($A32*MA_PPA!$C$6*(1+inp_ma_deal_cost_pct)+MA_Returns!$C$22-MA_Returns!$C$19)/MA_Returns!$C$20
A33: 5.5 | B33: =MA_Returns!$C$19+B$28*MA_Returns!$C$20-MA_Returns!$C$22-$A33*MA_PPA!$C$6*(1+inp_ma_deal_cost_pct) | C33: =MA_Returns!$C$19+C$28*MA_Returns!$C$20-MA_Returns!$C$22-$A33*MA_PPA!$C$6*(1+inp_ma_deal_cost_pct) | D33: =MA_Returns!$C$19+D$28*MA_Returns!$C$20-MA_Returns!$C$22-$A33*MA_PPA!$C$6*(1+inp_ma_deal_cost_pct) | E33: =MA_Returns!$C$19+E$28*MA_Returns!$C$20-MA_Returns!$C$22-$A33*MA_PPA!$C$6*(1+inp_ma_deal_cost_pct) | F33: =MA_Returns!$C$19+F$28*MA_Returns!$C$20-MA_Returns!$C$22-$A33*MA_PPA!$C$6*(1+inp_ma_deal_cost_pct) | G33: =($A33*MA_PPA!$C$6*(1+inp_ma_deal_cost_pct)+MA_Returns!$C$22-MA_Returns!$C$19)/MA_Returns!$C$20
A34: Value is linear in the synergy % and in the price, so this grid needs no model re-run. Negative = the deal destroys value.

Sheet Business_Review
A1: Business_Review - one-page pack: KPIs, what moved, risks, downside alongside the point estimate
A2: Section 1 is live for the selected scenario. Section 3 compares engine-run Base / Upside / Downside snapshots (grey italic).
A3: ="Scenario shown: "&inp_scenario&" | Master check: "&IF(chk_master=1,"ALL CHECKS PASS","CHECK FAILURE")
A5: 1. Headline KPIs (live)
A6: KPI | B6: FY1 | C6: FY2
A7: Revenue | B7: =IS!AN12 | C7: =IS!AO12
A8: Gross margin | B8: =IS!AN21 | C8: =IS!AO21
A9: EBITDA | B9: =IS!AN29 | C9: =IS!AO29
A10: EBITDA margin | B10: =IS!AN30 | C10: =IS!AO30
A11: Closing ARR | B11: =SaaS_Metrics!AN13 | C11: =SaaS_Metrics!AO13
A12: ARR growth (year on year) | B12: =SaaS_Metrics!AN16 | C12: =SaaS_Metrics!AO16
A13: Net revenue retention | B13: =SaaS_Metrics!AN19 | C13: =SaaS_Metrics!AO19
A14: Gross revenue retention | B14: =SaaS_Metrics!AN20 | C14: =SaaS_Metrics!AO20
A15: CAC payback (months) | B15: =SaaS_Metrics!AN28 | C15: =SaaS_Metrics!AO28
A16: LTV / CAC | B16: =SaaS_Metrics!AN31 | C16: =SaaS_Metrics!AO31
A17: Burn multiple | B17: =SaaS_Metrics!AN36 | C17: =SaaS_Metrics!AO36
A18: Rule of 40 | B18: =SaaS_Metrics!AN39 | C18: =SaaS_Metrics!AO39
A19: Closing cash | B19: =BS!AN9 | C19: =BS!AO9
A20: Closing headcount (FTE) | B20: =Headcount_Opex!AN33 | C20: =Headcount_Opex!AO33
A22: 2. What moved vs budget in FY1, and why (live, from Budget_vs_Forecast)
A23: Closing ARR vs budget | B23: =Budget_vs_Forecast!D32 | F23: Sum of the four ARR drivers below
A24: Volume (new customers) | B24: =Budget_vs_Forecast!B41 | F24: Fewer/more new logos than budgeted
A25: Price (ACV) | B25: =Budget_vs_Forecast!B42 | F25: Deal size vs budget
A26: Expansion | B26: =Budget_vs_Forecast!B43 | F26: Upsell on the installed base
A27: Churn | B27: =Budget_vs_Forecast!B44 | F27: Negative = more ARR lost than budgeted
A28: Revenue vs budget | B28: =Budget_vs_Forecast!D7
A29: EBITDA vs budget | B29: =Budget_vs_Forecast!D14
A31: 3. Point estimate vs downside (engine-run snapshots)
A32: Metric | B32: Base | C32: Upside | D32: Downside | E32: Downside vs Base
A33: FY1 revenue | B33: 48367.078 | C33: 51168.004 | D33: 43788.85 | E33: =IF(AND(ISNUMBER(B33),ISNUMBER(D33)),D33-B33,"")
A34: FY2 revenue | B34: 62987.254 | C34: 71813.507 | D34: 49503.97 | E34: =IF(AND(ISNUMBER(B34),ISNUMBER(D34)),D34-B34,"")
A35: FY1 EBITDA | B35: -6972.479 | C35: -5719.7454 | D35: -8479.333 | E35: =IF(AND(ISNUMBER(B35),ISNUMBER(D35)),D35-B35,"")
A36: FY2 EBITDA | B36: -3129.3066 | C36: 1191.6106 | D36: -7574.986 | E36: =IF(AND(ISNUMBER(B36),ISNUMBER(D36)),D36-B36,"")
A37: ARR, month 12 | B37: 53403.649 | C37: 58460.025 | D37: 45146.286 | E37: =IF(AND(ISNUMBER(B37),ISNUMBER(D37)),D37-B37,"")
A38: ARR, month 24 | B38: 68321.239 | C38: 80599.074 | D38: 50209.086 | E38: =IF(AND(ISNUMBER(B38),ISNUMBER(D38)),D38-B38,"")
A39: ARR growth, month 12 | B39: 0.33509122 | C39: 0.46150063 | D39: 0.12865716 | E39: =IF(AND(ISNUMBER(B39),ISNUMBER(D39)),D39-B39,"")
A40: NRR (annualised), month 12 | B40: 1.0276837 | C40: 1.0676914 | D40: 0.93836983 | E40: =IF(AND(ISNUMBER(B40),ISNUMBER(D40)),D40-B40,"")
A41: GRR (annualised), month 12 | B41: 0.91979261 | C41: 0.93329101 | D41: 0.87335501 | E41: =IF(AND(ISNUMBER(B41),ISNUMBER(D41)),D41-B41,"")
A42: CAC payback (months), month 12 | B42: 18.828614 | C42: 15.493878 | D42: 27.415418 | E42: =IF(AND(ISNUMBER(B42),ISNUMBER(D42)),D42-B42,"")
A43: LTV / CAC, month 12 | B43: 4.5027222 | C43: 6.2853834 | D43: 2.2278983 | E43: =IF(AND(ISNUMBER(B43),ISNUMBER(D43)),D43-B43,"")
A44: Cash, month 24 | B44: 22579.061 | C44: 31968.083 | D44: 9507.7776 | E44: =IF(AND(ISNUMBER(B44),ISNUMBER(D44)),D44-B44,"")
... A51: Pro-forma lowest month-end cash | B51: 6024.437 | C51: 9820.6074 | D51: -6226.3071 | E51: =IF(AND(ISNUMBER(B51),ISNUMBER(D51)),D51-B51,"")
A53: 4. Risk flags (live thresholds on the selected scenario)
A54: Cash runway under this many months (month 24) | B54: =IF(ISNUMBER(SaaS_Metrics!AL38),IF(SaaS_Metrics!AL38<$C54,"FLAG","OK"),"OK (cash generative)") | C54: 12 | F54: Runway = cash / trailing 3-month average burn.
A55: Net revenue retention below (month 12) | B55: =IF(SaaS_Metrics!Z19<$C55,"FLAG","OK") | C55: 1 | F55: The installed base is shrinking before new sales.
A56: CAC payback above this many months (month 12) | B56: =IF(SaaS_Metrics!Z28>$C56,"FLAG","OK") | C56: 24 | F56: Growth is expensive to buy.
A57: Lowest month-end cash below (GBP k) | B57: =IF(Sensitivity!B4<$C57,"FLAG","OK") | C57: 0 | F57: Funding gap.

Sheet MA_Target
A1: MA_Target - Vaultline Archive Ltd, standalone (simplified three statements)
A2: GBP thousands unless stated. Blue = input, black = formula, green = link to another tab.
A3: Period # | C3: =COLUMN()-COLUMN($N$1) | D3: =COLUMN()-COLUMN($N$1) | E3: =COLUMN()-COLUMN($N$1) | F3: =COLUMN()-COLUMN($N$1) | G3: =COLUMN()-COLUMN($N$1) | H3: =COLUMN()-COLUMN($N$1) | I3: =COLUMN()-COLUMN($N$1) | J3: =COLUMN()-COLUMN($N$1) | ... AL3: =COLUMN()-COLUMN($N$1) | AN3: Annual | AO3: Annual
A4: Period ending | C4: =EOMONTH(inp_model_start,C3-1) | D4: =EOMONTH(inp_model_start,D3-1) | E4: =EOMONTH(inp_model_start,E3-1) | F4: =EOMONTH(inp_model_start,F3-1) | G4: =EOMONTH(inp_model_start,G3-1) | H4: =EOMONTH(inp_model_start,H3-1) | I4: =EOMONTH(inp_model_start,I3-1) | J4: =EOMONTH(inp_model_start,J3-1) | ... AL4: =EOMONTH(inp_model_start,AL3-1) | AN4: ="FY"&(YEAR(inp_model_start)+AN5-1) | AO4: ="FY"&(YEAR(inp_model_start)+AO5-1)
A5: Year | C5: =IF(C3<1,0,ROUNDUP(C3/12,0)) | D5: =IF(D3<1,0,ROUNDUP(D3/12,0)) | E5: =IF(E3<1,0,ROUNDUP(E3/12,0)) | F5: =IF(F3<1,0,ROUNDUP(F3/12,0)) | G5: =IF(G3<1,0,ROUNDUP(G3/12,0)) | H5: =IF(H3<1,0,ROUNDUP(H3/12,0)) | I5: =IF(I3<1,0,ROUNDUP(I3/12,0)) | J5: =IF(J3<1,0,ROUNDUP(J3/12,0)) | ... AL5: =IF(AL3<1,0,ROUNDUP(AL3/12,0)) | AN5: =COLUMN()-COLUMN($AM$1) | AO5: =COLUMN()-COLUMN($AM$1)
A6: Quarter | C6: =IF(C3<1,0,ROUNDUP(C3/3,0)) | D6: =IF(D3<1,0,ROUNDUP(D3/3,0)) | E6: =IF(E3<1,0,ROUNDUP(E3/3,0)) | F6: =IF(F3<1,0,ROUNDUP(F3/3,0)) | G6: =IF(G3<1,0,ROUNDUP(G3/3,0)) | H6: =IF(H3<1,0,ROUNDUP(H3/3,0)) | I6: =IF(I3<1,0,ROUNDUP(I3/3,0)) | J6: =IF(J3<1,0,ROUNDUP(J3/3,0)) | ... AL6: =IF(AL3<1,0,ROUNDUP(AL3/3,0))
A8: Drivers
A9: Monthly gross churn rate | B9: %/mo | O9: =1-(1-inp_v_churn)^(1/12) | P9: =1-(1-inp_v_churn)^(1/12) | Q9: =1-(1-inp_v_churn)^(1/12) | R9: =1-(1-inp_v_churn)^(1/12) | S9: =1-(1-inp_v_churn)^(1/12) | T9: =1-(1-inp_v_churn)^(1/12) | U9: =1-(1-inp_v_churn)^(1/12) | V9: =1-(1-inp_v_churn)^(1/12) | ... AL9: =1-(1-inp_v_churn)^(1/12) | AN9: =INDEX($O9:$AL9,1,AN$5*12) | AO9: =INDEX($O9:$AL9,1,AO$5*12)
A10: Monthly expansion rate | B10: %/mo | O10: =(1+inp_v_exp)^(1/12)-1 | P10: =(1+inp_v_exp)^(1/12)-1 | Q10: =(1+inp_v_exp)^(1/12)-1 | R10: =(1+inp_v_exp)^(1/12)-1 | S10: =(1+inp_v_exp)^(1/12)-1 | T10: =(1+inp_v_exp)^(1/12)-1 | U10: =(1+inp_v_exp)^(1/12)-1 | V10: =(1+inp_v_exp)^(1/12)-1 | ... AL10: =(1+inp_v_exp)^(1/12)-1 | AN10: =INDEX($O10:$AL10,1,AN$5*12) | AO10: =INDEX($O10:$AL10,1,AO$5*12)
A12: ARR and customers
A13: Opening ARR | B13: GBP k | O13: =N17 | P13: =O17 | Q13: =P17 | R13: =Q17 | S13: =R17 | T13: =S17 | U13: =T17 | V13: =U17 | ... AL13: =AK17 | AN13: =INDEX($O13:$AL13,1,(AN$5-1)*12+1) | AO13: =INDEX($O13:$AL13,1,(AO$5-1)*12+1)
A14: + New logos | B14: GBP k | O14: =inp_v_logos*inp_v_acv | P14: =inp_v_logos*inp_v_acv | Q14: =inp_v_logos*inp_v_acv | R14: =inp_v_logos*inp_v_acv | S14: =inp_v_logos*inp_v_acv | T14: =inp_v_logos*inp_v_acv | U14: =inp_v_logos*inp_v_acv | V14: =inp_v_logos*inp_v_acv | ... AL14: =inp_v_logos*inp_v_acv | AN14: =SUMIF($O$5:$AL$5,AN$5,$O14:$AL14) | AO14: =SUMIF($O$5:$AL$5,AO$5,$O14:$AL14)
A15: + Expansion | B15: GBP k | O15: =O13*O10 | P15: =P13*P10 | Q15: =Q13*Q10 | R15: =R13*R10 | S15: =S13*S10 | T15: =T13*T10 | U15: =U13*U10 | V15: =V13*V10 | ... AL15: =AL13*AL10 | AN15: =SUMIF($O$5:$AL$5,AN$5,$O15:$AL15) | AO15: =SUMIF($O$5:$AL$5,AO$5,$O15:$AL15)
A16: - Churn | B16: GBP k | O16: =-O13*O9 | P16: =-P13*P9 | Q16: =-Q13*Q9 | R16: =-R13*R9 | S16: =-S13*S9 | T16: =-T13*T9 | U16: =-U13*U9 | V16: =-V13*V9 | ... AL16: =-AL13*AL9 | AN16: =SUMIF($O$5:$AL$5,AN$5,$O16:$AL16) | AO16: =SUMIF($O$5:$AL$5,AO$5,$O16:$AL16)
A17: Closing ARR | B17: GBP k | N17: =inp_v_arr_open | O17: =SUM(O13:O16) | P17: =SUM(P13:P16) | Q17: =SUM(Q13:Q16) | R17: =SUM(R13:R16) | S17: =SUM(S13:S16) | T17: =SUM(T13:T16) | U17: =SUM(U13:U16) | V17: =SUM(V13:V16) | ... AL17: =SUM(AL13:AL16) | AN17: =INDEX($O17:$AL17,1,AN$5*12) | AO17: =INDEX($O17:$AL17,1,AO$5*12)
A18: Closing customers | B18: # | N18: =inp_v_cust_open | O18: =N18*(1-O9)+inp_v_logos | P18: =O18*(1-P9)+inp_v_logos | Q18: =P18*(1-Q9)+inp_v_logos | R18: =Q18*(1-R9)+inp_v_logos | S18: =R18*(1-S9)+inp_v_logos | T18: =S18*(1-T9)+inp_v_logos | U18: =T18*(1-U9)+inp_v_logos | V18: =U18*(1-V9)+inp_v_logos | ... AL18: =AK18*(1-AL9)+inp_v_logos | AN18: =INDEX($O18:$AL18,1,AN$5*12) | AO18: =INDEX($O18:$AL18,1,AO$5*12)
A20: Billings and revenue (annual upfront, recognised ratably; columns C:N hold opening-year history)
A21: Invoices raised | B21: GBP k | C21: =inp_v_arr_open/12 | D21: =inp_v_arr_open/12 | E21: =inp_v_arr_open/12 | F21: =inp_v_arr_open/12 | G21: =inp_v_arr_open/12 | H21: =inp_v_arr_open/12 | I21: =inp_v_arr_open/12 | J21: =inp_v_arr_open/12 | ... N21: =inp_v_arr_open/12 | O21: =O14+(1+inp_v_exp-inp_v_churn)*C21 | P21: =P14+(1+inp_v_exp-inp_v_churn)*D21 | Q21: =Q14+(1+inp_v_exp-inp_v_churn)*E21 | R21: =R14+(1+inp_v_exp-inp_v_churn)*F21 | S21: =S14+(1+inp_v_exp-inp_v_churn)*G21 | T21: =T14+(1+inp_v_exp-inp_v_churn)*H21 | U21: =U14+(1+inp_v_exp-inp_v_churn)*I21 | V21: =V14+(1+inp_v_exp-inp_v_churn)*J21 | ... AL21: =AL14+(1+inp_v_exp-inp_v_churn)*Z21 | AN21: =SUMIF($O$5:$AL$5,AN$5,$O21:$AL21) | AO21: =SUMIF($O$5:$AL$5,AO$5,$O21:$AL21)
A22: Unexpired share of each historic invoice at opening date | B22: x | C22: =(C$3+11)/12 | D22: =(D$3+11)/12 | E22: =(E$3+11)/12 | F22: =(F$3+11)/12 | G22: =(G$3+11)/12 | H22: =(H$3+11)/12 | I22: =(I$3+11)/12 | J22: =(J$3+11)/12 | ... N22: =(N$3+11)/12
A23: Revenue (each invoice over 12 months) | B23: GBP k | O23: =SUM(D21:O21)/12 | P23: =SUM(E21:P21)/12 | Q23: =SUM(F21:Q21)/12 | R23: =SUM(G21:R21)/12 | S23: =SUM(H21:S21)/12 | T23: =SUM(I21:T21)/12 | U23: =SUM(J21:U21)/12 | V23: =SUM(K21:V21)/12 | ... AL23: =SUM(AA21:AL21)/12 | AN23: =SUMIF($O$5:$AL$5,AN$5,$O23:$AL23) | AO23: =SUMIF($O$5:$AL$5,AO$5,$O23:$AL23)
A24: Deferred revenue: opening | B24: GBP k | O24: =N27 | P24: =O27 | Q24: =P27 | R24: =Q27 | S24: =R27 | T24: =S27 | U24: =T27 | V24: =U27 | ... AL24: =AK27 | AN24: =INDEX($O24:$AL24,1,(AN$5-1)*12+1) | AO24: =INDEX($O24:$AL24,1,(AO$5-1)*12+1)
A25: + Invoices raised | B25: GBP k | O25: =O21 | P25: =P21 | Q25: =Q21 | R25: =R21 | S25: =S21 | T25: =T21 | U25: =U21 | V25: =V21 | ... AL25: =AL21 | AN25: =SUMIF($O$5:$AL$5,AN$5,$O25:$AL25) | AO25: =SUMIF($O$5:$AL$5,AO$5,$O25:$AL25)
A26: - Revenue recognised | B26: GBP k | O26: =-O23 | P26: =-P23 | Q26: =-Q23 | R26: =-R23 | S26: =-S23 | T26: =-T23 | U26: =-U23 | V26: =-V23 | ... AL26: =-AL23 | AN26: =SUMIF($O$5:$AL$5,AN$5,$O26:$AL26) | AO26: =SUMIF($O$5:$AL$5,AO$5,$O26:$AL26)
A27: Deferred revenue: closing | B27: GBP k | N27: =SUMPRODUCT(C21:N21,C22:N22) | O27: =SUM(O24:O26) | P27: =SUM(P24:P26) | Q27: =SUM(Q24:Q26) | R27: =SUM(R24:R26) | S27: =SUM(S24:S26) | T27: =SUM(T24:T26) | U27: =SUM(U24:U26) | V27: =SUM(V24:V26) | ... AL27: =SUM(AL24:AL26) | AN27: =INDEX($O27:$AL27,1,AN$5*12) | AO27: =INDEX($O27:$AL27,1,AO$5*12)
A28: Trade receivables | B28: GBP k | N28: =inp_v_open_ar | O28: =O21*MIN(1,inp_v_dso/30)+N21*MAX(0,MIN(1,(inp_v_dso-30)/30)) | P28: =P21*MIN(1,inp_v_dso/30)+O21*MAX(0,MIN(1,(inp_v_dso-30)/30)) | Q28: =Q21*MIN(1,inp_v_dso/30)+P21*MAX(0,MIN(1,(inp_v_dso-30)/30)) | R28: =R21*MIN(1,inp_v_dso/30)+Q21*MAX(0,MIN(1,(inp_v_dso-30)/30)) | S28: =S21*MIN(1,inp_v_dso/30)+R21*MAX(0,MIN(1,(inp_v_dso-30)/30)) | T28: =T21*MIN(1,inp_v_dso/30)+S21*MAX(0,MIN(1,(inp_v_dso-30)/30)) | U28: =U21*MIN(1,inp_v_dso/30)+T21*MAX(0,MIN(1,(inp_v_dso-30)/30)) | V28: =V21*MIN(1,inp_v_dso/30)+U21*MAX(0,MIN(1,(inp_v_dso-30)/30)) | ... AL28: =AL21*MIN(1,inp_v_dso/30)+AK21*MAX(0,MIN(1,(inp_v_dso-30)/30)) | AN28: =INDEX($O28:$AL28,1,AN$5*12) | AO28: =INDEX($O28:$AL28,1,AO$5*12)
A30: Income statement
A31: Cost of revenue | B31: GBP k | O31: =O23*inp_v_cogs_pct | P31: =P23*inp_v_cogs_pct | Q31: =Q23*inp_v_cogs_pct | R31: =R23*inp_v_cogs_pct | S31: =S23*inp_v_cogs_pct | T31: =T23*inp_v_cogs_pct | U31: =U23*inp_v_cogs_pct | V31: =V23*inp_v_cogs_pct | ... AL31: =AL23*inp_v_cogs_pct | AN31: =SUMIF($O$5:$AL$5,AN$5,$O31:$AL31) | AO31: =SUMIF($O$5:$AL$5,AO$5,$O31:$AL31)
A32: Gross profit | B32: GBP k | O32: =O23-O31 | P32: =P23-P31 | Q32: =Q23-Q31 | R32: =R23-R31 | S32: =S23-S31 | T32: =T23-T31 | U32: =U23-U31 | V32: =V23-V31 | ... AL32: =AL23-AL31 | AN32: =SUMIF($O$5:$AL$5,AN$5,$O32:$AL32) | AO32: =SUMIF($O$5:$AL$5,AO$5,$O32:$AL32)
A33: R&D | B33: GBP k | O33: =O23*inp_v_rd_pct | P33: =P23*inp_v_rd_pct | Q33: =Q23*inp_v_rd_pct | R33: =R23*inp_v_rd_pct | S33: =S23*inp_v_rd_pct | T33: =T23*inp_v_rd_pct | U33: =U23*inp_v_rd_pct | V33: =V23*inp_v_rd_pct | ... AL33: =AL23*inp_v_rd_pct | AN33: =SUMIF($O$5:$AL$5,AN$5,$O33:$AL33) | AO33: =SUMIF($O$5:$AL$5,AO$5,$O33:$AL33)
A34: Sales & marketing | B34: GBP k | O34: =O23*inp_v_sm_pct | P34: =P23*inp_v_sm_pct | Q34: =Q23*inp_v_sm_pct | R34: =R23*inp_v_sm_pct | S34: =S23*inp_v_sm_pct | T34: =T23*inp_v_sm_pct | U34: =U23*inp_v_sm_pct | V34: =V23*inp_v_sm_pct | ... AL34: =AL23*inp_v_sm_pct | AN34: =SUMIF($O$5:$AL$5,AN$5,$O34:$AL34) | AO34: =SUMIF($O$5:$AL$5,AO$5,$O34:$AL34)
A35: G&A | B35: GBP k | O35: =O23*inp_v_ga_pct | P35: =P23*inp_v_ga_pct | Q35: =Q23*inp_v_ga_pct | R35: =R23*inp_v_ga_pct | S35: =S23*inp_v_ga_pct | T35: =T23*inp_v_ga_pct | U35: =U23*inp_v_ga_pct | V35: =V23*inp_v_ga_pct | ... AL35: =AL23*inp_v_ga_pct | AN35: =SUMIF($O$5:$AL$5,AN$5,$O35:$AL35) | AO35: =SUMIF($O$5:$AL$5,AO$5,$O35:$AL35)
A36: EBITDA | B36: GBP k | O36: =O32-O33-O34-O35 | P36: =P32-P33-P34-P35 | Q36: =Q32-Q33-Q34-Q35 | R36: =R32-R33-R34-R35 | S36: =S32-S33-S34-S35 | T36: =T32-T33-T34-T35 | U36: =U32-U33-U34-U35 | V36: =V32-V33-V34-V35 | ... AL36: =AL32-AL33-AL34-AL35 | AN36: =SUMIF($O$5:$AL$5,AN$5,$O36:$AL36) | AO36: =SUMIF($O$5:$AL$5,AO$5,$O36:$AL36)
A37: EBITDA margin | B37: % | O37: =O36/O23 | P37: =P36/P23 | Q37: =Q36/Q23 | R37: =R36/R23 | S37: =S36/S23 | T37: =T36/T23 | U37: =U36/U23 | V37: =V36/V23 | ... AL37: =AL36/AL23 | AN37: =AN36/AN23 | AO37: =AO36/AO23
A38: Depreciation | B38: GBP k | O38: =O45/inp_v_dep_life | P38: =P45/inp_v_dep_life | Q38: =Q45/inp_v_dep_life | R38: =R45/inp_v_dep_life | S38: =S45/inp_v_dep_life | T38: =T45/inp_v_dep_life | U38: =U45/inp_v_dep_life | V38: =V45/inp_v_dep_life | ... AL38: =AL45/inp_v_dep_life | AN38: =SUMIF($O$5:$AL$5,AN$5,$O38:$AL38) | AO38: =SUMIF($O$5:$AL$5,AO$5,$O38:$AL38)
A39: Interest income (prior-period cash) | B39: GBP k | O39: =N51*inp_interest/12 | P39: =O51*inp_interest/12 | Q39: =P51*inp_interest/12 | R39: =Q51*inp_interest/12 | S39: =R51*inp_interest/12 | T39: =S51*inp_interest/12 | U39: =T51*inp_interest/12 | V39: =U51*inp_interest/12 | ... AL39: =AK51*inp_interest/12 | AN39: =SUMIF($O$5:$AL$5,AN$5,$O39:$AL39) | AO39: =SUMIF($O$5:$AL$5,AO$5,$O39:$AL39)
A40: Profit before tax | B40: GBP k | O40: =O36-O38+O39 | P40: =P36-P38+P39 | Q40: =Q36-Q38+Q39 | R40: =R36-R38+R39 | S40: =S36-S38+S39 | T40: =T36-T38+T39 | U40: =U36-U38+U39 | V40: =V36-V38+V39 | ... AL40: =AL36-AL38+AL39 | AN40: =SUMIF($O$5:$AL$5,AN$5,$O40:$AL40) | AO40: =SUMIF($O$5:$AL$5,AO$5,$O40:$AL40)
A41: Tax | B41: GBP k | O41: =MAX(0,O40)*inp_tax | P41: =MAX(0,P40)*inp_tax | Q41: =MAX(0,Q40)*inp_tax | R41: =MAX(0,R40)*inp_tax | S41: =MAX(0,S40)*inp_tax | T41: =MAX(0,T40)*inp_tax | U41: =MAX(0,U40)*inp_tax | V41: =MAX(0,V40)*inp_tax | ... AL41: =MAX(0,AL40)*inp_tax | AN41: =SUMIF($O$5:$AL$5,AN$5,$O41:$AL41) | AO41: =SUMIF($O$5:$AL$5,AO$5,$O41:$AL41)
A42: Net income | B42: GBP k | O42: =O40-O41 | P42: =P40-P41 | Q42: =Q40-Q41 | R42: =R40-R41 | S42: =S40-S41 | T42: =T40-T41 | U42: =U40-U41 | V42: =V40-V41 | ... AL42: =AL40-AL41 | AN42: =SUMIF($O$5:$AL$5,AN$5,$O42:$AL42) | AO42: =SUMIF($O$5:$AL$5,AO$5,$O42:$AL42)
A44: PP&E schedule
A45: Opening NBV | B45: GBP k | O45: =N48 | P45: =O48 | Q45: =P48 | R45: =Q48 | S45: =R48 | T45: =S48 | U45: =T48 | V45: =U48 | ... AL45: =AK48 | AN45: =INDEX($O45:$AL45,1,(AN$5-1)*12+1) | AO45: =INDEX($O45:$AL45,1,(AO$5-1)*12+1)
A46: + Capex | B46: GBP k | O46: =O23*inp_v_capex_pct | P46: =P23*inp_v_capex_pct | Q46: =Q23*inp_v_capex_pct | R46: =R23*inp_v_capex_pct | S46: =S23*inp_v_capex_pct | T46: =T23*inp_v_capex_pct | U46: =U23*inp_v_capex_pct | V46: =V23*inp_v_capex_pct | ... AL46: =AL23*inp_v_capex_pct | AN46: =SUMIF($O$5:$AL$5,AN$5,$O46:$AL46) | AO46: =SUMIF($O$5:$AL$5,AO$5,$O46:$AL46)
A47: - Depreciation | B47: GBP k | O47: =-O38 | P47: =-P38 | Q47: =-Q38 | R47: =-R38 | S47: =-S38 | T47: =-T38 | U47: =-U38 | V47: =-V38 | ... AL47: =-AL38 | AN47: =SUMIF($O$5:$AL$5,AN$5,$O47:$AL47) | AO47: =SUMIF($O$5:$AL$5,AO$5,$O47:$AL47)
A48: Closing NBV | B48: GBP k | N48: =inp_v_open_ppe | O48: =SUM(O45:O47) | P48: =SUM(P45:P47) | Q48: =SUM(Q45:Q47) | R48: =SUM(R45:R47) | S48: =SUM(S45:S47) | T48: =SUM(T45:T47) | U48: =SUM(U45:U47) | V48: =SUM(V45:V47) | ... AL48: =SUM(AL45:AL47) | AN48: =INDEX($O48:$AL48,1,AN$5*12) | AO48: =INDEX($O48:$AL48,1,AO$5*12)
A50: Balance sheet
A51: Cash | B51: GBP k | N51: =N68 | O51: =O68 | P51: =P68 | Q51: =Q68 | R51: =R68 | S51: =S68 | T51: =T68 | U51: =U68 | ... AL51: =AL68 | AN51: =INDEX($O51:$AL51,1,AN$5*12) | AO51: =INDEX($O51:$AL51,1,AO$5*12)
A52: Trade receivables | B52: GBP k | N52: =N28 | O52: =O28 | P52: =P28 | Q52: =Q28 | R52: =R28 | S52: =S28 | T52: =T28 | U52: =U28 | ... AL52: =AL28 | AN52: =INDEX($O52:$AL52,1,AN$5*12) | AO52: =INDEX($O52:$AL52,1,AO$5*12)
A53: PP&E (net) | B53: GBP k | N53: =N48 | O53: =O48 | P53: =P48 | Q53: =Q48 | R53: =R48 | S53: =S48 | T53: =T48 | U53: =U48 | ... AL53: =AL48 | AN53: =INDEX($O53:$AL53,1,AN$5*12) | AO53: =INDEX($O53:$AL53,1,AO$5*12)
A54: Total assets | B54: GBP k | N54: =SUM(N51:N53) | O54: =SUM(O51:O53) | P54: =SUM(P51:P53) | Q54: =SUM(Q51:Q53) | R54: =SUM(R51:R53) | S54: =SUM(S51:S53) | T54: =SUM(T51:T53) | U54: =SUM(U51:U53) | ... AL54: =SUM(AL51:AL53) | AN54: =INDEX($O54:$AL54,1,AN$5*12) | AO54: =INDEX($O54:$AL54,1,AO$5*12)
A55: Trade payables | B55: GBP k | N55: =inp_v_arr_open/12*(inp_v_cogs_pct+inp_v_rd_pct+inp_v_sm_pct+inp_v_ga_pct)*inp_v_ap_months | O55: =(O31+O33+O34+O35)*inp_v_ap_months | P55: =(P31+P33+P34+P35)*inp_v_ap_months | Q55: =(Q31+Q33+Q34+Q35)*inp_v_ap_months | R55: =(R31+R33+R34+R35)*inp_v_ap_months | S55: =(S31+S33+S34+S35)*inp_v_ap_months | T55: =(T31+T33+T34+T35)*inp_v_ap_months | U55: =(U31+U33+U34+U35)*inp_v_ap_months | V55: =(V31+V33+V34+V35)*inp_v_ap_months | ... AL55: =(AL31+AL33+AL34+AL35)*inp_v_ap_months | AN55: =INDEX($O55:$AL55,1,AN$5*12) | AO55: =INDEX($O55:$AL55,1,AO$5*12)
A56: Deferred revenue | B56: GBP k | N56: =N27 | O56: =O27 | P56: =P27 | Q56: =Q27 | R56: =R27 | S56: =S27 | T56: =T27 | U56: =U27 | ... AL56: =AL27 | AN56: =INDEX($O56:$AL56,1,AN$5*12) | AO56: =INDEX($O56:$AL56,1,AO$5*12)
A57: Total liabilities | B57: GBP k | N57: =N55+N56 | O57: =O55+O56 | P57: =P55+P56 | Q57: =Q55+Q56 | R57: =R55+R56 | S57: =S55+S56 | T57: =T55+T56 | U57: =U55+U56 | ... AL57: =AL55+AL56 | AN57: =INDEX($O57:$AL57,1,AN$5*12) | AO57: =INDEX($O57:$AL57,1,AO$5*12)
A58: Equity (opening net assets + cumulative net income) | B58: GBP k | N58: =N54-N57 | O58: =N58+O42 | P58: =O58+P42 | Q58: =P58+Q42 | R58: =Q58+R42 | S58: =R58+S42 | T58: =S58+T42 | U58: =T58+U42 | V58: =U58+V42 | ... AL58: =AK58+AL42 | AN58: =INDEX($O58:$AL58,1,AN$5*12) | AO58: =INDEX($O58:$AL58,1,AO$5*12)
A59: Balance check | B59: GBP k | N59: =N54-N57-N58 | O59: =O54-O57-O58 | P59: =P54-P57-P58 | Q59: =Q54-Q57-Q58 | R59: =R54-R57-R58 | S59: =S54-S57-S58 | T59: =T54-T57-T58 | U59: =U54-U57-U58 | ... AL59: =AL54-AL57-AL58 | AN59: =INDEX($O59:$AL59,1,AN$5*12) | AO59: =INDEX($O59:$AL59,1,AO$5*12)
A61: Cash flow
A62: Depreciation | B62: GBP k | O62: =O38 | P62: =P38 | Q62: =Q38 | R62: =R38 | S62: =S38 | T62: =T38 | U62: =U38 | V62: =V38 | ... AL62: =AL38 | AN62: =SUMIF($O$5:$AL$5,AN$5,$O62:$AL62) | AO62: =SUMIF($O$5:$AL$5,AO$5,$O62:$AL62)
A63: (Increase) / decrease in receivables | B63: GBP k | O63: =-(O52-N52) | P63: =-(P52-O52) | Q63: =-(Q52-P52) | R63: =-(R52-Q52) | S63: =-(S52-R52) | T63: =-(T52-S52) | U63: =-(U52-T52) | V63: =-(V52-U52) | ... AL63: =-(AL52-AK52) | AN63: =SUMIF($O$5:$AL$5,AN$5,$O63:$AL63) | AO63: =SUMIF($O$5:$AL$5,AO$5,$O63:$AL63)
A64: Increase / (decrease) in payables | B64: GBP k | O64: =O55-N55 | P64: =P55-O55 | Q64: =Q55-P55 | R64: =R55-Q55 | S64: =S55-R55 | T64: =T55-S55 | U64: =U55-T55 | V64: =V55-U55 | ... AL64: =AL55-AK55 | AN64: =SUMIF($O$5:$AL$5,AN$5,$O64:$AL64) | AO64: =SUMIF($O$5:$AL$5,AO$5,$O64:$AL64)
A65: Increase / (decrease) in deferred revenue | B65: GBP k | O65: =O56-N56 | P65: =P56-O56 | Q65: =Q56-P56 | R65: =R56-Q56 | S65: =S56-R56 | T65: =T56-S56 | U65: =U56-T56 | V65: =V56-U56 | ... AL65: =AL56-AK56 | AN65: =SUMIF($O$5:$AL$5,AN$5,$O65:$AL65) | AO65: =SUMIF($O$5:$AL$5,AO$5,$O65:$AL65)
A66: Net cash flow (net income + non-cash + working capital - capex) | B66: GBP k | O66: =O42+O62+O63+O64+O65-O46 | P66: =P42+P62+P63+P64+P65-P46 | Q66: =Q42+Q62+Q63+Q64+Q65-Q46 | R66: =R42+R62+R63+R64+R65-R46 | S66: =S42+S62+S63+S64+S65-S46 | T66: =T42+T62+T63+T64+T65-T46 | U66: =U42+U62+U63+U64+U65-U46 | V66: =V42+V62+V63+V64+V65-V46 | ... AL66: =AL42+AL62+AL63+AL64+AL65-AL46 | AN66: =SUMIF($O$5:$AL$5,AN$5,$O66:$AL66) | AO66: =SUMIF($O$5:$AL$5,AO$5,$O66:$AL66)
A67: Opening cash | B67: GBP k | O67: =N68 | P67: =O68 | Q67: =P68 | R67: =Q68 | S67: =R68 | T67: =S68 | U67: =T68 | V67: =U68 | ... AL67: =AK68 | AN67: =INDEX($O67:$AL67,1,(AN$5-1)*12+1) | AO67: =INDEX($O67:$AL67,1,(AO$5-1)*12+1)
A68: Closing cash | B68: GBP k | N68: =inp_v_open_cash | O68: =O67+O66 | P68: =P67+P66 | Q68: =Q67+Q66 | R68: =R67+R66 | S68: =S67+S66 | T68: =T67+T66 | U68: =U67+U66 | V68: =V67+V66 | ... AL68: =AL67+AL66 | AN68: =INDEX($O68:$AL68,1,AN$5*12) | AO68: =INDEX($O68:$AL68,1,AO$5*12)
A69: Unlevered free cash flow (EBITDA - tax - capex + working capital) | B69: GBP k | O69: =O36-O41-O46+O63+O64+O65 | P69: =P36-P41-P46+P63+P64+P65 | Q69: =Q36-Q41-Q46+Q63+Q64+Q65 | R69: =R36-R41-R46+R63+R64+R65 | S69: =S36-S41-S46+S63+S64+S65 | T69: =T36-T41-T46+T63+T64+T65 | U69: =U36-U41-U46+U63+U64+U65 | V69: =V36-V41-V46+V63+V64+V65 | ... AL69: =AL36-AL41-AL46+AL63+AL64+AL65 | AN69: =SUMIF($O$5:$AL$5,AN$5,$O69:$AL69) | AO69: =SUMIF($O$5:$AL$5,AO$5,$O69:$AL69)

Sheet MA_PPA
A1: MA_PPA - IFRS 3 purchase price allocation (deal closes at the model's opening date)
A2: GBP thousands. Column C = IFRS 3 (acquired deferred revenue at fair value). Column D = US GAAP after ASU 2021-08 (deferred revenue carried over per ASC 606), shown for comparison.
C4: IFRS 3 | D4: US GAAP | E4: Note
A5: Consideration
A6: Vaultline opening ARR | C6: =MA_Target!N17 | D6: =MA_Target!N17
A7: Offer multiple (EV / ARR) | C7: =inp_ma_offer_mult | D7: =inp_ma_offer_mult
A8: Enterprise value offered | C8: =C6*C7 | D8: =C6*C7
A9: + Cash acquired (Vaultline has no debt) | C9: =MA_Target!N51 | D9: =MA_Target!N51
A10: Equity purchase price | C10: =C8+C9 | D10: =C8+C9
A11: Funded by: acquisition term loan | C11: =inp_ma_debt | D11: =inp_ma_debt
A12: Funded by: Northgate cash | C12: =C10-C11 | D12: =C10-C11 | E12: Check the Checks tab: pro-forma cash must stay positive
A13: Transaction costs (expensed in month 1, not part of consideration) | C13: =inp_ma_deal_cost_pct*C8 | D13: =inp_ma_deal_cost_pct*C8 | E13: IFRS 3.53: acquisition-related costs are expensed
A15: Net assets acquired at book value
A16: Cash | C16: =MA_Target!N51 | D16: =MA_Target!N51
A17: Trade receivables | C17: =MA_Target!N52 | D17: =MA_Target!N52
A18: PP&E | C18: =MA_Target!N53 | D18: =MA_Target!N53
A19: Trade payables | C19: =-MA_Target!N55 | D19: =-MA_Target!N55
A20: Deferred revenue (book) | C20: =-MA_Target!N56 | D20: =-MA_Target!N56
A21: Net assets at book value | C21: =SUM(C16:C20) | D21: =SUM(C16:C20) | E21: Equals Vaultline's opening equity
A23: Fair value adjustments
A24: Deferred revenue: fair-value haircut (reduces the liability) | C24: =inp_ma_dr_haircut*-C20 | D24: =0 | E24: IFRS 3 measures it at fair value: less than book. US GAAP (ASU 2021-08) carries it over, so no haircut
A25: Customer relationships (intangible) | C25: =inp_ma_cr_pct*C8 | D25: =inp_ma_cr_pct*C8 | E25: Amortised straight-line over inp_ma_cr_life
A26: Acquired technology (intangible) | C26: =inp_ma_tech_pct*C8 | D26: =inp_ma_tech_pct*C8 | E26: Amortised straight-line over inp_ma_tech_life
A27: Deferred tax liability on intangibles | C27: =-inp_tax*(C25+C26) | D27: =-inp_tax*(C25+C26) | E27: Intangibles have no tax base in a share deal, so a DTL is recognised
A28: Fair value of identifiable net assets | C28: =C21+C24+C25+C26+C27 | D28: =D21+D24+D25+D26+D27
A30: Goodwill
A31: Goodwill = equity purchase price - fair value of net assets | C31: =C10-C28 | D31: =D10-D28 | E31: Not amortised under IFRS; tested annually for impairment. Positive = goodwill; negative would be a bargain purchase
A32: Goodwill as % of equity purchase price | C32: =C31/C10 | D32: =D31/D10
A34: What the choice of standard changes after closing
A35: Year 1 revenue lost because acquired deferred revenue is written down | C35: =C24 | D35: =0 | E35: Unwinds over 12 months. The cash is still collected; reported revenue and EBITDA are lower under IFRS 3
A36: Monthly amortisation of acquired intangibles | C36: =C25/inp_ma_cr_life+C26/inp_ma_tech_life | D36: =C25/inp_ma_cr_life+C26/inp_ma_tech_life
A37: Annual amortisation of acquired intangibles | C37: =C36*12 | D37: =C36*12 | E37: Below EBITDA but reduces operating profit and net income

Sheet MA_ProForma
A1: MA_ProForma - Northgate + Vaultline: eliminations, synergies, integration, PPA effects (deal closes at t=0)
A2: GBP thousands unless stated. Blue = input, black = formula, green = link to another tab.
A3: Period # | C3: =COLUMN()-COLUMN($N$1) | D3: =COLUMN()-COLUMN($N$1) | E3: =COLUMN()-COLUMN($N$1) | F3: =COLUMN()-COLUMN($N$1) | G3: =COLUMN()-COLUMN($N$1) | H3: =COLUMN()-COLUMN($N$1) | I3: =COLUMN()-COLUMN($N$1) | J3: =COLUMN()-COLUMN($N$1) | ... AL3: =COLUMN()-COLUMN($N$1) | AN3: Annual | AO3: Annual
A4: Period ending | C4: =EOMONTH(inp_model_start,C3-1) | D4: =EOMONTH(inp_model_start,D3-1) | E4: =EOMONTH(inp_model_start,E3-1) | F4: =EOMONTH(inp_model_start,F3-1) | G4: =EOMONTH(inp_model_start,G3-1) | H4: =EOMONTH(inp_model_start,H3-1) | I4: =EOMONTH(inp_model_start,I3-1) | J4: =EOMONTH(inp_model_start,J3-1) | ... AL4: =EOMONTH(inp_model_start,AL3-1) | AN4: ="FY"&(YEAR(inp_model_start)+AN5-1) | AO4: ="FY"&(YEAR(inp_model_start)+AO5-1)
A5: Year | C5: =IF(C3<1,0,ROUNDUP(C3/12,0)) | D5: =IF(D3<1,0,ROUNDUP(D3/12,0)) | E5: =IF(E3<1,0,ROUNDUP(E3/12,0)) | F5: =IF(F3<1,0,ROUNDUP(F3/12,0)) | G5: =IF(G3<1,0,ROUNDUP(G3/12,0)) | H5: =IF(H3<1,0,ROUNDUP(H3/12,0)) | I5: =IF(I3<1,0,ROUNDUP(I3/12,0)) | J5: =IF(J3<1,0,ROUNDUP(J3/12,0)) | ... AL5: =IF(AL3<1,0,ROUNDUP(AL3/12,0)) | AN5: =COLUMN()-COLUMN($AM$1) | AO5: =COLUMN()-COLUMN($AM$1)
A6: Quarter | C6: =IF(C3<1,0,ROUNDUP(C3/3,0)) | D6: =IF(D3<1,0,ROUNDUP(D3/3,0)) | E6: =IF(E3<1,0,ROUNDUP(E3/3,0)) | F6: =IF(F3<1,0,ROUNDUP(F3/3,0)) | G6: =IF(G3<1,0,ROUNDUP(G3/3,0)) | H6: =IF(H3<1,0,ROUNDUP(H3/3,0)) | I6: =IF(I3<1,0,ROUNDUP(I3/3,0)) | J6: =IF(J3<1,0,ROUNDUP(J3/3,0)) | ... AL6: =IF(AL3<1,0,ROUNDUP(AL3/3,0))
A8: Northgate standalone (links)
A9: Northgate ARR: Opening ARR | B9: GBP k | O9: =SaaS_Metrics!O9 | P9: =SaaS_Metrics!P9 | Q9: =SaaS_Metrics!Q9 | R9: =SaaS_Metrics!R9 | S9: =SaaS_Metrics!S9 | T9: =SaaS_Metrics!T9 | U9: =SaaS_Metrics!U9 | V9: =SaaS_Metrics!V9 | ... AL9: =SaaS_Metrics!AL9 | AN9: =INDEX($O9:$AL9,1,(AN$5-1)*12+1) | AO9: =INDEX($O9:$AL9,1,(AO$5-1)*12+1)
A10: Northgate ARR: + New logos | B10: GBP k | O10: =SaaS_Metrics!O10 | P10: =SaaS_Metrics!P10 | Q10: =SaaS_Metrics!Q10 | R10: =SaaS_Metrics!R10 | S10: =SaaS_Metrics!S10 | T10: =SaaS_Metrics!T10 | U10: =SaaS_Metrics!U10 | V10: =SaaS_Metrics!V10 | ... AL10: =SaaS_Metrics!AL10 | AN10: =SUMIF($O$5:$AL$5,AN$5,$O10:$AL10) | AO10: =SUMIF($O$5:$AL$5,AO$5,$O10:$AL10)
A11: Northgate ARR: + Expansion | B11: GBP k | O11: =SaaS_Metrics!O11 | P11: =SaaS_Metrics!P11 | Q11: =SaaS_Metrics!Q11 | R11: =SaaS_Metrics!R11 | S11: =SaaS_Metrics!S11 | T11: =SaaS_Metrics!T11 | U11: =SaaS_Metrics!U11 | V11: =SaaS_Metrics!V11 | ... AL11: =SaaS_Metrics!AL11 | AN11: =SUMIF($O$5:$AL$5,AN$5,$O11:$AL11) | AO11: =SUMIF($O$5:$AL$5,AO$5,$O11:$AL11)
A12: Northgate ARR: - Churn | B12: GBP k | O12: =SaaS_Metrics!O12 | P12: =SaaS_Metrics!P12 | Q12: =SaaS_Metrics!Q12 | R12: =SaaS_Metrics!R12 | S12: =SaaS_Metrics!S12 | T12: =SaaS_Metrics!T12 | U12: =SaaS_Metrics!U12 | V12: =SaaS_Metrics!V12 | ... AL12: =SaaS_Metrics!AL12 | AN12: =SUMIF($O$5:$AL$5,AN$5,$O12:$AL12) | AO12: =SUMIF($O$5:$AL$5,AO$5,$O12:$AL12)
A13: Northgate closing ARR | B13: GBP k | N13: =SaaS_Metrics!N13 | O13: =SaaS_Metrics!O13 | P13: =SaaS_Metrics!P13 | Q13: =SaaS_Metrics!Q13 | R13: =SaaS_Metrics!R13 | S13: =SaaS_Metrics!S13 | T13: =SaaS_Metrics!T13 | U13: =SaaS_Metrics!U13 | ... AL13: =SaaS_Metrics!AL13 | AN13: =INDEX($O13:$AL13,1,AN$5*12) | AO13: =INDEX($O13:$AL13,1,AO$5*12)
A14: Northgate revenue | B14: GBP k | O14: =IS!O12 | P14: =IS!P12 | Q14: =IS!Q12 | R14: =IS!R12 | S14: =IS!S12 | T14: =IS!T12 | U14: =IS!U12 | V14: =IS!V12 | ... AL14: =IS!AL12 | AN14: =SUMIF($O$5:$AL$5,AN$5,$O14:$AL14) | AO14: =SUMIF($O$5:$AL$5,AO$5,$O14:$AL14)
A15: Northgate EBITDA | B15: GBP k | O15: =IS!O29 | P15: =IS!P29 | Q15: =IS!Q29 | R15: =IS!R29 | S15: =IS!S29 | T15: =IS!T29 | U15: =IS!U29 | V15: =IS!V29 | ... AL15: =IS!AL29 | AN15: =SUMIF($O$5:$AL$5,AN$5,$O15:$AL15) | AO15: =SUMIF($O$5:$AL$5,AO$5,$O15:$AL15)
A16: Northgate net income | B16: GBP k | O16: =IS!O36 | P16: =IS!P36 | Q16: =IS!Q36 | R16: =IS!R36 | S16: =IS!S36 | T16: =IS!T36 | U16: =IS!U36 | V16: =IS!V36 | ... AL16: =IS!AL36 | AN16: =SUMIF($O$5:$AL$5,AN$5,$O16:$AL16) | AO16: =SUMIF($O$5:$AL$5,AO$5,$O16:$AL16)
A17: Northgate free cash flow | B17: GBP k | O17: =CF!O22 | P17: =CF!P22 | Q17: =CF!Q22 | R17: =CF!R22 | S17: =CF!S22 | T17: =CF!T22 | U17: =CF!U22 | V17: =CF!V22 | ... AL17: =CF!AL22 | AN17: =SUMIF($O$5:$AL$5,AN$5,$O17:$AL17) | AO17: =SUMIF($O$5:$AL$5,AO$5,$O17:$AL17)
A18: Northgate cash | B18: GBP k | N18: =BS!N9 | O18: =BS!O9 | P18: =BS!P9 | Q18: =BS!Q9 | R18: =BS!R9 | S18: =BS!S9 | T18: =BS!T9 | U18: =BS!U9 | ... AL18: =BS!AL9 | AN18: =INDEX($O18:$AL18,1,AN$5*12) | AO18: =INDEX($O18:$AL18,1,AO$5*12)
A19: Northgate receivables | B19: GBP k | N19: =BS!N10 | O19: =BS!O10 | P19: =BS!P10 | Q19: =BS!Q10 | R19: =BS!R10 | S19: =BS!S10 | T19: =BS!T10 | U19: =BS!U10 | ... AL19: =BS!AL10 | AN19: =INDEX($O19:$AL19,1,AN$5*12) | AO19: =INDEX($O19:$AL19,1,AO$5*12)
A20: Northgate PP&E | B20: GBP k | N20: =BS!N11 | O20: =BS!O11 | P20: =BS!P11 | Q20: =BS!Q11 | R20: =BS!R11 | S20: =BS!S11 | T20: =BS!T11 | U20: =BS!U11 | ... AL20: =BS!AL11 | AN20: =INDEX($O20:$AL20,1,AN$5*12) | AO20: =INDEX($O20:$AL20,1,AO$5*12)
A21: Northgate contract-cost asset | B21: GBP k | N21: =BS!N12 | O21: =BS!O12 | P21: =BS!P12 | Q21: =BS!Q12 | R21: =BS!R12 | S21: =BS!S12 | T21: =BS!T12 | U21: =BS!U12 | ... AL21: =BS!AL12 | AN21: =INDEX($O21:$AL21,1,AN$5*12) | AO21: =INDEX($O21:$AL21,1,AO$5*12)
A22: Northgate payables | B22: GBP k | N22: =BS!N16 | O22: =BS!O16 | P22: =BS!P16 | Q22: =BS!Q16 | R22: =BS!R16 | S22: =BS!S16 | T22: =BS!T16 | U22: =BS!U16 | ... AL22: =BS!AL16 | AN22: =INDEX($O22:$AL22,1,AN$5*12) | AO22: =INDEX($O22:$AL22,1,AO$5*12)
A23: Northgate deferred revenue | B23: GBP k | N23: =BS!N17 | O23: =BS!O17 | P23: =BS!P17 | Q23: =BS!Q17 | R23: =BS!R17 | S23: =BS!S17 | T23: =BS!T17 | U23: =BS!U17 | ... AL23: =BS!AL17 | AN23: =INDEX($O23:$AL23,1,AN$5*12) | AO23: =INDEX($O23:$AL23,1,AO$5*12)
A24: Northgate equity | B24: GBP k | N24: =BS!N21 | O24: =BS!O21 | P24: =BS!P21 | Q24: =BS!Q21 | R24: =BS!R21 | S24: =BS!S21 | T24: =BS!T21 | U24: =BS!U21 | ... AL24: =BS!AL21 | AN24: =INDEX($O24:$AL24,1,AN$5*12) | AO24: =INDEX($O24:$AL24,1,AO$5*12)
A26: Vaultline (multiplied by the include switch)
A27: Vaultline ARR: Opening ARR | B27: GBP k | O27: =inp_ma_include*MA_Target!O13 | P27: =inp_ma_include*MA_Target!P13 | Q27: =inp_ma_include*MA_Target!Q13 | R27: =inp_ma_include*MA_Target!R13 | S27: =inp_ma_include*MA_Target!S13 | T27: =inp_ma_include*MA_Target!T13 | U27: =inp_ma_include*MA_Target!U13 | V27: =inp_ma_include*MA_Target!V13 | ... AL27: =inp_ma_include*MA_Target!AL13 | AN27: =INDEX($O27:$AL27,1,(AN$5-1)*12+1) | AO27: =INDEX($O27:$AL27,1,(AO$5-1)*12+1)
A28: Vaultline ARR: + New logos | B28: GBP k | O28: =inp_ma_include*MA_Target!O14 | P28: =inp_ma_include*MA_Target!P14 | Q28: =inp_ma_include*MA_Target!Q14 | R28: =inp_ma_include*MA_Target!R14 | S28: =inp_ma_include*MA_Target!S14 | T28: =inp_ma_include*MA_Target!T14 | U28: =inp_ma_include*MA_Target!U14 | V28: =inp_ma_include*MA_Target!V14 | ... AL28: =inp_ma_include*MA_Target!AL14 | AN28: =SUMIF($O$5:$AL$5,AN$5,$O28:$AL28) | AO28: =SUMIF($O$5:$AL$5,AO$5,$O28:$AL28)
A29: Vaultline ARR: + Expansion | B29: GBP k | O29: =inp_ma_include*MA_Target!O15 | P29: =inp_ma_include*MA_Target!P15 | Q29: =inp_ma_include*MA_Target!Q15 | R29: =inp_ma_include*MA_Target!R15 | S29: =inp_ma_include*MA_Target!S15 | T29: =inp_ma_include*MA_Target!T15 | U29: =inp_ma_include*MA_Target!U15 | V29: =inp_ma_include*MA_Target!V15 | ... AL29: =inp_ma_include*MA_Target!AL15 | AN29: =SUMIF($O$5:$AL$5,AN$5,$O29:$AL29) | AO29: =SUMIF($O$5:$AL$5,AO$5,$O29:$AL29)
A30: Vaultline ARR: - Churn | B30: GBP k | O30: =inp_ma_include*MA_Target!O16 | P30: =inp_ma_include*MA_Target!P16 | Q30: =inp_ma_include*MA_Target!Q16 | R30: =inp_ma_include*MA_Target!R16 | S30: =inp_ma_include*MA_Target!S16 | T30: =inp_ma_include*MA_Target!T16 | U30: =inp_ma_include*MA_Target!U16 | V30: =inp_ma_include*MA_Target!V16 | ... AL30: =inp_ma_include*MA_Target!AL16 | AN30: =SUMIF($O$5:$AL$5,AN$5,$O30:$AL30) | AO30: =SUMIF($O$5:$AL$5,AO$5,$O30:$AL30)
A31: Vaultline closing ARR | B31: GBP k | N31: =inp_ma_include*MA_Target!N17 | O31: =inp_ma_include*MA_Target!O17 | P31: =inp_ma_include*MA_Target!P17 | Q31: =inp_ma_include*MA_Target!Q17 | R31: =inp_ma_include*MA_Target!R17 | S31: =inp_ma_include*MA_Target!S17 | T31: =inp_ma_include*MA_Target!T17 | U31: =inp_ma_include*MA_Target!U17 | ... AL31: =inp_ma_include*MA_Target!AL17 | AN31: =INDEX($O31:$AL31,1,AN$5*12) | AO31: =INDEX($O31:$AL31,1,AO$5*12)
A32: Vaultline revenue | B32: GBP k | O32: =inp_ma_include*MA_Target!O23 | P32: =inp_ma_include*MA_Target!P23 | Q32: =inp_ma_include*MA_Target!Q23 | R32: =inp_ma_include*MA_Target!R23 | S32: =inp_ma_include*MA_Target!S23 | T32: =inp_ma_include*MA_Target!T23 | U32: =inp_ma_include*MA_Target!U23 | V32: =inp_ma_include*MA_Target!V23 | ... AL32: =inp_ma_include*MA_Target!AL23 | AN32: =SUMIF($O$5:$AL$5,AN$5,$O32:$AL32) | AO32: =SUMIF($O$5:$AL$5,AO$5,$O32:$AL32)
A33: Vaultline EBITDA | B33: GBP k | O33: =inp_ma_include*MA_Target!O36 | P33: =inp_ma_include*MA_Target!P36 | Q33: =inp_ma_include*MA_Target!Q36 | R33: =inp_ma_include*MA_Target!R36 | S33: =inp_ma_include*MA_Target!S36 | T33: =inp_ma_include*MA_Target!T36 | U33: =inp_ma_include*MA_Target!U36 | V33: =inp_ma_include*MA_Target!V36 | ... AL33: =inp_ma_include*MA_Target!AL36 | AN33: =SUMIF($O$5:$AL$5,AN$5,$O33:$AL33) | AO33: =SUMIF($O$5:$AL$5,AO$5,$O33:$AL33)
A34: Vaultline net income | B34: GBP k | O34: =inp_ma_include*MA_Target!O42 | P34: =inp_ma_include*MA_Target!P42 | Q34: =inp_ma_include*MA_Target!Q42 | R34: =inp_ma_include*MA_Target!R42 | S34: =inp_ma_include*MA_Target!S42 | T34: =inp_ma_include*MA_Target!T42 | U34: =inp_ma_include*MA_Target!U42 | V34: =inp_ma_include*MA_Target!V42 | ... AL34: =inp_ma_include*MA_Target!AL42 | AN34: =SUMIF($O$5:$AL$5,AN$5,$O34:$AL34) | AO34: =SUMIF($O$5:$AL$5,AO$5,$O34:$AL34)
A35: Vaultline free cash flow | B35: GBP k | O35: =inp_ma_include*MA_Target!O66 | P35: =inp_ma_include*MA_Target!P66 | Q35: =inp_ma_include*MA_Target!Q66 | R35: =inp_ma_include*MA_Target!R66 | S35: =inp_ma_include*MA_Target!S66 | T35: =inp_ma_include*MA_Target!T66 | U35: =inp_ma_include*MA_Target!U66 | V35: =inp_ma_include*MA_Target!V66 | ... AL35: =inp_ma_include*MA_Target!AL66 | AN35: =SUMIF($O$5:$AL$5,AN$5,$O35:$AL35) | AO35: =SUMIF($O$5:$AL$5,AO$5,$O35:$AL35)
A36: Vaultline cash | B36: GBP k | N36: =inp_ma_include*MA_Target!N51 | O36: =inp_ma_include*MA_Target!O51 | P36: =inp_ma_include*MA_Target!P51 | Q36: =inp_ma_include*MA_Target!Q51 | R36: =inp_ma_include*MA_Target!R51 | S36: =inp_ma_include*MA_Target!S51 | T36: =inp_ma_include*MA_Target!T51 | U36: =inp_ma_include*MA_Target!U51 | ... AL36: =inp_ma_include*MA_Target!AL51 | AN36: =INDEX($O36:$AL36,1,AN$5*12) | AO36: =INDEX($O36:$AL36,1,AO$5*12)
A37: Vaultline receivables | B37: GBP k | N37: =inp_ma_include*MA_Target!N52 | O37: =inp_ma_include*MA_Target!O52 | P37: =inp_ma_include*MA_Target!P52 | Q37: =inp_ma_include*MA_Target!Q52 | R37: =inp_ma_include*MA_Target!R52 | S37: =inp_ma_include*MA_Target!S52 | T37: =inp_ma_include*MA_Target!T52 | U37: =inp_ma_include*MA_Target!U52 | ... AL37: =inp_ma_include*MA_Target!AL52 | AN37: =INDEX($O37:$AL37,1,AN$5*12) | AO37: =INDEX($O37:$AL37,1,AO$5*12)
A38: Vaultline PP&E | B38: GBP k | N38: =inp_ma_include*MA_Target!N53 | O38: =inp_ma_include*MA_Target!O53 | P38: =inp_ma_include*MA_Target!P53 | Q38: =inp_ma_include*MA_Target!Q53 | R38: =inp_ma_include*MA_Target!R53 | S38: =inp_ma_include*MA_Target!S53 | T38: =inp_ma_include*MA_Target!T53 | U38: =inp_ma_include*MA_Target!U53 | ... AL38: =inp_ma_include*MA_Target!AL53 | AN38: =INDEX($O38:$AL38,1,AN$5*12) | AO38: =INDEX($O38:$AL38,1,AO$5*12)
A39: Vaultline payables | B39: GBP k | N39: =inp_ma_include*MA_Target!N55 | O39: =inp_ma_include*MA_Target!O55 | P39: =inp_ma_include*MA_Target!P55 | Q39: =inp_ma_include*MA_Target!Q55 | R39: =inp_ma_include*MA_Target!R55 | S39: =inp_ma_include*MA_Target!S55 | T39: =inp_ma_include*MA_Target!T55 | U39: =inp_ma_include*MA_Target!U55 | ... AL39: =inp_ma_include*MA_Target!AL55 | AN39: =INDEX($O39:$AL39,1,AN$5*12) | AO39: =INDEX($O39:$AL39,1,AO$5*12)
A40: Vaultline deferred revenue (book) | B40: GBP k | N40: =inp_ma_include*MA_Target!N56 | O40: =inp_ma_include*MA_Target!O56 | P40: =inp_ma_include*MA_Target!P56 | Q40: =inp_ma_include*MA_Target!Q56 | R40: =inp_ma_include*MA_Target!R56 | S40: =inp_ma_include*MA_Target!S56 | T40: =inp_ma_include*MA_Target!T56 | U40: =inp_ma_include*MA_Target!U56 | ... AL40: =inp_ma_include*MA_Target!AL56 | AN40: =INDEX($O40:$AL40,1,AN$5*12) | AO40: =INDEX($O40:$AL40,1,AO$5*12)
A42: Intercompany elimination (Northgate software contract with Vaultline)
A43: Eliminate intercompany revenue | B43: GBP k | O43: =-inp_ma_include*inp_ma_ic_annual/12 | P43: =-inp_ma_include*inp_ma_ic_annual/12 | Q43: =-inp_ma_include*inp_ma_ic_annual/12 | R43: =-inp_ma_include*inp_ma_ic_annual/12 | S43: =-inp_ma_include*inp_ma_ic_annual/12 | T43: =-inp_ma_include*inp_ma_ic_annual/12 | U43: =-inp_ma_include*inp_ma_ic_annual/12 | V43: =-inp_ma_include*inp_ma_ic_annual/12 | ... AL43: =-inp_ma_include*inp_ma_ic_annual/12 | AN43: =SUMIF($O$5:$AL$5,AN$5,$O43:$AL43) | AO43: =SUMIF($O$5:$AL$5,AO$5,$O43:$AL43)
A44: Eliminate intercompany cost (EBITDA effect nil) | B44: GBP k | O44: =inp_ma_include*inp_ma_ic_annual/12 | P44: =inp_ma_include*inp_ma_ic_annual/12 | Q44: =inp_ma_include*inp_ma_ic_annual/12 | R44: =inp_ma_include*inp_ma_ic_annual/12 | S44: =inp_ma_include*inp_ma_ic_annual/12 | T44: =inp_ma_include*inp_ma_ic_annual/12 | U44: =inp_ma_include*inp_ma_ic_annual/12 | V44: =inp_ma_include*inp_ma_ic_annual/12 | ... AL44: =inp_ma_include*inp_ma_ic_annual/12 | AN44: =SUMIF($O$5:$AL$5,AN$5,$O44:$AL44) | AO44: =SUMIF($O$5:$AL$5,AO$5,$O44:$AL44)
A46: Synergies at 100% of plan (before include switch and achievement %)
A47: Ramp factor | B47: x | O47: =MIN(1,MAX(0,(O$3-inp_ma_syn_start+1)/inp_ma_syn_ramp)) | P47: =MIN(1,MAX(0,(P$3-inp_ma_syn_start+1)/inp_ma_syn_ramp)) | Q47: =MIN(1,MAX(0,(Q$3-inp_ma_syn_start+1)/inp_ma_syn_ramp)) | R47: =MIN(1,MAX(0,(R$3-inp_ma_syn_start+1)/inp_ma_syn_ramp)) | S47: =MIN(1,MAX(0,(S$3-inp_ma_syn_start+1)/inp_ma_syn_ramp)) | T47: =MIN(1,MAX(0,(T$3-inp_ma_syn_start+1)/inp_ma_syn_ramp)) | U47: =MIN(1,MAX(0,(U$3-inp_ma_syn_start+1)/inp_ma_syn_ramp)) | V47: =MIN(1,MAX(0,(V$3-inp_ma_syn_start+1)/inp_ma_syn_ramp)) | ... AL47: =MIN(1,MAX(0,(AL$3-inp_ma_syn_start+1)/inp_ma_syn_ramp)) | AN47: =INDEX($O47:$AL47,1,AN$5*12) | AO47: =INDEX($O47:$AL47,1,AO$5*12)
A48: Cross-sell new ARR | B48: GBP k | O48: =inp_ma_xsell_logos_m*inp_ma_xsell_acv*O47 | P48: =inp_ma_xsell_logos_m*inp_ma_xsell_acv*P47 | Q48: =inp_ma_xsell_logos_m*inp_ma_xsell_acv*Q47 | R48: =inp_ma_xsell_logos_m*inp_ma_xsell_acv*R47 | S48: =inp_ma_xsell_logos_m*inp_ma_xsell_acv*S47 | T48: =inp_ma_xsell_logos_m*inp_ma_xsell_acv*T47 | U48: =inp_ma_xsell_logos_m*inp_ma_xsell_acv*U47 | V48: =inp_ma_xsell_logos_m*inp_ma_xsell_acv*V47 | ... AL48: =inp_ma_xsell_logos_m*inp_ma_xsell_acv*AL47 | AN48: =SUMIF($O$5:$AL$5,AN$5,$O48:$AL48) | AO48: =SUMIF($O$5:$AL$5,AO$5,$O48:$AL48)
A49: Cross-sell ARR (closing) | B49: GBP k | N49: =0 | O49: =N49+O48 | P49: =O49+P48 | Q49: =P49+Q48 | R49: =Q49+R48 | S49: =R49+S48 | T49: =S49+T48 | U49: =T49+U48 | V49: =U49+V48 | ... AL49: =AK49+AL48 | AN49: =INDEX($O49:$AL49,1,AN$5*12) | AO49: =INDEX($O49:$AL49,1,AO$5*12)
A50: Cross-sell revenue | B50: GBP k | O50: =(N49+O49)/2/12 | P50: =(O49+P49)/2/12 | Q50: =(P49+Q49)/2/12 | R50: =(Q49+R49)/2/12 | S50: =(R49+S49)/2/12 | T50: =(S49+T49)/2/12 | U50: =(T49+U49)/2/12 | V50: =(U49+V49)/2/12 | ... AL50: =(AK49+AL49)/2/12 | AN50: =SUMIF($O$5:$AL$5,AN$5,$O50:$AL50) | AO50: =SUMIF($O$5:$AL$5,AO$5,$O50:$AL50)
A51: Cross-sell contribution | B51: GBP k | O51: =O50*inp_ma_syn_margin | P51: =P50*inp_ma_syn_margin | Q51: =Q50*inp_ma_syn_margin | R51: =R50*inp_ma_syn_margin | S51: =S50*inp_ma_syn_margin | T51: =T50*inp_ma_syn_margin | U51: =U50*inp_ma_syn_margin | V51: =V50*inp_ma_syn_margin | ... AL51: =AL50*inp_ma_syn_margin | AN51: =SUMIF($O$5:$AL$5,AN$5,$O51:$AL51) | AO51: =SUMIF($O$5:$AL$5,AO$5,$O51:$AL51)
A52: Cost synergies | B52: GBP k | O52: =inp_ma_cost_syn/12*O47 | P52: =inp_ma_cost_syn/12*P47 | Q52: =inp_ma_cost_syn/12*Q47 | R52: =inp_ma_cost_syn/12*R47 | S52: =inp_ma_cost_syn/12*S47 | T52: =inp_ma_cost_syn/12*T47 | U52: =inp_ma_cost_syn/12*U47 | V52: =inp_ma_cost_syn/12*V47 | ... AL52: =inp_ma_cost_syn/12*AL47 | AN52: =SUMIF($O$5:$AL$5,AN$5,$O52:$AL52) | AO52: =SUMIF($O$5:$AL$5,AO$5,$O52:$AL52)
A53: Integration cost | B53: GBP k | O53: =IF(O$3<=inp_ma_integration_months,inp_ma_integration_total/inp_ma_integration_months,0) | P53: =IF(P$3<=inp_ma_integration_months,inp_ma_integration_total/inp_ma_integration_months,0) | Q53: =IF(Q$3<=inp_ma_integration_months,inp_ma_integration_total/inp_ma_integration_months,0) | R53: =IF(R$3<=inp_ma_integration_months,inp_ma_integration_total/inp_ma_integration_months,0) | S53: =IF(S$3<=inp_ma_integration_months,inp_ma_integration_total/inp_ma_integration_months,0) | T53: =IF(T$3<=inp_ma_integration_months,inp_ma_integration_total/inp_ma_integration_months,0) | U53: =IF(U$3<=inp_ma_integration_months,inp_ma_integration_total/inp_ma_integration_months,0) | V53: =IF(V$3<=inp_ma_integration_months,inp_ma_integration_total/inp_ma_integration_months,0) | ... AL53: =IF(AL$3<=inp_ma_integration_months,inp_ma_integration_total/inp_ma_integration_months,0) | AN53: =SUMIF($O$5:$AL$5,AN$5,$O53:$AL53) | AO53: =SUMIF($O$5:$AL$5,AO$5,$O53:$AL53)
A55: Adjustments in the pro-forma (include switch and achievement % applied)
A56: Synergy ARR (closing) | B56: GBP k | N56: =0 | O56: =inp_ma_include*inp_ma_syn_achieved*O49 | P56: =inp_ma_include*inp_ma_syn_achieved*P49 | Q56: =inp_ma_include*inp_ma_syn_achieved*Q49 | R56: =inp_ma_include*inp_ma_syn_achieved*R49 | S56: =inp_ma_include*inp_ma_syn_achieved*S49 | T56: =inp_ma_include*inp_ma_syn_achieved*T49 | U56: =inp_ma_include*inp_ma_syn_achieved*U49 | V56: =inp_ma_include*inp_ma_syn_achieved*V49 | ... AL56: =inp_ma_include*inp_ma_syn_achieved*AL49 | AN56: =INDEX($O56:$AL56,1,AN$5*12) | AO56: =INDEX($O56:$AL56,1,AO$5*12)
A57: Revenue synergies | B57: GBP k | O57: =inp_ma_include*inp_ma_syn_achieved*O50 | P57: =inp_ma_include*inp_ma_syn_achieved*P50 | Q57: =inp_ma_include*inp_ma_syn_achieved*Q50 | R57: =inp_ma_include*inp_ma_syn_achieved*R50 | S57: =inp_ma_include*inp_ma_syn_achieved*S50 | T57: =inp_ma_include*inp_ma_syn_achieved*T50 | U57: =inp_ma_include*inp_ma_syn_achieved*U50 | V57: =inp_ma_include*inp_ma_syn_achieved*V50 | ... AL57: =inp_ma_include*inp_ma_syn_achieved*AL50 | AN57: =SUMIF($O$5:$AL$5,AN$5,$O57:$AL57) | AO57: =SUMIF($O$5:$AL$5,AO$5,$O57:$AL57)
A58: EBITDA from synergies (cross-sell contribution + cost savings) | B58: GBP k | O58: =inp_ma_include*inp_ma_syn_achieved*(O51+O52) | P58: =inp_ma_include*inp_ma_syn_achieved*(P51+P52) | Q58: =inp_ma_include*inp_ma_syn_achieved*(Q51+Q52) | R58: =inp_ma_include*inp_ma_syn_achieved*(R51+R52) | S58: =inp_ma_include*inp_ma_syn_achieved*(S51+S52) | T58: =inp_ma_include*inp_ma_syn_achieved*(T51+T52) | U58: =inp_ma_include*inp_ma_syn_achieved*(U51+U52) | V58: =inp_ma_include*inp_ma_syn_achieved*(V51+V52) | ... AL58: =inp_ma_include*inp_ma_syn_achieved*(AL51+AL52) | AN58: =SUMIF($O$5:$AL$5,AN$5,$O58:$AL58) | AO58: =SUMIF($O$5:$AL$5,AO$5,$O58:$AL58)
A59: Integration costs | B59: GBP k | O59: =-inp_ma_include*O53 | P59: =-inp_ma_include*P53 | Q59: =-inp_ma_include*Q53 | R59: =-inp_ma_include*R53 | S59: =-inp_ma_include*S53 | T59: =-inp_ma_include*T53 | U59: =-inp_ma_include*U53 | V59: =-inp_ma_include*V53 | ... AL59: =-inp_ma_include*AL53 | AN59: =SUMIF($O$5:$AL$5,AN$5,$O59:$AL59) | AO59: =SUMIF($O$5:$AL$5,AO$5,$O59:$AL59)
A60: Transaction costs | B60: GBP k | O60: =-inp_ma_include*IF(O$3=1,MA_PPA!$C$13,0) | P60: =-inp_ma_include*IF(P$3=1,MA_PPA!$C$13,0) | Q60: =-inp_ma_include*IF(Q$3=1,MA_PPA!$C$13,0) | R60: =-inp_ma_include*IF(R$3=1,MA_PPA!$C$13,0) | S60: =-inp_ma_include*IF(S$3=1,MA_PPA!$C$13,0) | T60: =-inp_ma_include*IF(T$3=1,MA_PPA!$C$13,0) | U60: =-inp_ma_include*IF(U$3=1,MA_PPA!$C$13,0) | V60: =-inp_ma_include*IF(V$3=1,MA_PPA!$C$13,0) | ... AL60: =-inp_ma_include*IF(AL$3=1,MA_PPA!$C$13,0) | AN60: =SUMIF($O$5:$AL$5,AN$5,$O60:$AL60) | AO60: =SUMIF($O$5:$AL$5,AO$5,$O60:$AL60)
A61: Revenue lost: acquired deferred revenue at fair value (IFRS 3) | B61: GBP k | O61: =-inp_ma_include*IF(O$3<=12,MA_PPA!$C$24/12,0) | P61: =-inp_ma_include*IF(P$3<=12,MA_PPA!$C$24/12,0) | Q61: =-inp_ma_include*IF(Q$3<=12,MA_PPA!$C$24/12,0) | R61: =-inp_ma_include*IF(R$3<=12,MA_PPA!$C$24/12,0) | S61: =-inp_ma_include*IF(S$3<=12,MA_PPA!$C$24/12,0) | T61: =-inp_ma_include*IF(T$3<=12,MA_PPA!$C$24/12,0) | U61: =-inp_ma_include*IF(U$3<=12,MA_PPA!$C$24/12,0) | V61: =-inp_ma_include*IF(V$3<=12,MA_PPA!$C$24/12,0) | ... AL61: =-inp_ma_include*IF(AL$3<=12,MA_PPA!$C$24/12,0) | AN61: =SUMIF($O$5:$AL$5,AN$5,$O61:$AL61) | AO61: =SUMIF($O$5:$AL$5,AO$5,$O61:$AL61)
A62: Amortisation of acquired intangibles | B62: GBP k | O62: =-inp_ma_include*(MA_PPA!$C$25/inp_ma_cr_life*IF(O$3<=inp_ma_cr_life,1,0)+MA_PPA!$C$26/inp_ma_tech_life*IF(O$3<=inp_ma_tech_life,1,0)) | P62: =-inp_ma_include*(MA_PPA!$C$25/inp_ma_cr_life*IF(P$3<=inp_ma_cr_life,1,0)+MA_PPA!$C$26/inp_ma_tech_life*IF(P$3<=inp_ma_tech_life,1,0)) | Q62: =-inp_ma_include*(MA_PPA!$C$25/inp_ma_cr_life*IF(Q$3<=inp_ma_cr_life,1,0)+MA_PPA!$C$26/inp_ma_tech_life*IF(Q$3<=inp_ma_tech_life,1,0)) | R62: =-inp_ma_include*(MA_PPA!$C$25/inp_ma_cr_life*IF(R$3<=inp_ma_cr_life,1,0)+MA_PPA!$C$26/inp_ma_tech_life*IF(R$3<=inp_ma_tech_life,1,0)) | S62: =-inp_ma_include*(MA_PPA!$C$25/inp_ma_cr_life*IF(S$3<=inp_ma_cr_life,1,0)+MA_PPA!$C$26/inp_ma_tech_life*IF(S$3<=inp_ma_tech_life,1,0)) | T62: =-inp_ma_include*(MA_PPA!$C$25/inp_ma_cr_life*IF(T$3<=inp_ma_cr_life,1,0)+MA_PPA!$C$26/inp_ma_tech_life*IF(T$3<=inp_ma_tech_life,1,0)) | U62: =-inp_ma_include*(MA_PPA!$C$25/inp_ma_cr_life*IF(U$3<=inp_ma_cr_life,1,0)+MA_PPA!$C$26/inp_ma_tech_life*IF(U$3<=inp_ma_tech_life,1,0)) | V62: =-inp_ma_include*(MA_PPA!$C$25/inp_ma_cr_life*IF(V$3<=inp_ma_cr_life,1,0)+MA_PPA!$C$26/inp_ma_tech_life*IF(V$3<=inp_ma_tech_life,1,0)) | ... AL62: =-inp_ma_include*(MA_PPA!$C$25/inp_ma_cr_life*IF(AL$3<=inp_ma_cr_life,1,0)+MA_PPA!$C$26/inp_ma_tech_life*IF(AL$3<=inp_ma_tech_life,1,0)) | AN62: =SUMIF($O$5:$AL$5,AN$5,$O62:$AL62) | AO62: =SUMIF($O$5:$AL$5,AO$5,$O62:$AL62)
A63: Deferred tax credit on amortisation (non-cash) | B63: GBP k | O63: =-O62*inp_tax | P63: =-P62*inp_tax | Q63: =-Q62*inp_tax | R63: =-R62*inp_tax | S63: =-S62*inp_tax | T63: =-T62*inp_tax | U63: =-U62*inp_tax | V63: =-V62*inp_tax | ... AL63: =-AL62*inp_tax | AN63: =SUMIF($O$5:$AL$5,AN$5,$O63:$AL63) | AO63: =SUMIF($O$5:$AL$5,AO$5,$O63:$AL63)
A64: Acquisition loan balance (bullet) | B64: GBP k | N64: =inp_ma_include*MA_PPA!$C$11 | O64: =N64 | P64: =O64 | Q64: =P64 | R64: =Q64 | S64: =R64 | T64: =S64 | U64: =T64 | V64: =U64 | ... AL64: =AK64 | AN64: =INDEX($O64:$AL64,1,AN$5*12) | AO64: =INDEX($O64:$AL64,1,AO$5*12)
A65: Interest on acquisition loan (prior-period balance) | B65: GBP k | O65: =-N64*inp_ma_loan_rate/12 | P65: =-O64*inp_ma_loan_rate/12 | Q65: =-P64*inp_ma_loan_rate/12 | R65: =-Q64*inp_ma_loan_rate/12 | S65: =-R64*inp_ma_loan_rate/12 | T65: =-S64*inp_ma_loan_rate/12 | U65: =-T64*inp_ma_loan_rate/12 | V65: =-U64*inp_ma_loan_rate/12 | ... AL65: =-AK64*inp_ma_loan_rate/12 | AN65: =SUMIF($O$5:$AL$5,AN$5,$O65:$AL65) | AO65: =SUMIF($O$5:$AL$5,AO$5,$O65:$AL65)
A66: Interest income lost on cash paid out (prior-period) | B66: GBP k | O66: =(N74-N18-N36)*inp_interest/12 | P66: =(O74-O18-O36)*inp_interest/12 | Q66: =(P74-P18-P36)*inp_interest/12 | R66: =(Q74-Q18-Q36)*inp_interest/12 | S66: =(R74-R18-R36)*inp_interest/12 | T66: =(S74-S18-S36)*inp_interest/12 | U66: =(T74-T18-T36)*inp_interest/12 | V66: =(U74-U18-U36)*inp_interest/12 | ... AL66: =(AK74-AK18-AK36)*inp_interest/12 | AN66: =SUMIF($O$5:$AL$5,AN$5,$O66:$AL66) | AO66: =SUMIF($O$5:$AL$5,AO$5,$O66:$AL66)
A68: Pro-forma income and cash
A69: Pro-forma revenue | B69: GBP k | O69: =O14+O32+O57+O43+O61 | P69: =P14+P32+P57+P43+P61 | Q69: =Q14+Q32+Q57+Q43+Q61 | R69: =R14+R32+R57+R43+R61 | S69: =S14+S32+S57+S43+S61 | T69: =T14+T32+T57+T43+T61 | U69: =U14+U32+U57+U43+U61 | V69: =V14+V32+V57+V43+V61 | ... AL69: =AL14+AL32+AL57+AL43+AL61 | AN69: =SUMIF($O$5:$AL$5,AN$5,$O69:$AL69) | AO69: =SUMIF($O$5:$AL$5,AO$5,$O69:$AL69)
A70: Pro-forma EBITDA | B70: GBP k | O70: =O15+O33+O58+O59+O60+O61 | P70: =P15+P33+P58+P59+P60+P61 | Q70: =Q15+Q33+Q58+Q59+Q60+Q61 | R70: =R15+R33+R58+R59+R60+R61 | S70: =S15+S33+S58+S59+S60+S61 | T70: =T15+T33+T58+T59+T60+T61 | U70: =U15+U33+U58+U59+U60+U61 | V70: =V15+V33+V58+V59+V60+V61 | ... AL70: =AL15+AL33+AL58+AL59+AL60+AL61 | AN70: =SUMIF($O$5:$AL$5,AN$5,$O70:$AL70) | AO70: =SUMIF($O$5:$AL$5,AO$5,$O70:$AL70)
A71: Pro-forma net income | B71: GBP k | O71: =O16+O34+O58+O59+O60+O61+O62+O63+O65+O66 | P71: =P16+P34+P58+P59+P60+P61+P62+P63+P65+P66 | Q71: =Q16+Q34+Q58+Q59+Q60+Q61+Q62+Q63+Q65+Q66 | R71: =R16+R34+R58+R59+R60+R61+R62+R63+R65+R66 | S71: =S16+S34+S58+S59+S60+S61+S62+S63+S65+S66 | T71: =T16+T34+T58+T59+T60+T61+T62+T63+T65+T66 | U71: =U16+U34+U58+U59+U60+U61+U62+U63+U65+U66 | V71: =V16+V34+V58+V59+V60+V61+V62+V63+V65+V66 | ... AL71: =AL16+AL34+AL58+AL59+AL60+AL61+AL62+AL63+AL65+AL66 | AN71: =SUMIF($O$5:$AL$5,AN$5,$O71:$AL71) | AO71: =SUMIF($O$5:$AL$5,AO$5,$O71:$AL71)
A72: Cash effect of adjustments | B72: GBP k | O72: =O58+O59+O60+O65+O66 | P72: =P58+P59+P60+P65+P66 | Q72: =Q58+Q59+Q60+Q65+Q66 | R72: =R58+R59+R60+R65+R66 | S72: =S58+S59+S60+S65+S66 | T72: =T58+T59+T60+T65+T66 | U72: =U58+U59+U60+U65+U66 | V72: =V58+V59+V60+V65+V66 | ... AL72: =AL58+AL59+AL60+AL65+AL66 | AN72: =SUMIF($O$5:$AL$5,AN$5,$O72:$AL72) | AO72: =SUMIF($O$5:$AL$5,AO$5,$O72:$AL72)
A73: Pro-forma free cash flow | B73: GBP k | O73: =O17+O35+O72 | P73: =P17+P35+P72 | Q73: =Q17+Q35+Q72 | R73: =R17+R35+R72 | S73: =S17+S35+S72 | T73: =T17+T35+T72 | U73: =U17+U35+U72 | V73: =V17+V35+V72 | ... AL73: =AL17+AL35+AL72 | AN73: =SUMIF($O$5:$AL$5,AN$5,$O73:$AL73) | AO73: =SUMIF($O$5:$AL$5,AO$5,$O73:$AL73)
A74: Pro-forma closing cash | B74: GBP k | N74: =N18+N36-inp_ma_include*MA_PPA!$C$10+inp_ma_include*MA_PPA!$C$11 | O74: =N74+O73 | P74: =O74+P73 | Q74: =P74+Q73 | R74: =Q74+R73 | S74: =R74+S73 | T74: =S74+T73 | U74: =T74+U73 | V74: =U74+V73 | ... AL74: =AK74+AL73 | AN74: =INDEX($O74:$AL74,1,AN$5*12) | AO74: =INDEX($O74:$AL74,1,AO$5*12)
A76: Pro-forma balance sheet
A77: Cash | B77: GBP k | N77: =N74 | O77: =O74 | P77: =P74 | Q77: =Q74 | R77: =R74 | S77: =S74 | T77: =T74 | U77: =U74 | ... AL77: =AL74 | AN77: =INDEX($O77:$AL77,1,AN$5*12) | AO77: =INDEX($O77:$AL77,1,AO$5*12)
A78: Trade receivables | B78: GBP k | N78: =N19+N37 | O78: =O19+O37 | P78: =P19+P37 | Q78: =Q19+Q37 | R78: =R19+R37 | S78: =S19+S37 | T78: =T19+T37 | U78: =U19+U37 | ... AL78: =AL19+AL37 | AN78: =INDEX($O78:$AL78,1,AN$5*12) | AO78: =INDEX($O78:$AL78,1,AO$5*12)
A79: PP&E | B79: GBP k | N79: =N20+N38 | O79: =O20+O38 | P79: =P20+P38 | Q79: =Q20+Q38 | R79: =R20+R38 | S79: =S20+S38 | T79: =T20+T38 | U79: =U20+U38 | ... AL79: =AL20+AL38 | AN79: =INDEX($O79:$AL79,1,AN$5*12) | AO79: =INDEX($O79:$AL79,1,AO$5*12)
A80: Capitalised contract costs | B80: GBP k | N80: =N21 | O80: =O21 | P80: =P21 | Q80: =Q21 | R80: =R21 | S80: =S21 | T80: =T21 | U80: =U21 | ... AL80: =AL21 | AN80: =INDEX($O80:$AL80,1,AN$5*12) | AO80: =INDEX($O80:$AL80,1,AO$5*12)
A81: Acquired intangibles (net) | B81: GBP k | N81: =inp_ma_include*(MA_PPA!$C$25+MA_PPA!$C$26) | O81: =N81+O62 | P81: =O81+P62 | Q81: =P81+Q62 | R81: =Q81+R62 | S81: =R81+S62 | T81: =S81+T62 | U81: =T81+U62 | V81: =U81+V62 | ... AL81: =AK81+AL62 | AN81: =INDEX($O81:$AL81,1,AN$5*12) | AO81: =INDEX($O81:$AL81,1,AO$5*12)
A82: Goodwill | B82: GBP k | N82: =inp_ma_include*MA_PPA!$C$31 | O82: =N82 | P82: =O82 | Q82: =P82 | R82: =Q82 | S82: =R82 | T82: =S82 | U82: =T82 | V82: =U82 | ... AL82: =AK82 | AN82: =INDEX($O82:$AL82,1,AN$5*12) | AO82: =INDEX($O82:$AL82,1,AO$5*12)
A83: Total assets | B83: GBP k | N83: =SUM(N77:N82) | O83: =SUM(O77:O82) | P83: =SUM(P77:P82) | Q83: =SUM(Q77:Q82) | R83: =SUM(R77:R82) | S83: =SUM(S77:S82) | T83: =SUM(T77:T82) | U83: =SUM(U77:U82) | ... AL83: =SUM(AL77:AL82) | AN83: =INDEX($O83:$AL83,1,AN$5*12) | AO83: =INDEX($O83:$AL83,1,AO$5*12)
A84: Trade payables | B84: GBP k | N84: =N22+N39 | O84: =O22+O39 | P84: =P22+P39 | Q84: =Q22+Q39 | R84: =R22+R39 | S84: =S22+S39 | T84: =T22+T39 | U84: =U22+U39 | ... AL84: =AL22+AL39 | AN84: =INDEX($O84:$AL84,1,AN$5*12) | AO84: =INDEX($O84:$AL84,1,AO$5*12)
A85: Memo: fair-value write-down of acquired deferred revenue still to unwind | B85: GBP k | N85: =inp_ma_include*MA_PPA!$C$24 | O85: =N85+O61 | P85: =O85+P61 | Q85: =P85+Q61 | R85: =Q85+R61 | S85: =R85+S61 | T85: =S85+T61 | U85: =T85+U61 | V85: =U85+V61 | ... AL85: =AK85+AL61 | AN85: =INDEX($O85:$AL85,1,AN$5*12) | AO85: =INDEX($O85:$AL85,1,AO$5*12)
A86: Deferred revenue (net of write-down) | B86: GBP k | N86: =N23+N40-N85 | O86: =O23+O40-O85 | P86: =P23+P40-P85 | Q86: =Q23+Q40-Q85 | R86: =R23+R40-R85 | S86: =S23+S40-S85 | T86: =T23+T40-T85 | U86: =U23+U40-U85 | ... AL86: =AL23+AL40-AL85 | AN86: =INDEX($O86:$AL86,1,AN$5*12) | AO86: =INDEX($O86:$AL86,1,AO$5*12)
A87: Acquisition loan | B87: GBP k | N87: =N64 | O87: =O64 | P87: =P64 | Q87: =Q64 | R87: =R64 | S87: =S64 | T87: =T64 | U87: =U64 | ... AL87: =AL64 | AN87: =INDEX($O87:$AL87,1,AN$5*12) | AO87: =INDEX($O87:$AL87,1,AO$5*12)
A88: Deferred tax liability | B88: GBP k | N88: =-inp_ma_include*MA_PPA!$C$27 | O88: =N88-O63 | P88: =O88-P63 | Q88: =P88-Q63 | R88: =Q88-R63 | S88: =R88-S63 | T88: =S88-T63 | U88: =T88-U63 | V88: =U88-V63 | ... AL88: =AK88-AL63 | AN88: =INDEX($O88:$AL88,1,AN$5*12) | AO88: =INDEX($O88:$AL88,1,AO$5*12)
A89: Total liabilities | B89: GBP k | N89: =N84+N86+N87+N88 | O89: =O84+O86+O87+O88 | P89: =P84+P86+P87+P88 | Q89: =Q84+Q86+Q87+Q88 | R89: =R84+R86+R87+R88 | S89: =S84+S86+S87+S88 | T89: =T84+T86+T87+T88 | U89: =U84+U86+U87+U88 | ... AL89: =AL84+AL86+AL87+AL88 | AN89: =INDEX($O89:$AL89,1,AN$5*12) | AO89: =INDEX($O89:$AL89,1,AO$5*12)
A90: Equity (Northgate opening equity + pro-forma net income) | B90: GBP k | N90: =N24 | O90: =N90+O71 | P90: =O90+P71 | Q90: =P90+Q71 | R90: =Q90+R71 | S90: =R90+S71 | T90: =S90+T71 | U90: =T90+U71 | V90: =U90+V71 | ... AL90: =AK90+AL71 | AN90: =INDEX($O90:$AL90,1,AN$5*12) | AO90: =INDEX($O90:$AL90,1,AO$5*12)
A91: Balance check | B91: GBP k | N91: =N83-N89-N90 | O91: =O83-O89-O90 | P91: =P83-P89-P90 | Q91: =Q83-Q89-Q90 | R91: =R83-R89-R90 | S91: =S83-S89-S90 | T91: =T83-T89-T90 | U91: =U83-U89-U90 | ... AL91: =AL83-AL89-AL90 | AN91: =INDEX($O91:$AL91,1,AN$5*12) | AO91: =INDEX($O91:$AL91,1,AO$5*12)
A93: Pro-forma SaaS metrics
A94: Pro-forma closing ARR | B94: GBP k | N94: =N13+N31+N56 | O94: =O13+O31+O56 | P94: =P13+P31+P56 | Q94: =Q13+Q31+Q56 | R94: =R13+R31+R56 | S94: =S13+S31+S56 | T94: =T13+T31+T56 | U94: =U13+U31+U56 | ... AL94: =AL13+AL31+AL56 | AN94: =INDEX($O94:$AL94,1,AN$5*12) | AO94: =INDEX($O94:$AL94,1,AO$5*12)
A95: Net new ARR | B95: GBP k | O95: =O94-N94 | P95: =P94-O94 | Q95: =Q94-P94 | R95: =R94-Q94 | S95: =S94-R94 | T95: =T94-S94 | U95: =U94-T94 | V95: =V94-U94 | ... AL95: =AL94-AK94 | AN95: =SUMIF($O$5:$AL$5,AN$5,$O95:$AL95) | AO95: =SUMIF($O$5:$AL$5,AO$5,$O95:$AL95)
A96: ARR growth, year on year | B96: % | O96: =IF(O$3<12,"",O94/INDEX($N94:$AL94,1,O$3-12+1)-1) | P96: =IF(P$3<12,"",P94/INDEX($N94:$AL94,1,P$3-12+1)-1) | Q96: =IF(Q$3<12,"",Q94/INDEX($N94:$AL94,1,Q$3-12+1)-1) | R96: =IF(R$3<12,"",R94/INDEX($N94:$AL94,1,R$3-12+1)-1) | S96: =IF(S$3<12,"",S94/INDEX($N94:$AL94,1,S$3-12+1)-1) | T96: =IF(T$3<12,"",T94/INDEX($N94:$AL94,1,T$3-12+1)-1) | U96: =IF(U$3<12,"",U94/INDEX($N94:$AL94,1,U$3-12+1)-1) | V96: =IF(V$3<12,"",V94/INDEX($N94:$AL94,1,V$3-12+1)-1) | ... AL96: =IF(AL$3<12,"",AL94/INDEX($N94:$AL94,1,AL$3-12+1)-1) | AN96: =INDEX($O96:$AL96,1,AN$5*12) | AO96: =INDEX($O96:$AL96,1,AO$5*12)
A97: Net revenue retention (annualised) | B97: % | O97: =(1+(O11+O12+O29+O30)/(O9+O27))^12 | P97: =(1+(P11+P12+P29+P30)/(P9+P27))^12 | Q97: =(1+(Q11+Q12+Q29+Q30)/(Q9+Q27))^12 | R97: =(1+(R11+R12+R29+R30)/(R9+R27))^12 | S97: =(1+(S11+S12+S29+S30)/(S9+S27))^12 | T97: =(1+(T11+T12+T29+T30)/(T9+T27))^12 | U97: =(1+(U11+U12+U29+U30)/(U9+U27))^12 | V97: =(1+(V11+V12+V29+V30)/(V9+V27))^12 | ... AL97: =(1+(AL11+AL12+AL29+AL30)/(AL9+AL27))^12 | AN97: =INDEX($O97:$AL97,1,AN$5*12) | AO97: =INDEX($O97:$AL97,1,AO$5*12)
A98: EBITDA margin | B98: % | O98: =O70/O69 | P98: =P70/P69 | Q98: =Q70/Q69 | R98: =R70/R69 | S98: =S70/S69 | T98: =T70/T69 | U98: =U70/U69 | V98: =V70/V69 | ... AL98: =AL70/AL69 | AN98: =AN70/AN69 | AO98: =AO70/AO69
A99: Rule of 40 | B99: % | O99: =IF(O$3<12,"",O96+O98) | P99: =IF(P$3<12,"",P96+P98) | Q99: =IF(Q$3<12,"",Q96+Q98) | R99: =IF(R$3<12,"",R96+R98) | S99: =IF(S$3<12,"",S96+S98) | T99: =IF(T$3<12,"",T96+T98) | U99: =IF(U$3<12,"",U96+U98) | V99: =IF(V$3<12,"",V96+V98) | ... AL99: =IF(AL$3<12,"",AL96+AL98) | AN99: =INDEX($O99:$AL99,1,AN$5*12) | AO99: =INDEX($O99:$AL99,1,AO$5*12)
A100: Net burn (positive = cash consumed) | B100: GBP k | O100: =-O73 | P100: =-P73 | Q100: =-Q73 | R100: =-R73 | S100: =-S73 | T100: =-T73 | U100: =-U73 | V100: =-V73 | ... AL100: =-AL73 | AN100: =SUMIF($O$5:$AL$5,AN$5,$O100:$AL100) | AO100: =SUMIF($O$5:$AL$5,AO$5,$O100:$AL100)
A101: Burn multiple | B101: x | O101: =IF(O95<=0,"n/a",MAX(0,O100)/O95) | P101: =IF(P95<=0,"n/a",MAX(0,P100)/P95) | Q101: =IF(Q95<=0,"n/a",MAX(0,Q100)/Q95) | R101: =IF(R95<=0,"n/a",MAX(0,R100)/R95) | S101: =IF(S95<=0,"n/a",MAX(0,S100)/S95) | T101: =IF(T95<=0,"n/a",MAX(0,T100)/T95) | U101: =IF(U95<=0,"n/a",MAX(0,U100)/U95) | V101: =IF(V95<=0,"n/a",MAX(0,V100)/V95) | ... AL101: =IF(AL95<=0,"n/a",MAX(0,AL100)/AL95) | AN101: =INDEX($O101:$AL101,1,AN$5*12) | AO101: =INDEX($O101:$AL101,1,AO$5*12)
A102: Cash runway (months at trailing 3m average burn) | B102: months | O102: =IF(AVERAGE(M100:O100)<=0,"n/a",O74/AVERAGE(M100:O100)) | P102: =IF(AVERAGE(N100:P100)<=0,"n/a",P74/AVERAGE(N100:P100)) | Q102: =IF(AVERAGE(O100:Q100)<=0,"n/a",Q74/AVERAGE(O100:Q100)) | R102: =IF(AVERAGE(P100:R100)<=0,"n/a",R74/AVERAGE(P100:R100)) | S102: =IF(AVERAGE(Q100:S100)<=0,"n/a",S74/AVERAGE(Q100:S100)) | T102: =IF(AVERAGE(R100:T100)<=0,"n/a",T74/AVERAGE(R100:T100)) | U102: =IF(AVERAGE(S100:U100)<=0,"n/a",U74/AVERAGE(S100:U100)) | V102: =IF(AVERAGE(T100:V100)<=0,"n/a",V74/AVERAGE(T100:V100)) | ... AL102: =IF(AVERAGE(AJ100:AL100)<=0,"n/a",AL74/AVERAGE(AJ100:AL100)) | AN102: =INDEX($O102:$AL102,1,AN$5*12) | AO102: =INDEX($O102:$AL102,1,AO$5*12)

Sheet Inputs_Comps
A1: Inputs_Comps - illustrative trading comparables (synthetic, fictitious companies)
A2: Typed inputs. Not real market data: for demonstrating the method only.
A4: Peer | B4: EV / ARR | C4: EV / revenue (NTM) | D4: ARR growth
A5: ArchivePoint plc | B5: 5.8 | C5: 5.4 | D5: 0.18
A6: ComplyStream Inc | B6: 7.2 | C6: 6.8 | D6: 0.24
A7: RecordKeep Software | B7: 3.9 | C7: 3.6 | D7: 0.1
A8: SurveilCore Ltd | B8: 6.5 | C8: 6 | D8: 0.21
A9: Datavault Group | B9: 4.4 | C9: 4.1 | D9: 0.12
A10: Regulyx | B10: 5.1 | C10: 4.8 | D10: 0.15
A12: Minimum | B12: =MIN(B5:B10) | C12: =MIN(C5:C10) | D12: =MIN(D5:D10)
A13: Average | B13: =AVERAGE(B5:B10) | C13: =AVERAGE(C5:C10) | D13: =AVERAGE(D5:D10)
A14: Maximum | B14: =MAX(B5:B10) | C14: =MAX(C5:C10) | D14: =MAX(D5:D10)
A16: Vaultline's own growth is lower than most peers, which argues for the lower half of the range.

Sheet MA_Valuation
A1: MA_Valuation - Vaultline: DCF, trading comps, offer range and football field
A2: GBP thousands unless stated. Years 1-2 from MA_Target; years 3-5 fade growth by inp_ma_fade with free cash flow margin held at year 2.
A4: Vaultline standalone DCF | B4: Unit | C4: ="FY"&(YEAR(inp_model_start)+C5-1) | D4: ="FY"&(YEAR(inp_model_start)+D5-1) | E4: ="FY"&(YEAR(inp_model_start)+E5-1) | F4: ="FY"&(YEAR(inp_model_start)+F5-1) | G4: ="FY"&(YEAR(inp_model_start)+G5-1)
A5: Year index | C5: =COLUMN()-COLUMN($B$1) | D5: =COLUMN()-COLUMN($B$1) | E5: =COLUMN()-COLUMN($B$1) | F5: =COLUMN()-COLUMN($B$1) | G5: =COLUMN()-COLUMN($B$1)
A6: Opening ARR | B6: GBP k | C6: =MA_Target!AN13 | D6: =MA_Target!AO13 | E6: =D8 | F6: =E8 | G6: =F8
A7: ARR growth | B7: % | C7: =C8/C6-1 | D7: =D8/D6-1 | E7: =D7-inp_ma_fade | F7: =E7-inp_ma_fade | G7: =F7-inp_ma_fade
A8: Closing ARR | B8: GBP k | C8: =MA_Target!AN17 | D8: =MA_Target!AO17 | E8: =E6*(1+E7) | F8: =F6*(1+F7) | G8: =G6*(1+G7)
A9: Revenue | B9: GBP k | C9: =MA_Target!AN23 | D9: =MA_Target!AO23 | E9: =D9*E8/D8 | F9: =E9*F8/E8 | G9: =F9*G8/F8
A10: EBITDA | B10: GBP k | C10: =MA_Target!AN36 | D10: =MA_Target!AO36 | E10: =E9*D10/D9 | F10: =F9*E10/E9 | G10: =G9*F10/F9
A11: Unlevered FCF margin (held at year 2 from year 3) | B11: % | C11: =C12/C9 | D11: =D12/D9 | E11: =D11 | F11: =E11 | G11: =F11
A12: Unlevered free cash flow | B12: GBP k | C12: =MA_Target!AN69 | D12: =MA_Target!AO69 | E12: =E9*E11 | F12: =F9*F11 | G12: =G9*G11
A14: DCF cases (low = WACC +1pt and growth -0.5pt; high = WACC -1pt and growth +0.5pt)
B15: Unit | C15: Low | D15: Base | E15: High
A16: Discount rate (WACC) | C16: =inp_ma_wacc+inp_ma_wacc_band | D16: =inp_ma_wacc | E16: =inp_ma_wacc-inp_ma_wacc_band
A17: Terminal growth | C17: =inp_ma_tg-inp_ma_tg_band | D17: =inp_ma_tg | E17: =inp_ma_tg+inp_ma_tg_band
A18: Discount factor, low case | C18: =1/(1+$C$16)^C$5 | D18: =1/(1+$C$16)^D$5 | E18: =1/(1+$C$16)^E$5 | F18: =1/(1+$C$16)^F$5 | G18: =1/(1+$C$16)^G$5
A19: Discount factor, base case | C19: =1/(1+$D$16)^C$5 | D19: =1/(1+$D$16)^D$5 | E19: =1/(1+$D$16)^E$5 | F19: =1/(1+$D$16)^F$5 | G19: =1/(1+$D$16)^G$5
A20: Discount factor, high case | C20: =1/(1+$E$16)^C$5 | D20: =1/(1+$E$16)^D$5 | E20: =1/(1+$E$16)^E$5 | F20: =1/(1+$E$16)^F$5 | G20: =1/(1+$E$16)^G$5
A21: Present value of years 1-5 cash flows | C21: =SUMPRODUCT($C$12:$G$12,$C$18:$G$18) | D21: =SUMPRODUCT($C$12:$G$12,$C$19:$G$19) | E21: =SUMPRODUCT($C$12:$G$12,$C$20:$G$20)
A22: Terminal value (Gordon growth on year 5) | C22: =$G$12*(1+C17)/(C16-C17) | D22: =$G$12*(1+D17)/(D16-D17) | E22: =$G$12*(1+E17)/(E16-E17)
A23: Present value of terminal value | C23: =C22*$G$18 | D23: =D22*$G$19 | E23: =E22*$G$20
A24: Enterprise value (DCF) | C24: =C21+C23 | D24: =D21+D23 | E24: =E21+E23
A25: Terminal value as % of EV (base) | D25: =D23/D24
A27: Trading comps applied to Vaultline (Inputs_Comps)
B28: Unit | C28: Low (min) | D28: Mid (average) | E28: High (max)
A29: EV / ARR multiple | C29: =Inputs_Comps!B12 | D29: =Inputs_Comps!B13 | E29: =Inputs_Comps!B14
A30: Implied EV from ARR | C30: =C29*MA_PPA!$C$6 | D30: =D29*MA_PPA!$C$6 | E30: =E29*MA_PPA!$C$6
A31: EV / revenue multiple (NTM) | C31: =Inputs_Comps!C12 | D31: =Inputs_Comps!C13 | E31: =Inputs_Comps!C14
A32: Implied EV from FY1 revenue | C32: =C31*C9 | D32: =D31*C9 | E32: =E31*C9
A34: Offer
B35: Unit | C35: Low | D35: Offer | E35: High
A36: EV / ARR (offer -0.5x / offer / +0.5x) | C36: =inp_ma_offer_mult-0.5 | D36: =inp_ma_offer_mult | E36: =inp_ma_offer_mult+0.5
A37: Enterprise value | C37: =C36*MA_PPA!$C$6 | D37: =D36*MA_PPA!$C$6 | E37: =E36*MA_PPA!$C$6
A38: Equity purchase price (EV + cash acquired) | C38: =C37+MA_PPA!$C$9 | D38: =D37+MA_PPA!$C$9 | E38: =E37+MA_PPA!$C$9
A39: Implied EV / FY1 revenue | C39: =C37/$C$9 | D39: =D37/$C$9 | E39: =E37/$C$9
A40: Implied EV / FY1 EBITDA | C40: =C37/$C$10 | D40: =D37/$C$10 | E40: =E37/$C$10
A42: Football field: enterprise value (GBP m)
A43: Method | C43: Low | D43: Mid | E43: High | F43: Spread
A44: DCF (WACC +/-1pt, growth +/-0.5pt) | C44: =MA_Valuation!$C$24/1000 | D44: =MA_Valuation!$D$24/1000 | E44: =MA_Valuation!$E$24/1000 | F44: =E44-C44
A45: DCF plus net synergies (50% / achieved / 100%) | C45: =(MA_Valuation!$C$24+0.5*MA_Returns!C20-MA_Returns!C22)/1000 | D45: =(MA_Valuation!$D$24+MA_Returns!C21-MA_Returns!C22)/1000 | E45: =(MA_Valuation!$E$24+MA_Returns!C20-MA_Returns!C22)/1000 | F45: =E45-C45
A46: Trading comps: EV / ARR | C46: =C30/1000 | D46: =D30/1000 | E46: =E30/1000 | F46: =E46-C46
A47: Trading comps: EV / FY1 revenue | C47: =C32/1000 | D47: =D32/1000 | E47: =E32/1000 | F47: =E47-C47
A48: Offer range (+/-0.5x ARR) | C48: =C37/1000 | D48: =D37/1000 | E48: =E37/1000 | F48: =E48-C48

Sheet MA_Returns
